Workbook
Name A: #REF!
Name B: #REF!
Name d: #REF!
Name e: #REF!
Name f: #REF!
Name g: #REF!
Name h: #REF!
Name IQRThomsonEstM343: #REF!
Name IQRThomsonEstM344: #REF!
Name IQRThomsonEstM345: #REF!
Name IQRThomsonEstM346: #REF!
Name IQRThomsonEstM347: #REF!
Name IQRThomsonEstM348: #REF!
Name IQRThomsonEstM351: #REF!
Name IQRThomsonEstM352: #REF!
Name IQRThomsonEstM365: #REF!
Name IQRThomsonEstM366: #REF!
Name IQRThomsonEstM373: #REF!
Name IQRThomsonEstM374: #REF!
Name IQRThomsonEstM375: #REF!
Name IQRThomsonEstM376: #REF!
Name IQRThomsonEstM377: #REF!
Name IQRThomsonEstM378: #REF!
Name IQRThomsonEstM387: #REF!
Name IQRThomsonEstM388: #REF!
Name IQRThomsonEstM395: #REF!
Name IQRThomsonEstM396: #REF!
Name IQRThomsonEstM419: #REF!
Name IQRThomsonEstM420: #REF!

Sheet Instructions
A7: Building your Plan
B8: Performance Tab: | D8: A summary of the Bottoms Up Model vs your actual results on revenue and Leading Indicators of Unit Economics.
B10: Model Assumptions Tab: | D10: Fill in the BLUE numbers in the Model Assumptions column. These will populate in the monthly assumptions columns.
D11: We recommend you start with your current results to get a baseline model.
B13: GTM Bottoms Up Model: | D13: Add your headcount including ramp for your AEs and SDRs
D14: Everything else will populate based on your inputs from the Model Assumptions tab.
B15: LIR: | D15: A worksheet to track your Leading Indicator of Retention.
A18: Definitions | C18: You can change these to whatever language you use internally.
B19: TOFU | C19: Top of funnel leads
B20: Contacts | C20: A Contact in an accounts prospected for outbound
B21: MQL | C21: Marketing Qualified Lead for inbound leads
B22: SQL | C22: Sales Qualified lead - qualified opportunities you add to your pipeline
B23: ACV | C23: Average 1 year contract value

Sheet Performance Plan vs. Actual
A1: 2024 Plan
A2: Fill in the cells in yellow | O2: 2025
B3: 45658 | C3: =EDATE(B3,1) -> 45689 | D3: =EDATE(C3,1) -> 45717 | E3: =EDATE(D3,1) -> 45748 | F3: =EDATE(E3,1) -> 45778 | G3: =EDATE(F3,1) -> 45809 | H3: =EDATE(G3,1) -> 45839 | I3: =EDATE(H3,1) -> 45870 | J3: =EDATE(I3,1) -> 45901 | ... M3: =EDATE(L3,1) -> 45992 | O3: Q1 | P3: Q2 | Q3: Q3 | R3: Q4 | S3: TOTAL
A4: Revenue
A5: Starting ARR | B5: 0 | C5: =B10 -> 63000 | D5: =C10 -> 124740 | E5: =D10 -> 185245.2 | F5: =E10 -> 274540.3 | G5: =F10 -> 362049.49 | H5: =G10 -> 447808.5 | I5: =H10 -> 571227.33 | J5: =I10 -> 725927.78 | ... M5: =L10 -> 1321793.1
A6: New | B6: ='GTM Bottoms up Model'!B30 -> 60000 | C6: ='GTM Bottoms up Model'!C30 -> 60000 | D6: ='GTM Bottoms up Model'!D30 -> 60000 | E6: ='GTM Bottoms up Model'!E30 -> 90000 | F6: ='GTM Bottoms up Model'!F30 -> 90000 | G6: ='GTM Bottoms up Model'!G30 -> 90000 | H6: ='GTM Bottoms up Model'!H30 -> 129375 | I6: ='GTM Bottoms up Model'!I30 -> 163125 | ... M6: ='GTM Bottoms up Model'!M30 -> 241875 | O6: =SUM(B6:D6) -> 180000 | P6: =SUM(E6:G6) -> 270000 | Q6: =SUM(H6:J6) -> 472500 | R6: =SUM(K6:M6) -> 703125 | S6: =SUM(O6:R6) -> 1625625
A7: Expansion | B7: ='GTM Bottoms up Model'!B32 -> 6000 | C7: ='GTM Bottoms up Model'!C32 -> 6000 | D7: ='GTM Bottoms up Model'!D32 -> 6000 | E7: ='GTM Bottoms up Model'!E32 -> 6000 | F7: ='GTM Bottoms up Model'!F32 -> 6000 | G7: ='GTM Bottoms up Model'!G32 -> 6000 | H7: ='GTM Bottoms up Model'!H32 -> 6000 | I7: ='GTM Bottoms up Model'!I32 -> 6000 | ... M7: ='GTM Bottoms up Model'!M32 -> 6000 | O7: =SUM(B7:D7) -> 18000 | P7: =SUM(E7:G7) -> 18000 | Q7: =SUM(H7:J7) -> 18000 | R7: =SUM(K7:M7) -> 18000 | S7: =SUM(O7:R7) -> 72000
A8: Contraction | B8: -3000 | C8: -3000 | D8: -3000 | E8: -3000 | F8: -3000 | G8: -3000 | H8: -3000 | I8: -3000 | J8: -3000 | K8: -3000 | L8: -3000 | M8: -3000
A9: Churn | B9: =-SUM(B5*0.02) -> 0 | C9: =-SUM(C5*0.02) -> -1260 | D9: =-SUM(D5*0.02) -> -2494.8 | E9: =-SUM(E5*0.02) -> -3704.904 | F9: =-SUM(F5*0.02) -> -5490.8059 | G9: =-SUM(G5*0.02) -> -7240.9898 | H9: =-SUM(H5*0.02) -> -8956.17 | I9: =-SUM(I5*0.02) -> -11424.547 | ... M9: =-SUM(M5*0.02) -> -26435.862
A10: Total | B10: =SUM(B5:B9) -> 63000 | C10: =SUM(C5:C9) -> 124740 | D10: =SUM(D5:D9) -> 185245.2 | E10: =SUM(E5:E9) -> 274540.3 | F10: =SUM(F5:F9) -> 362049.49 | G10: =SUM(G5:G9) -> 447808.5 | H10: =SUM(H5:H9) -> 571227.33 | I10: =SUM(I5:I9) -> 725927.78 | ... M10: =SUM(M5:M9) -> 1540232.3 | O10: =SUM(B10:D10) -> 372985.2 | P10: =SUM(E10:G10) -> 1084398.3 | Q10: =SUM(H10:J10) -> 2191564.3 | R10: =SUM(K10:M10) -> 3960921.4 | S10: =SUM(O10:R10) -> 7609869.3
A11: New Customers | B11: ='GTM Bottoms up Model'!B29 -> 4 | C11: ='GTM Bottoms up Model'!C29 -> 4 | D11: ='GTM Bottoms up Model'!D29 -> 4 | E11: ='GTM Bottoms up Model'!E29 -> 4 | F11: ='GTM Bottoms up Model'!F29 -> 4 | G11: ='GTM Bottoms up Model'!G29 -> 4 | H11: ='GTM Bottoms up Model'!H29 -> 5.75 | I11: ='GTM Bottoms up Model'!I29 -> 7.25 | ... M11: ='GTM Bottoms up Model'!M29 -> 10.75 | O11: =SUM(B11:D11) -> 12 | P11: =SUM(E11:G11) -> 12 | Q11: =SUM(H11:J11) -> 21 | R11: =SUM(K11:M11) -> 31.25 | S11: =SUM(O11:R11) -> 76.25
A12: CaC payback (months) | B12: ='GTM Bottoms up Model'!B123 -> 9.570412 | C12: ='GTM Bottoms up Model'!C123 -> 9.570412 | D12: ='GTM Bottoms up Model'!D123 -> 9.570412 | E12: ='GTM Bottoms up Model'!E123 -> 10.746325 | F12: ='GTM Bottoms up Model'!F123 -> 10.746325 | G12: ='GTM Bottoms up Model'!G123 -> 12.048408 | H12: ='GTM Bottoms up Model'!H123 -> 10.412228 | I12: ='GTM Bottoms up Model'!I123 -> 8.3491384 | ... M12: ='GTM Bottoms up Model'!M123 -> 7.7372237 | O12: =AVERAGE(B12:D12) -> 9.570412 | P12: =AVERAGE(E12:G12) -> 11.180353 | Q12: =AVERAGE(H12:J12) -> 9.2346031 | R12: =AVERAGE(K12:M12) -> 7.6224901
A13: S/M expense as a % of Revenue | B13: ='GTM Bottoms up Model'!B124 -> 0.63802747 | C13: ='GTM Bottoms up Model'!C124 -> 0.63802747 | D13: ='GTM Bottoms up Model'!D124 -> 0.63802747 | E13: ='GTM Bottoms up Model'!E124 -> 0.71642166 | F13: ='GTM Bottoms up Model'!F124 -> 0.71642166 | G13: ='GTM Bottoms up Model'!G124 -> 0.80322722 | H13: ='GTM Bottoms up Model'!H124 -> 0.69414852 | I13: ='GTM Bottoms up Model'!I124 -> 0.55660923 | ... M13: ='GTM Bottoms up Model'!M124 -> 0.51581491 | O13: =AVERAGE(B13:D13) -> 0.63802747 | P13: =AVERAGE(E13:G13) -> 0.74535685 | Q13: =AVERAGE(H13:J13) -> 0.6156402 | R13: =AVERAGE(K13:M13) -> 0.50816601
A15: Demand Gen - SQLs by Channel
A16: Outbound | B16: ='GTM Bottoms up Model'!B45 -> 2.2503516 | C16: ='GTM Bottoms up Model'!C45 -> 2.2503516 | D16: ='GTM Bottoms up Model'!D45 -> 2.2503516 | E16: ='GTM Bottoms up Model'!E45 -> 2.2503516 | F16: ='GTM Bottoms up Model'!F45 -> 2.2503516 | G16: ='GTM Bottoms up Model'!G45 -> 2.2503516 | H16: ='GTM Bottoms up Model'!H45 -> 3.2348805 | I16: ='GTM Bottoms up Model'!I45 -> 4.0787623 | ... M16: ='GTM Bottoms up Model'!M45 -> 6.04782 | O16: =SUM(B16:D16) -> 6.7510549 | P16: =SUM(E16:G16) -> 6.7510549 | Q16: =SUM(H16:J16) -> 11.814346 | R16: =SUM(K16:M16) -> 17.580872 | S16: =SUM(O16:R16) -> 42.897328
A17: Inbound | B17: ='GTM Bottoms up Model'!B59 -> 9.0014065 | C17: ='GTM Bottoms up Model'!C59 -> 9.0014065 | D17: ='GTM Bottoms up Model'!D59 -> 9.0014065 | E17: ='GTM Bottoms up Model'!E59 -> 9.0014065 | F17: ='GTM Bottoms up Model'!F59 -> 9.0014065 | G17: ='GTM Bottoms up Model'!G59 -> 9.0014065 | H17: ='GTM Bottoms up Model'!H59 -> 12.939522 | I17: ='GTM Bottoms up Model'!I59 -> 16.315049 | ... M17: ='GTM Bottoms up Model'!M59 -> 24.19128 | O17: =SUM(B17:D17) -> 27.004219 | P17: =SUM(E17:G17) -> 27.004219 | Q17: =SUM(H17:J17) -> 47.257384 | R17: =SUM(K17:M17) -> 70.323488 | S17: =SUM(O17:R17) -> 171.58931
A18: Partner | B18: ='GTM Bottoms up Model'!B70 -> 0 | C18: ='GTM Bottoms up Model'!C70 -> 0 | D18: ='GTM Bottoms up Model'!D70 -> 0 | E18: ='GTM Bottoms up Model'!E70 -> 0 | F18: ='GTM Bottoms up Model'!F70 -> 0 | G18: ='GTM Bottoms up Model'!G70 -> 0 | H18: ='GTM Bottoms up Model'!H70 -> 0 | I18: ='GTM Bottoms up Model'!I70 -> 0 | ... M18: ='GTM Bottoms up Model'!M70 -> 0 | O18: =SUM(B18:D18) -> 0 | P18: =SUM(E18:G18) -> 0 | Q18: =SUM(H18:J18) -> 0 | R18: =SUM(K18:M18) -> 0 | S18: =SUM(O18:R18) -> 0
A19: Total | B19: =SUM(B16:B18) -> 11.251758 | C19: =SUM(C16:C18) -> 11.251758 | D19: =SUM(D16:D18) -> 11.251758 | E19: =SUM(E16:E18) -> 11.251758 | F19: =SUM(F16:F18) -> 11.251758 | G19: =SUM(G16:G18) -> 11.251758 | H19: =SUM(H16:H18) -> 16.174402 | I19: =SUM(I16:I18) -> 20.393812 | ... M19: =SUM(M16:M18) -> 30.2391 | O19: =SUM(B19:D19) -> 33.755274 | P19: =SUM(E19:G19) -> 33.755274 | Q19: =SUM(H19:J19) -> 59.07173 | R19: =SUM(K19:M19) -> 87.90436 | S19: =SUM(O19:R19) -> 214.48664
A21: Leading Indicators of Unit Economics
A22: SQLs per Rep | B22: ='GTM Bottoms up Model'!B126 -> 5.625879 | C22: ='GTM Bottoms up Model'!C126 -> 5.625879 | D22: ='GTM Bottoms up Model'!D126 -> 5.625879 | E22: ='GTM Bottoms up Model'!E126 -> 5.625879 | F22: ='GTM Bottoms up Model'!F126 -> 5.625879 | G22: ='GTM Bottoms up Model'!G126 -> 5.625879 | H22: ='GTM Bottoms up Model'!H126 -> 5.3914674 | I22: ='GTM Bottoms up Model'!I126 -> 6.7979372 | ... M22: ='GTM Bottoms up Model'!M126 -> 6.04782 | O22: =AVERAGE(B22:D22) -> 5.625879 | P22: =AVERAGE(E22:G22) -> 5.625879 | Q22: =AVERAGE(H22:J22) -> 5.9384279 | R22: =AVERAGE(K22:M22) -> 6.3173933 | S22: =AVERAGE(O22:R22) -> 5.8768948
A23: Deals per Rep | B23: ='GTM Bottoms up Model'!B127 -> 2 | C23: ='GTM Bottoms up Model'!C127 -> 2 | D23: ='GTM Bottoms up Model'!D127 -> 2 | E23: ='GTM Bottoms up Model'!E127 -> 2 | F23: ='GTM Bottoms up Model'!F127 -> 2 | G23: ='GTM Bottoms up Model'!G127 -> 2 | H23: ='GTM Bottoms up Model'!H127 -> 2.5 | I23: ='GTM Bottoms up Model'!I127 -> 2.5 | ... M23: ='GTM Bottoms up Model'!M127 -> 2.5 | O23: =AVERAGE(B23:D23) -> 2 | P23: =AVERAGE(E23:G23) -> 2 | Q23: =AVERAGE(H23:J23) -> 2.5 | R23: =AVERAGE(K23:M23) -> 2.5 | S23: =AVERAGE(O23:R23) -> 2.25
A24: ACV | B24: ='GTM Bottoms up Model'!B128 -> 15000 | C24: ='GTM Bottoms up Model'!C128 -> 15000 | D24: ='GTM Bottoms up Model'!D128 -> 15000 | E24: ='GTM Bottoms up Model'!E128 -> 22500 | F24: ='GTM Bottoms up Model'!F128 -> 22500 | G24: ='GTM Bottoms up Model'!G128 -> 22500 | H24: ='GTM Bottoms up Model'!H128 -> 22500 | I24: ='GTM Bottoms up Model'!I128 -> 22500 | ... M24: ='GTM Bottoms up Model'!M128 -> 22500 | O24: =AVERAGE(B24:D24) -> 15000 | P24: =AVERAGE(E24:G24) -> 22500 | Q24: =AVERAGE(H24:J24) -> 22500 | R24: =AVERAGE(K24:M24) -> 22500 | S24: =AVERAGE(O24:R24) -> 20625
A25: CAC per Customer | B25: ='GTM Bottoms up Model'!B130 -> 10527.453 | C25: ='GTM Bottoms up Model'!C130 -> 10527.453 | D25: ='GTM Bottoms up Model'!D130 -> 10527.453 | E25: ='GTM Bottoms up Model'!E130 -> 17194.12 | F25: ='GTM Bottoms up Model'!F130 -> 17194.12 | G25: ='GTM Bottoms up Model'!G130 -> 19277.453 | H25: ='GTM Bottoms up Model'!H130 -> 16342.671 | I25: ='GTM Bottoms up Model'!I130 -> 12984.35 | ... M25: ='GTM Bottoms up Model'!M130 -> 11893.732 | O25: =AVERAGE(B25:D25) -> 10527.453 | P25: =AVERAGE(E25:G25) -> 17888.564 | Q25: =AVERAGE(H25:J25) -> 14395.936 | R25: =AVERAGE(K25:M25) -> 11726.767 | S25: =AVERAGE(O25:R25) -> 13634.68
A27: Headcount
A28: AE | B28: =ROUNDUP('GTM Bottoms up Model'!B19,0) -> 2 | C28: =ROUNDUP('GTM Bottoms up Model'!C19,0) -> 2 | D28: =ROUNDUP('GTM Bottoms up Model'!D19,0) -> 2 | E28: 1 | F28: =ROUNDUP('GTM Bottoms up Model'!F19,0) -> 2 | G28: =ROUNDUP('GTM Bottoms up Model'!G19,0) -> 2 | H28: =ROUNDUP('GTM Bottoms up Model'!H19,0) -> 3 | I28: =ROUNDUP('GTM Bottoms up Model'!I19,0) -> 3 | J28: =ROUNDUP('GTM Bottoms up Model'!J19,0) -> 4 | K28: =ROUNDUP('GTM Bottoms up Model'!K19,0) -> 4 | L28: =ROUNDUP('GTM Bottoms up Model'!L19,0) -> 5 | M28: =ROUNDUP('GTM Bottoms up Model'!M19,0) -> 5 | O28: =D28 -> 2 | P28: =G28 -> 2 | Q28: =J28 -> 4 | R28: =M28 -> 5 | S28: =R28 -> 5
A29: CS | B29: =ROUNDUP('GTM Bottoms up Model'!B20,0) -> 1 | C29: =ROUNDUP('GTM Bottoms up Model'!C20,0) -> 1 | D29: =ROUNDUP('GTM Bottoms up Model'!D20,0) -> 1 | E29: =ROUNDUP('GTM Bottoms up Model'!E20,0) -> 1 | F29: =ROUNDUP('GTM Bottoms up Model'!F20,0) -> 1 | G29: =ROUNDUP('GTM Bottoms up Model'!G20,0) -> 1 | H29: =ROUNDUP('GTM Bottoms up Model'!H20,0) -> 1 | I29: =ROUNDUP('GTM Bottoms up Model'!I20,0) -> 1 | ... M29: =ROUNDUP('GTM Bottoms up Model'!M20,0) -> 1 | O29: =D29 -> 1 | P29: =G29 -> 1 | Q29: =J29 -> 1 | R29: =M29 -> 1 | S29: =R29 -> 1
A30: SDR | B30: =ROUNDUP('GTM Bottoms up Model'!B21,0) -> 1 | C30: =ROUNDUP('GTM Bottoms up Model'!C21,0) -> 1 | D30: =ROUNDUP('GTM Bottoms up Model'!D21,0) -> 1 | E30: =ROUNDUP('GTM Bottoms up Model'!E21,0) -> 1 | F30: =ROUNDUP('GTM Bottoms up Model'!F21,0) -> 1 | G30: =ROUNDUP('GTM Bottoms up Model'!G21,0) -> 2 | H30: =ROUNDUP('GTM Bottoms up Model'!H21,0) -> 2 | I30: =ROUNDUP('GTM Bottoms up Model'!I21,0) -> 2 | ... M30: =ROUNDUP('GTM Bottoms up Model'!M21,0) -> 2 | O30: =D30 -> 1 | P30: =G30 -> 2 | Q30: =J30 -> 2 | R30: =M30 -> 2 | S30: =R30 -> 2
A31: Total | B31: =SUM(B28:B30) -> 4 | C31: =SUM(C28:C30) -> 4 | D31: =SUM(D28:D30) -> 4 | E31: =SUM(E28:E30) -> 3 | F31: =SUM(F28:F30) -> 4 | G31: =SUM(G28:G30) -> 5 | H31: =SUM(H28:H30) -> 6 | I31: =SUM(I28:I30) -> 6 | ... M31: =SUM(M28:M30) -> 8 | O31: =D31 -> 4 | P31: =G31 -> 5 | Q31: =J31 -> 7 | R31: =M31 -> 8 | S31: =R31 -> 8
A33: Cash
A34: Beginning Balance
A35: Change in Cash
A36: Ending Balance
A37: Runway | B37: =IFERROR((B36/B35)*12,"NA") -> NA | C37: =IFERROR((C36/C35)*12,"NA") -> NA | D37: =IFERROR((D36/D35)*12,"NA") -> NA | E37: =IFERROR((E36/E35)*12,"NA") -> NA | F37: =IFERROR((F36/F35)*12,"NA") -> NA | G37: =IFERROR((G36/G35)*12,"NA") -> NA | H37: =IFERROR((H36/H35)*12,"NA") -> NA | I37: =IFERROR((I36/I35)*12,"NA") -> NA | ... M37: =IFERROR((M36/M35)*12,"NA") -> NA
A39: ACTUAL
A40: Fill in the cells in yellow
A42: Revenue
A43: Starting ARR | C43: =B48 -> 0 | D43: =C48 -> 0 | E43: =D48 -> 0 | F43: =E48 -> 0 | G43: =F48 -> 0 | H43: =G48 -> 0 | I43: =H48 -> 0 | J43: =I48 -> 0 | ... M43: =L48 -> 0
A44: New
A45: Expansion
A46: Contraction
A47: Churn
A48: Total | B48: =SUM(B43:B47) -> 0 | C48: =SUM(C43:C47) -> 0 | D48: =SUM(D43:D47) -> 0 | E48: =SUM(E43:E47) -> 0 | F48: =SUM(F43:F47) -> 0 | G48: =SUM(G43:G47) -> 0 | H48: =SUM(H43:H47) -> 0 | I48: =SUM(I43:I47) -> 0 | ... M48: =SUM(M43:M47) -> 0
A49: % to plan | B49: =B48/B10 -> 0 | C49: =C48/C10 -> 0 | D49: =D48/D10 -> 0 | E49: =E48/E10 -> 0 | F49: =F48/F10 -> 0 | G49: =G48/G10 -> 0 | H49: =H48/H10 -> 0 | I49: =I48/I10 -> 0 | ... M49: =M48/M10 -> 0
A50: NRR
A51: Gross Margin
A52: New Customers
A53: S&M Spend (CAC)
A54: CaC payback (months) | B54: =SUM(B53/((B44/12)*B51)) -> #DIV/0! | C54: =SUM(C53/((C44/12)*C51)) -> #DIV/0! | D54: =SUM(D53/((D44/12)*D51)) -> #DIV/0! | E54: =SUM(E53/((E44/12)*E51)) -> #DIV/0! | F54: =SUM(F53/((F44/12)*F51)) -> #DIV/0! | G54: =SUM(G53/((G44/12)*G51)) -> #DIV/0! | H54: =SUM(H53/((H44/12)*H51)) -> #DIV/0! | I54: =SUM(I53/((I44/12)*I51)) -> #DIV/0! | ... M54: =SUM(M53/((M44/12)*M51)) -> #DIV/0!
A55: S/M expense as a % of Revenue | B55: =B53/B48 -> #DIV/0! | C55: =C53/C48 -> #DIV/0! | D55: =D53/D48 -> #DIV/0! | E55: =E53/E48 -> #DIV/0! | F55: =F53/F48 -> #DIV/0! | G55: =G53/G48 -> #DIV/0! | H55: =H53/H48 -> #DIV/0! | I55: =I53/I48 -> #DIV/0! | ... M55: =M53/M48 -> #DIV/0!
A57: Demand Gen - SQLs by Channel
A58: Outbound
A59: Inbound
A60: Partner
A61: Total | B61: =SUM(B58:B60) -> 0 | C61: =SUM(C58:C60) -> 0 | D61: =SUM(D58:D60) -> 0 | E61: =SUM(E58:E60) -> 0 | F61: =SUM(F58:F60) -> 0 | G61: =SUM(G58:G60) -> 0 | H61: =SUM(H58:H60) -> 0 | I61: =SUM(I58:I60) -> 0 | ... M61: =SUM(M58:M60) -> 0
A62: % to plan | B62: =B61/B19 -> 0 | C62: =C61/C19 -> 0 | D62: =D61/D19 -> 0 | E62: =E61/E19 -> 0 | F62: =F61/F19 -> 0 | G62: =G61/G19 -> 0 | H62: =H61/H19 -> 0 | I62: =I61/I19 -> 0 | ... M62: =M61/M19 -> 0
A63: Leading Indicators of Unit Economics
A64: SQLs per Rep | B64: =B61/B70 -> #DIV/0! | C64: =C61/C70 -> #DIV/0! | D64: =D61/D70 -> #DIV/0! | E64: =E61/E70 -> #DIV/0! | F64: =F61/F70 -> #DIV/0! | G64: =G61/G70 -> #DIV/0! | H64: =H61/H70 -> #DIV/0! | I64: =I61/I70 -> #DIV/0! | ... M64: =M61/M70 -> #DIV/0!
A65: Deals per Rep | B65: =B52/B70 -> #DIV/0! | C65: =C52/C70 -> #DIV/0! | D65: =D52/D70 -> #DIV/0! | E65: =E52/E70 -> #DIV/0! | F65: =F52/F70 -> #DIV/0! | G65: =G52/G70 -> #DIV/0! | H65: =H52/H70 -> #DIV/0! | I65: =I52/I70 -> #DIV/0! | ... M65: =M52/M70 -> #DIV/0!
A66: ACV | B66: =B44/B52 -> #DIV/0! | C66: =C44/C52 -> #DIV/0! | D66: =D44/D52 -> #DIV/0! | E66: =E44/E52 -> #DIV/0! | F66: =F44/F52 -> #DIV/0! | G66: =G44/G52 -> #DIV/0! | H66: =H44/H52 -> #DIV/0! | I66: =I44/I52 -> #DIV/0! | ... M66: =M44/M52 -> #DIV/0!
A67: CAC per Customer | B67: =B53/B52 -> #DIV/0! | C67: =C53/C52 -> #DIV/0! | D67: =D53/D52 -> #DIV/0! | E67: =E53/E52 -> #DIV/0! | F67: =F53/F52 -> #DIV/0! | G67: =G53/G52 -> #DIV/0! | H67: =H53/H52 -> #DIV/0! | I67: =I53/I52 -> #DIV/0! | ... M67: =M53/M52 -> #DIV/0!
A69: Headcount
A70: AE
A71: CS
A72: SDR
A73: Total | B73: =SUM(B70:B72) -> 0 | C73: =SUM(C70:C72) -> 0 | D73: =SUM(D70:D72) -> 0 | E73: =SUM(E70:E72) -> 0 | F73: =SUM(F70:F72) -> 0 | G73: =SUM(G70:G72) -> 0 | H73: =SUM(H70:H72) -> 0 | I73: =SUM(I70:I72) -> 0 | ... M73: =SUM(M70:M72) -> 0
A74: % to plan | B74: =B73/B31 -> 0 | C74: =C73/C31 -> 0 | D74: =D73/D31 -> 0 | E74: =E73/E31 -> 0 | F74: =F73/F31 -> 0 | G74: =G73/G31 -> 0 | H74: =H73/H31 -> 0 | I74: =I73/I31 -> 0 | ... M74: =M73/M31 -> 0
A76: Cash
A77: Beginning Balance | C77: =B79 -> 0 | D77: =C79 -> 0 | E77: =D79 -> 0 | F77: =E79 -> 0 | G77: =F79 -> 0 | H77: =G79 -> 0 | I77: =H79 -> 0 | J77: =I79 -> 0 | ... M77: =L79 -> 0
A78: Change in Cash
A79: Ending Balance | B79: =SUM(B77:B78) -> 0 | C79: =SUM(C77:C78) -> 0
A80: Runway | B80: =IFERROR((B79/-B78)*12,"NA") -> NA | C80: =IFERROR((C79/-C78)*12,"NA") -> NA | D80: =IFERROR((D79/-D78)*12,"NA") -> NA | E80: =IFERROR((E79/-E78)*12,"NA") -> NA | F80: =IFERROR((F79/-F78)*12,"NA") -> NA | G80: =IFERROR((G79/-G78)*12,"NA") -> NA | H80: =IFERROR((H79/-H78)*12,"NA") -> NA | I80: =IFERROR((I79/-I78)*12,"NA") -> NA | ... M80: =IFERROR((M79/-M78)*12,"NA") -> NA
A81: % to plan

Sheet Model Assumptions
A1: Exchange | B1: 1.4
B2: Model Assumptions: Fill in the BLUE numbers in the assumptions column. You can override the autopopulation if you want to adjust by month.
B3: GTM Bottoms Up Model: Fill in the hiring plan in blue.
E5: Model Assumptions | G5: 45658 | H5: =EDATE(G5,1) -> 45689 | I5: =EDATE(H5,1) -> 45717 | J5: =EDATE(I5,1) -> 45748 | K5: =EDATE(J5,1) -> 45778 | L5: =EDATE(K5,1) -> 45809 | M5: =EDATE(L5,1) -> 45839 | N5: =EDATE(M5,1) -> 45870 | O5: =EDATE(N5,1) -> 45901 | ... R5: =EDATE(Q5,1) -> 45992
B6: Productivity
B7: AE
B8: Aggregate Average ACV | E8: 15000 | G8: =$E$8 -> 15000 | H8: =$E$8 -> 15000 | I8: =$E$8 -> 15000 | J8: 22500 | K8: 22500 | L8: 22500 | M8: 22500 | N8: 22500 | O8: 22500 | P8: 22500 | Q8: 22500 | R8: 22500
B9: New Customers Signed per Rep | E9: 2 | G9: =$E$9 -> 2 | H9: =$E$9 -> 2 | I9: =$E$9 -> 2 | J9: =$E$9 -> 2 | K9: =$E$9 -> 2 | L9: =$E$9 -> 2 | M9: 2.5 | N9: 2.5 | O9: 2.5 | P9: 2.5 | Q9: 2.5 | R9: 2.5
B10: CS
B11: Average Expansion ACV | E11: 3000 | G11: =$E$11 -> 3000 | H11: =$E$11 -> 3000 | I11: =$E$11 -> 3000 | J11: =$E$11 -> 3000 | K11: =$E$11 -> 3000 | L11: =$E$11 -> 3000 | M11: =$E$11 -> 3000 | N11: =$E$11 -> 3000 | ... R11: =$E$11 -> 3000
B12: Expansions per rep | E12: 2 | G12: =$E$12 -> 2 | H12: =$E$12 -> 2 | I12: =$E$12 -> 2 | J12: =$E$12 -> 2 | K12: =$E$12 -> 2 | L12: =$E$12 -> 2 | M12: =$E$12 -> 2 | N12: =$E$12 -> 2 | ... R12: =$E$12 -> 2
B14: Gross Margin | E14: 0.8 | G14: =$E$14 -> 0.8 | H14: =$E$14 -> 0.8 | I14: =$E$14 -> 0.8 | J14: =$E$14 -> 0.8 | K14: =$E$14 -> 0.8 | L14: =$E$14 -> 0.8 | M14: =$E$14 -> 0.8 | N14: =$E$14 -> 0.8 | ... R14: =$E$14 -> 0.8
B16: Demand Gen Channels - Deals Closed by channel
B17: Inbound | E17: 0.8 | G17: =$E$17 -> 0.8 | H17: =$E$17 -> 0.8 | I17: =$E$17 -> 0.8 | J17: =$E$17 -> 0.8 | K17: =$E$17 -> 0.8 | L17: =$E$17 -> 0.8 | M17: =$E$17 -> 0.8 | N17: =$E$17 -> 0.8 | ... R17: =$E$17 -> 0.8
B18: Outbound | E18: 0.2 | G18: =$E$18 -> 0.2 | H18: =$E$18 -> 0.2 | I18: =$E$18 -> 0.2 | J18: =$E$18 -> 0.2 | K18: =$E$18 -> 0.2 | L18: =$E$18 -> 0.2 | M18: =$E$18 -> 0.2 | N18: =$E$18 -> 0.2 | ... R18: =$E$18 -> 0.2
B19: Partners | E19: 0 | G19: =$E$19 -> 0 | H19: =$E$19 -> 0 | I19: =$E$19 -> 0 | J19: =$E$19 -> 0 | K19: =$E$19 -> 0 | L19: =$E$19 -> 0 | M19: =$E$19 -> 0 | N19: =$E$19 -> 0 | ... R19: =$E$19 -> 0
B21: Demand Generation Performance
B22: Channel 1: Inbound
B23: Marketing Spend per Month per Rep | E23: =E26*E30 -> 49.853944 | G23: =$E$23 -> 49.853944 | H23: =$E$23 -> 49.853944 | I23: =$E$23 -> 49.853944 | J23: =$E$23 -> 49.853944 | K23: =$E$23 -> 49.853944 | L23: =$E$23 -> 49.853944 | M23: =$E$23 -> 49.853944 | N23: =$E$23 -> 49.853944 | ... R23: =$E$23 -> 49.853944
B24: Deals per Rep | E24: =AVERAGE(E9)*E17 -> 1.6 | G24: =$E$24 -> 1.6 | H24: =$E$24 -> 1.6 | I24: =$E$24 -> 1.6 | J24: =$E$24 -> 1.6 | K24: =$E$24 -> 1.6 | L24: =$E$24 -> 1.6 | M24: =$E$24 -> 1.6 | N24: =$E$24 -> 1.6 | ... R24: =$E$24 -> 1.6
B25: SQLs per Rep | E25: =E24/E29 -> 2.0253165 | G25: =$E$25 -> 2.0253165 | H25: =$E$25 -> 2.0253165 | I25: =$E$25 -> 2.0253165 | J25: =$E$25 -> 2.0253165 | K25: =$E$25 -> 2.0253165 | L25: =$E$25 -> 2.0253165 | M25: =$E$25 -> 2.0253165 | N25: =$E$25 -> 2.0253165 | ... R25: =$E$25 -> 2.0253165
B26: TOFU Leads per Rep | E26: =E25/E27 -> 3.1158715 | G26: =$E$26 -> 3.1158715 | H26: =$E$26 -> 3.1158715 | I26: =$E$26 -> 3.1158715 | J26: =$E$26 -> 3.1158715 | K26: =$E$26 -> 3.1158715 | L26: =$E$26 -> 3.1158715 | M26: =$E$26 -> 3.1158715 | N26: =$E$26 -> 3.1158715 | ... R26: =$E$26 -> 3.1158715
B27: Lead to SQL Conversion (demo) | E27: 0.65 | G27: =$E$27 -> 0.65 | H27: =$E$27 -> 0.65 | I27: =$E$27 -> 0.65 | J27: =$E$27 -> 0.65 | K27: =$E$27 -> 0.65 | L27: =$E$27 -> 0.65 | M27: =$E$27 -> 0.65 | N27: =$E$27 -> 0.65 | ... R27: =$E$27 -> 0.65
B28: Demo to Eval | E28: 0.45 | G28: =$E$28 -> 0.45 | H28: =$E$28 -> 0.45 | I28: =$E$28 -> 0.45 | J28: =$E$28 -> 0.45 | K28: =$E$28 -> 0.45 | L28: =$E$28 -> 0.45 | M28: =$E$28 -> 0.45 | N28: =$E$28 -> 0.45 | ... R28: =$E$28 -> 0.45
B29: Eval to Contracting | E29: 0.79 | G29: =$E$29 -> 0.79 | H29: =$E$29 -> 0.79 | I29: =$E$29 -> 0.79 | J29: =$E$29 -> 0.79 | K29: =$E$29 -> 0.79 | L29: =$E$29 -> 0.79 | M29: =$E$29 -> 0.79 | N29: =$E$29 -> 0.79 | ... R29: =$E$29 -> 0.79
B30: Cost per TOFU Lead | E30: 16 | G30: =$E$30 -> 16 | H30: =$E$30 -> 16 | I30: =$E$30 -> 16 | J30: =$E$30 -> 16 | K30: =$E$30 -> 16 | L30: =$E$30 -> 16 | M30: =$E$30 -> 16 | N30: =$E$30 -> 16 | ... R30: =$E$30 -> 16
B31: Channel 2: Outbound
B32: SDR Accounts Needed # | E32: =E34/E36*2 -> 3.9506173 | G32: =$E$32 -> 3.9506173 | H32: =$E$32 -> 3.9506173 | I32: =$E$32 -> 3.9506173 | J32: =$E$32 -> 3.9506173 | K32: =$E$32 -> 3.9506173 | L32: =$E$32 -> 3.9506173 | M32: =$E$32 -> 3.9506173 | N32: =$E$32 -> 3.9506173 | ... R32: =$E$32 -> 3.9506173
B33: Deals per Rep | E33: =AVERAGE(E9)*E18 -> 0.4 | G33: =$E$33 -> 0.4 | H33: =$E$33 -> 0.4 | I33: =$E$33 -> 0.4 | J33: =$E$33 -> 0.4 | K33: =$E$33 -> 0.4 | L33: =$E$33 -> 0.4 | M33: =$E$33 -> 0.4 | N33: =$E$33 -> 0.4 | ... R33: =$E$33 -> 0.4
B34: SQLs per Rep | E34: =E33/E36 -> 0.88888889 | G34: =$E$34 -> 0.88888889 | H34: =$E$34 -> 0.88888889 | I34: =$E$34 -> 0.88888889 | J34: =$E$34 -> 0.88888889 | K34: =$E$34 -> 0.88888889 | L34: =$E$34 -> 0.88888889 | M34: =$E$34 -> 0.88888889 | N34: =$E$34 -> 0.88888889 | ... R34: =$E$34 -> 0.88888889
B35: Contacts to SQL Conversion (demo) | E35: 0.03 | G35: =$E$35 -> 0.03 | H35: =$E$35 -> 0.03 | I35: =$E$35 -> 0.03 | J35: =$E$35 -> 0.03 | K35: =$E$35 -> 0.03 | L35: =$E$35 -> 0.03 | M35: =$E$35 -> 0.03 | N35: =$E$35 -> 0.03 | ... R35: =$E$35 -> 0.03
B36: Outbound SQL to Pilot | E36: 0.45 | G36: =$E$36 -> 0.45 | H36: =$E$36 -> 0.45 | I36: =$E$36 -> 0.45 | J36: =$E$36 -> 0.45 | K36: =$E$36 -> 0.45 | L36: =$E$36 -> 0.45 | M36: =$E$36 -> 0.45 | N36: =$E$36 -> 0.45 | ... R36: =$E$36 -> 0.45
B37: Pilot to Customer Conversion | E37: 0.79 | G37: =$E$37 -> 0.79 | H37: =$E$37 -> 0.79 | I37: =$E$37 -> 0.79 | J37: =$E$37 -> 0.79 | K37: =$E$37 -> 0.79 | L37: =$E$37 -> 0.79 | M37: =$E$37 -> 0.79 | N37: =$E$37 -> 0.79 | ... R37: =$E$37 -> 0.79
B38: SDR to AE Ratio | E38: 2 | G38: =$E$38 -> 2 | H38: =$E$38 -> 2 | I38: =$E$38 -> 2 | J38: =$E$38 -> 2 | K38: =$E$38 -> 2 | L38: =$E$38 -> 2 | M38: =$E$38 -> 2 | N38: =$E$38 -> 2 | ... R38: =$E$38 -> 2
B39: Channel 3: Partners
B40: Partner Compensation per Lead | E40: 0 | G40: =$E$40 -> 0 | H40: =$E$40 -> 0 | I40: =$E$40 -> 0 | J40: =$E$40 -> 0 | K40: =$E$40 -> 0 | L40: =$E$40 -> 0 | M40: =$E$40 -> 0 | N40: =$E$40 -> 0 | ... R40: =$E$40 -> 0
B41: Partner Deals per Rep | E41: =AVERAGE(E9)*E19 -> 0 | G41: =$E$41 -> 0 | H41: =$E$41 -> 0 | I41: =$E$41 -> 0 | J41: =$E$41 -> 0 | K41: =$E$41 -> 0 | L41: =$E$41 -> 0 | M41: =$E$41 -> 0 | N41: =$E$41 -> 0 | ... R41: =$E$41 -> 0
B42: Partner TOFU Leads to SQL Conversion | E42: 0.1 | G42: =$E$42 -> 0.1 | H42: =$E$42 -> 0.1 | I42: =$E$42 -> 0.1 | J42: =$E$42 -> 0.1 | K42: =$E$42 -> 0.1 | L42: =$E$42 -> 0.1 | M42: =$E$42 -> 0.1 | N42: =$E$42 -> 0.1 | ... R42: =$E$42 -> 0.1
B43: Partner SQL to Customer Conversion | E43: 0.2 | G43: =$E$43 -> 0.2 | H43: =$E$43 -> 0.2 | I43: =$E$43 -> 0.2 | J43: =$E$43 -> 0.2 | K43: =$E$43 -> 0.2 | L43: =$E$43 -> 0.2 | M43: =$E$43 -> 0.2 | N43: =$E$43 -> 0.2 | ... R43: =$E$43 -> 0.2
B46: Headcount Cost (Annual)
B47: SR AE OTE ($K) | E47: 0 | G47: =$E$47/12 -> 0 | H47: =$E$47/12 -> 0 | I47: =$E$47/12 -> 0 | J47: =$E$47/12 -> 0 | K47: =$E$47/12 -> 0 | L47: =$E$47/12 -> 0 | M47: =$E$47/12 -> 0 | N47: =$E$47/12 -> 0 | ... R47: =$E$47/12 -> 0
B48: AE OTE | E48: 200 | G48: =$E$48/12 -> 16.666667 | H48: =$E$48/12 -> 16.666667 | I48: =$E$48/12 -> 16.666667 | J48: =$E$48/12 -> 16.666667 | K48: =$E$48/12 -> 16.666667 | L48: =$E$48/12 -> 16.666667 | M48: =$E$48/12 -> 16.666667 | N48: =$E$48/12 -> 16.666667 | ... R48: =$E$48/12 -> 16.666667
B49: Head of Sales | E49: 320 | G49: =$E$49/12 -> 26.666667 | H49: =$E$49/12 -> 26.666667 | I49: =$E$49/12 -> 26.666667 | J49: =$E$49/12 -> 26.666667 | K49: =$E$49/12 -> 26.666667 | L49: =$E$49/12 -> 26.666667 | M49: =$E$49/12 -> 26.666667 | N49: =$E$49/12 -> 26.666667 | ... R49: =$E$49/12 -> 26.666667
B50: SDR | E50: 100 | G50: =$E$50/12 -> 8.3333333 | H50: =$E$50/12 -> 8.3333333 | I50: =$E$50/12 -> 8.3333333 | J50: =$E$50/12 -> 8.3333333 | K50: =$E$50/12 -> 8.3333333 | L50: =$E$50/12 -> 8.3333333 | M50: =$E$50/12 -> 8.3333333 | N50: =$E$50/12 -> 8.3333333 | ... R50: =$E$50/12 -> 8.3333333
B51: Marketing | E51: 180 | G51: =$E$51/12 -> 15 | H51: =$E$51/12 -> 15 | I51: =$E$51/12 -> 15 | J51: =$E$51/12 -> 15 | K51: =$E$51/12 -> 15 | L51: =$E$51/12 -> 15 | M51: =$E$51/12 -> 15 | N51: =$E$51/12 -> 15 | ... R51: =$E$51/12 -> 15
B52: Other Metrics

Sheet GTM Bottoms up Model
A2: Sales Team: Including Ramp | C2: =B2+1 -> 1 | D2: =C2+1 -> 2 | E2: =D2+1 -> 3 | F2: =E2+1 -> 4 | G2: =F2+1 -> 5 | H2: =G2+1 -> 6 | I2: =H2+1 -> 7 | J2: =I2+1 -> 8 | ... M2: =L2+1 -> 11
B3: 45658 | C3: =EDATE(B3,1) -> 45689 | D3: =EDATE(C3,1) -> 45717 | E3: =EDATE(D3,1) -> 45748 | F3: =EDATE(E3,1) -> 45778 | G3: =EDATE(F3,1) -> 45809 | H3: =EDATE(G3,1) -> 45839 | I3: =EDATE(H3,1) -> 45870 | J3: =EDATE(I3,1) -> 45901 | ... M3: =EDATE(L3,1) -> 45992
A5: Headcount
A6: AE Headcount
A7: VP Sales / Sales Leader ( ) | B7: 0 | C7: 0 | D7: 0 | E7: 1 | F7: 1 | G7: 1 | H7: 1 | I7: 1 | J7: 1 | K7: 1 | L7: 1 | M7: 1
A8: AEI Quota | B8: =SUM('Model Assumptions'!G8*'Model Assumptions'!G9) -> 30000 | C8: =SUM('Model Assumptions'!H8*'Model Assumptions'!H9) -> 30000 | D8: =SUM('Model Assumptions'!I8*'Model Assumptions'!I9) -> 30000 | E8: =SUM('Model Assumptions'!J8*'Model Assumptions'!J9) -> 45000 | F8: =SUM('Model Assumptions'!K8*'Model Assumptions'!K9) -> 45000 | G8: =SUM('Model Assumptions'!L8*'Model Assumptions'!L9) -> 45000 | H8: =SUM('Model Assumptions'!M8*'Model Assumptions'!M9) -> 56250 | I8: =SUM('Model Assumptions'!N8*'Model Assumptions'!N9) -> 56250 | ... M8: =SUM('Model Assumptions'!R8*'Model Assumptions'!R9) -> 56250
A9: AE0 | B9: 1 | C9: 1 | D9: 1 | E9: 1 | F9: 1 | G9: 1 | H9: 1 | I9: 1 | J9: 1 | K9: 1 | L9: 1 | M9: 1
A10: AE1 | B10: 1 | C10: 1 | D10: 1 | E10: 1 | F10: 1 | G10: 1 | H10: 1 | I10: 1 | J10: 1 | K10: 1 | L10: 1 | M10: 1
A11: AE2 | B11: 0 | C11: 0 | D11: 0 | E11: 0 | F11: 0 | G11: 0 | H11: 0.3 | I11: 0.6 | J11: 0.6 | K11: 1 | L11: 1 | M11: 1
A12: AE3 | B12: 0 | C12: 0 | D12: 0 | E12: 0 | F12: 0 | G12: 0 | H12: 0 | I12: 0.3 | J12: 0.6 | K12: 0.6 | L12: 1 | M12: 1
A13: AE4 | K13: 0.3 | L13: 0.3 | M13: 0.3
A14: AE5
A15: Customer Success / AM Quota
A16: CS 1 TBH | B16: 1 | C16: 1 | D16: 1 | E16: 1 | F16: 1 | G16: 1 | H16: 1 | I16: 1 | J16: 1 | K16: 1 | L16: 1 | M16: 1
A17: CS2
A18: CS3
A19: AEs | B19: =SUM(B9:B14) -> 2 | C19: =SUM(C9:C14) -> 2 | D19: =SUM(D9:D14) -> 2 | E19: =SUM(E9:E14) -> 2 | F19: =SUM(F9:F14) -> 2 | G19: =SUM(G9:G14) -> 2 | H19: =SUM(H9:H14) -> 2.3 | I19: =SUM(I9:I14) -> 2.9 | ... M19: =SUM(M9:M14) -> 4.3
A20: CS Total | B20: =SUM(B16:B18) -> 1 | C20: =SUM(C16:C18) -> 1 | D20: =SUM(D16:D18) -> 1 | E20: =SUM(E16:E18) -> 1 | F20: =SUM(F16:F18) -> 1 | G20: =SUM(G16:G18) -> 1 | H20: =SUM(H16:H18) -> 1 | I20: =SUM(I16:I18) -> 1 | ... M20: =SUM(M16:M18) -> 1
A21: SDRs Total Outbound | B21: 1 | C21: 1 | D21: 1 | E21: 1 | F21: 1 | G21: 2 | H21: 2 | I21: 2 | J21: 2 | K21: 2 | L21: 2 | M21: 2
A24: New Revenue Projections
A26: Signed Revenue
A27: Total New ARR | B27: =SUM(B32+B30) -> 66000 | C27: =SUM(C32+C30) -> 66000 | D27: =SUM(D32+D30) -> 66000 | E27: =SUM(E32+E30) -> 96000 | F27: =SUM(F32+F30) -> 96000 | G27: =SUM(G32+G30) -> 96000 | H27: =SUM(H32+H30) -> 135375 | I27: =SUM(I32+I30) -> 169125 | ... M27: =SUM(M32+M30) -> 247875
A29: New Customers | B29: =B19*'Model Assumptions'!G9 -> 4 | C29: =C19*'Model Assumptions'!H9 -> 4 | D29: =D19*'Model Assumptions'!I9 -> 4 | E29: =E19*'Model Assumptions'!J9 -> 4 | F29: =F19*'Model Assumptions'!K9 -> 4 | G29: =G19*'Model Assumptions'!L9 -> 4 | H29: =H19*'Model Assumptions'!M9 -> 5.75 | I29: =I19*'Model Assumptions'!N9 -> 7.25 | ... M29: =M19*'Model Assumptions'!R9 -> 10.75
A30: New Customer ARR | B30: =(B29*'Model Assumptions'!G8) -> 60000 | C30: =(C29*'Model Assumptions'!H8) -> 60000 | D30: =(D29*'Model Assumptions'!I8) -> 60000 | E30: =(E29*'Model Assumptions'!J8) -> 90000 | F30: =(F29*'Model Assumptions'!K8) -> 90000 | G30: =(G29*'Model Assumptions'!L8) -> 90000 | H30: =(H29*'Model Assumptions'!M8) -> 129375 | I30: =(I29*'Model Assumptions'!N8) -> 163125 | ... M30: =(M29*'Model Assumptions'!R8) -> 241875
A31: Expansion Customers | B31: =B20*'Model Assumptions'!G12 -> 2 | C31: =C20*'Model Assumptions'!H12 -> 2 | D31: =D20*'Model Assumptions'!I12 -> 2 | E31: =E20*'Model Assumptions'!J12 -> 2 | F31: =F20*'Model Assumptions'!K12 -> 2 | G31: =G20*'Model Assumptions'!L12 -> 2 | H31: =H20*'Model Assumptions'!M12 -> 2 | I31: =I20*'Model Assumptions'!N12 -> 2 | ... M31: =M20*'Model Assumptions'!R12 -> 2
A32: Expansion ARR | B32: =B31*'Model Assumptions'!G11 -> 6000 | C32: =C31*'Model Assumptions'!H11 -> 6000 | D32: =D31*'Model Assumptions'!I11 -> 6000 | E32: =E31*'Model Assumptions'!J11 -> 6000 | F32: =F31*'Model Assumptions'!K11 -> 6000 | G32: =G31*'Model Assumptions'!L11 -> 6000 | H32: =H31*'Model Assumptions'!M11 -> 6000 | I32: =I31*'Model Assumptions'!N11 -> 6000 | ... M32: =M31*'Model Assumptions'!R11 -> 6000
A34: Pipeline Needed
A35: New Customers
A36: TOFU Leads | B36: =B39/#REF! -> #REF! | C36: =C39/#REF! -> #REF! | D36: =D39/#REF! -> #REF! | E36: =E39/#REF! -> #REF! | F36: =F39/#REF! -> #REF! | G36: =G39/#REF! -> #REF! | H36: =H39/#REF! -> #REF! | I36: =I39/#REF! -> #REF! | ... M36: =M39/#REF! -> #REF!
A37: TOFU -Outbound Accounts | B37: =B44 -> 75.011721 | C37: =C44 -> 75.011721 | D37: =D44 -> 75.011721 | E37: =E44 -> 75.011721 | F37: =F44 -> 75.011721 | G37: =G44 -> 75.011721 | H37: =H44 -> 107.82935 | I37: =I44 -> 135.95874 | ... M37: =M44 -> 201.594
A38: TOFU - Inbound MQLs | B38: =B58 -> 13.848318 | C38: =C58 -> 13.848318 | D38: =D58 -> 13.848318 | E38: =E58 -> 13.848318 | F38: =F58 -> 13.848318 | G38: =G58 -> 13.848318 | H38: =H58 -> 19.906957 | I38: =I58 -> 25.100076 | ... M38: =M58 -> 37.217354
A39: Opportunities (SQLs) | B39: =SUM(B45+B59+B70) -> 11.251758 | C39: =SUM(C45+C59+C70) -> 11.251758 | D39: =SUM(D45+D59+D70) -> 11.251758 | E39: =SUM(E45+E59+E70) -> 11.251758 | F39: =SUM(F45+F59+F70) -> 11.251758 | G39: =SUM(G45+G59+G70) -> 11.251758 | H39: =SUM(H45+H59+H70) -> 16.174402 | I39: =SUM(I45+I59+I70) -> 20.393812 | ... M39: =SUM(M45+M59+M70) -> 30.2391
A40: Pilots | B40: =SUM(B46+B60) -> 5.0632911 | C40: =SUM(C46+C60) -> 5.0632911 | D40: =SUM(D46+D60) -> 5.0632911 | E40: =SUM(E46+E60) -> 5.0632911 | F40: =SUM(F46+F60) -> 5.0632911 | G40: =SUM(G46+G60) -> 5.0632911 | H40: =SUM(H46+H60) -> 7.278481 | I40: =SUM(I46+I60) -> 9.1772152 | ... M40: =SUM(M46+M60) -> 13.607595
A41: New Customers | B41: =SUM(B19*'Model Assumptions'!G9) -> 4 | C41: =SUM(C19*'Model Assumptions'!H9) -> 4 | D41: =SUM(D19*'Model Assumptions'!I9) -> 4 | E41: =SUM(E19*'Model Assumptions'!J9) -> 4 | F41: =SUM(F19*'Model Assumptions'!K9) -> 4 | G41: =SUM(G19*'Model Assumptions'!L9) -> 4 | H41: =SUM(H19*'Model Assumptions'!M9) -> 5.75 | I41: =SUM(I19*'Model Assumptions'!N9) -> 7.25 | ... M41: =SUM(M19*'Model Assumptions'!R9) -> 10.75
A42: Demand Gen Channels
A43: Channel 1: Outbound
A44: Top of Funnel Leads / Accounts Needed | B44: =B45/'Model Assumptions'!G35 -> 75.011721 | C44: =C45/'Model Assumptions'!H35 -> 75.011721 | D44: =D45/'Model Assumptions'!I35 -> 75.011721 | E44: =E45/'Model Assumptions'!J35 -> 75.011721 | F44: =F45/'Model Assumptions'!K35 -> 75.011721 | G44: =G45/'Model Assumptions'!L35 -> 75.011721 | H44: =H45/'Model Assumptions'!M35 -> 107.82935 | I44: =I45/'Model Assumptions'!N35 -> 135.95874 | ... M44: =M45/'Model Assumptions'!R35 -> 201.594
A45: SQL | B45: =B46/'Model Assumptions'!G36 -> 2.2503516 | C45: =C46/'Model Assumptions'!H36 -> 2.2503516 | D45: =D46/'Model Assumptions'!I36 -> 2.2503516 | E45: =E46/'Model Assumptions'!J36 -> 2.2503516 | F45: =F46/'Model Assumptions'!K36 -> 2.2503516 | G45: =G46/'Model Assumptions'!L36 -> 2.2503516 | H45: =H46/'Model Assumptions'!M36 -> 3.2348805 | I45: =I46/'Model Assumptions'!N36 -> 4.0787623 | ... M45: =M46/'Model Assumptions'!R36 -> 6.04782
A46: Pilot | B46: =B47/'Model Assumptions'!G37 -> 1.0126582 | C46: =C47/'Model Assumptions'!H37 -> 1.0126582 | D46: =D47/'Model Assumptions'!I37 -> 1.0126582 | E46: =E47/'Model Assumptions'!J37 -> 1.0126582 | F46: =F47/'Model Assumptions'!K37 -> 1.0126582 | G46: =G47/'Model Assumptions'!L37 -> 1.0126582 | H46: =H47/'Model Assumptions'!M37 -> 1.4556962 | I46: =I47/'Model Assumptions'!N37 -> 1.835443 | ... M46: =M47/'Model Assumptions'!R37 -> 2.721519
A47: Customers | B47: =B29*'Model Assumptions'!G18 -> 0.8 | C47: =C29*'Model Assumptions'!H18 -> 0.8 | D47: =D29*'Model Assumptions'!I18 -> 0.8 | E47: =E29*'Model Assumptions'!J18 -> 0.8 | F47: =F29*'Model Assumptions'!K18 -> 0.8 | G47: =G29*'Model Assumptions'!L18 -> 0.8 | H47: =H29*'Model Assumptions'!M18 -> 1.15 | I47: =I29*'Model Assumptions'!N18 -> 1.45 | ... M47: =M29*'Model Assumptions'!R18 -> 2.15
A48: SQLS per AE
A49: SQLs per SDR
A51: Implied Metrics
A52: SDR Cost $ / Outbound SQL | B52: =B86/B45 -> 3703.125 | C52: =C86/C45 -> 3703.125 | D52: =D86/D45 -> 3703.125 | E52: =E86/E45 -> 3703.125 | F52: =F86/F45 -> 3703.125 | G52: =G86/G45 -> 7406.25 | H52: =H86/H45 -> 5152.1739 | I52: =I86/I45 -> 4086.2069 | ... M52: =M86/M45 -> 2755.814
A53: SDR Cost $ / Outbound Customer | B53: =B86/B47 -> 10416.667 | C53: =C86/C47 -> 10416.667 | D53: =D86/D47 -> 10416.667 | E53: =E86/E47 -> 10416.667 | F53: =F86/F47 -> 10416.667 | G53: =G86/G47 -> 20833.333 | H53: =H86/H47 -> 14492.754 | I53: =I86/I47 -> 11494.253 | ... M53: =M86/M47 -> 7751.938
A54: SQLs per Outbound SDR per month | B54: =B45/B21 -> 2.2503516 | C54: =C45/C21 -> 2.2503516 | D54: =D45/D21 -> 2.2503516 | E54: =E45/E21 -> 2.2503516 | F54: =F45/F21 -> 2.2503516 | G54: =G45/G21 -> 1.1251758 | H54: =H45/H21 -> 1.6174402 | I54: =I45/I21 -> 2.0393812 | ... M54: =M45/M21 -> 3.02391
A55: Customers per Outbound SDR per month | B55: =B47/B21 -> 0.8 | C55: =C47/C21 -> 0.8 | D55: =D47/D21 -> 0.8 | E55: =E47/E21 -> 0.8 | F55: =F47/F21 -> 0.8 | G55: =G47/G21 -> 0.4 | H55: =H47/H21 -> 0.575 | I55: =I47/I21 -> 0.725 | ... M55: =M47/M21 -> 1.075
A57: Channel 2: Inbound
A58: MQLs | B58: =B59/'Model Assumptions'!G27 -> 13.848318 | C58: =C59/'Model Assumptions'!H27 -> 13.848318 | D58: =D59/'Model Assumptions'!I27 -> 13.848318 | E58: =E59/'Model Assumptions'!J27 -> 13.848318 | F58: =F59/'Model Assumptions'!K27 -> 13.848318 | G58: =G59/'Model Assumptions'!L27 -> 13.848318 | H58: =H59/'Model Assumptions'!M27 -> 19.906957 | I58: =I59/'Model Assumptions'!N27 -> 25.100076 | ... M58: =M59/'Model Assumptions'!R27 -> 37.217354
A59: SQL (demos) | B59: =B60/'Model Assumptions'!G28 -> 9.0014065 | C59: =C60/'Model Assumptions'!H28 -> 9.0014065 | D59: =D60/'Model Assumptions'!I28 -> 9.0014065 | E59: =E60/'Model Assumptions'!J28 -> 9.0014065 | F59: =F60/'Model Assumptions'!K28 -> 9.0014065 | G59: =G60/'Model Assumptions'!L28 -> 9.0014065 | H59: =H60/'Model Assumptions'!M28 -> 12.939522 | I59: =I60/'Model Assumptions'!N28 -> 16.315049 | ... M59: =M60/'Model Assumptions'!R28 -> 24.19128
A60: Pilot | B60: =B61/'Model Assumptions'!G29 -> 4.0506329 | C60: =C61/'Model Assumptions'!H29 -> 4.0506329 | D60: =D61/'Model Assumptions'!I29 -> 4.0506329 | E60: =E61/'Model Assumptions'!J29 -> 4.0506329 | F60: =F61/'Model Assumptions'!K29 -> 4.0506329 | G60: =G61/'Model Assumptions'!L29 -> 4.0506329 | H60: =H61/'Model Assumptions'!M29 -> 5.8227848 | I60: =I61/'Model Assumptions'!N29 -> 7.3417722 | ... M60: =M61/'Model Assumptions'!R29 -> 10.886076
A61: Customers | B61: =B29*'Model Assumptions'!G17 -> 3.2 | C61: =C29*'Model Assumptions'!H17 -> 3.2 | D61: =D29*'Model Assumptions'!I17 -> 3.2 | E61: =E29*'Model Assumptions'!J17 -> 3.2 | F61: =F29*'Model Assumptions'!K17 -> 3.2 | G61: =G29*'Model Assumptions'!L17 -> 3.2 | H61: =H29*'Model Assumptions'!M17 -> 4.6 | I61: =I29*'Model Assumptions'!N17 -> 5.8 | ... M61: =M29*'Model Assumptions'!R17 -> 8.6
A63: Implied Metrics
A64: Marketing $ / Inbound SQL | B64: =IFERROR(B82/B59,"") -> 24.615385 | C64: =IFERROR(C82/C59,"") -> 24.615385 | D64: =IFERROR(D82/D59,"") -> 24.615385 | E64: =IFERROR(E82/E59,"") -> 24.615385 | F64: =IFERROR(F82/F59,"") -> 24.615385 | G64: =IFERROR(G82/G59,"") -> 24.615385 | H64: =IFERROR(H82/H59,"") -> 24.615385 | I64: =IFERROR(I82/I59,"") -> 24.615385 | ... M64: =IFERROR(M82/M59,"") -> 24.615385
A65: Marketing $ / Inbound Customer | B65: =IFERROR(B82/B61,"") -> 69.241588 | C65: =IFERROR(C82/C61,"") -> 69.241588 | D65: =IFERROR(D82/D61,"") -> 69.241588 | E65: =IFERROR(E82/E61,"") -> 69.241588 | F65: =IFERROR(F82/F61,"") -> 69.241588 | G65: =IFERROR(G82/G61,"") -> 69.241588 | H65: =IFERROR(H82/H61,"") -> 69.241588 | I65: =IFERROR(I82/I61,"") -> 69.241588 | ... M65: =IFERROR(M82/M61,"") -> 69.241588
A66: Inbound SQLs per AE per month | B66: =B59/B19 -> 4.5007032 | C66: =C59/C19 -> 4.5007032 | D66: =D59/D19 -> 4.5007032 | E66: =E59/E19 -> 4.5007032 | F66: =F59/F19 -> 4.5007032 | G66: =G59/G19 -> 4.5007032 | H66: =H59/H19 -> 5.625879 | I66: =I59/I19 -> 5.625879 | ... M66: =M59/M19 -> 5.625879
A67: Inbound Customers per AE per month | B67: =B61/B19 -> 1.6 | C67: =C61/C19 -> 1.6 | D67: =D61/D19 -> 1.6 | E67: =E61/E19 -> 1.6 | F67: =F61/F19 -> 1.6 | G67: =G61/G19 -> 1.6 | H67: =H61/H19 -> 2 | I67: =I61/I19 -> 2 | ... M67: =M61/M19 -> 2
A69: Channel 3: Partnerships
A70: SQL | B70: =B71/'Model Assumptions'!G43 -> 0 | C70: =C71/'Model Assumptions'!H43 -> 0 | D70: =D71/'Model Assumptions'!I43 -> 0 | E70: =E71/'Model Assumptions'!J43 -> 0 | F70: =F71/'Model Assumptions'!K43 -> 0 | G70: =G71/'Model Assumptions'!L43 -> 0 | H70: =H71/'Model Assumptions'!M43 -> 0 | I70: =I71/'Model Assumptions'!N43 -> 0 | ... M70: =M71/'Model Assumptions'!R43 -> 0
A71: Customers | B71: =B29*'Model Assumptions'!G19 -> 0 | C71: =C29*'Model Assumptions'!H19 -> 0 | D71: =D29*'Model Assumptions'!I19 -> 0 | E71: =E29*'Model Assumptions'!J19 -> 0 | F71: =F29*'Model Assumptions'!K19 -> 0 | G71: =G29*'Model Assumptions'!L19 -> 0 | H71: =H29*'Model Assumptions'!M19 -> 0 | I71: =I29*'Model Assumptions'!N19 -> 0 | ... M71: =M29*'Model Assumptions'!R19 -> 0
A73: Partner Cost $ / Partner SQL | B73: =B89/B70 -> #DIV/0! | C73: =C89/C70 -> #DIV/0! | D73: =D89/D70 -> #DIV/0! | E73: =E89/E70 -> #DIV/0! | F73: =F89/F70 -> #DIV/0! | G73: =G89/G70 -> #DIV/0! | H73: =H89/H70 -> #DIV/0! | I73: =I89/I70 -> #DIV/0! | ... M73: =M89/M70 -> #DIV/0!
A74: Partner Cost $ / Partner Customer | B74: =B89/B71 -> #DIV/0! | C74: =C89/C71 -> #DIV/0! | D74: =D89/D71 -> #DIV/0! | E74: =E89/E71 -> #DIV/0! | F74: =F89/F71 -> #DIV/0! | G74: =G89/G71 -> #DIV/0! | H74: =H89/H71 -> #DIV/0! | I74: =I89/I71 -> #DIV/0! | ... M74: =M89/M71 -> #DIV/0!
A75: Partner SQLs per AE per month | B75: =B70/B19 -> 0 | C75: =C70/C19 -> 0 | D75: =D70/D19 -> 0 | E75: =E70/E19 -> 0 | F75: =F70/F19 -> 0 | G75: =G70/G19 -> 0 | H75: =H70/H19 -> 0 | I75: =I70/I19 -> 0 | ... M75: =M70/M19 -> 0
A76: Partner Customers per AE per month | B76: =B71/B19 -> 0 | C76: =C71/C19 -> 0 | D76: =D71/D19 -> 0 | E76: =E71/E19 -> 0 | F76: =F71/F19 -> 0 | G76: =G71/G19 -> 0 | H76: =H71/H19 -> 0 | I76: =I71/I19 -> 0 | ... M76: =M71/M19 -> 0
A80: CAC
A81: Inbound
A82: Marketing Spend | B82: ='Model Assumptions'!G30*B58 -> 221.57308 | C82: ='Model Assumptions'!H30*C58 -> 221.57308 | D82: ='Model Assumptions'!I30*D58 -> 221.57308 | E82: ='Model Assumptions'!J30*E58 -> 221.57308 | F82: ='Model Assumptions'!K30*F58 -> 221.57308 | G82: ='Model Assumptions'!L30*G58 -> 221.57308 | H82: ='Model Assumptions'!M30*H58 -> 318.51131 | I82: ='Model Assumptions'!N30*I58 -> 401.60121 | ... M82: ='Model Assumptions'!R30*M58 -> 595.47766
A83: Marketing Salary | B83: ='Model Assumptions'!G51*1000 -> 15000 | C83: ='Model Assumptions'!H51*1000 -> 15000 | D83: ='Model Assumptions'!I51*1000 -> 15000 | E83: ='Model Assumptions'!J51*1000 -> 15000 | F83: ='Model Assumptions'!K51*1000 -> 15000 | G83: ='Model Assumptions'!L51*1000 -> 15000 | H83: ='Model Assumptions'!M51*1000 -> 15000 | I83: ='Model Assumptions'!N51*1000 -> 15000 | ... M83: ='Model Assumptions'!R51*1000 -> 15000
A84: Other Spend
A85: Outbound
A86: SDR Cost | B86: =SUM('Model Assumptions'!G50*1000)*B21 -> 8333.3333 | C86: =SUM('Model Assumptions'!H50*1000)*C21 -> 8333.3333 | D86: =SUM('Model Assumptions'!I50*1000)*D21 -> 8333.3333 | E86: =SUM('Model Assumptions'!J50*1000)*E21 -> 8333.3333 | F86: =SUM('Model Assumptions'!K50*1000)*F21 -> 8333.3333 | G86: =SUM('Model Assumptions'!L50*1000)*G21 -> 16666.667 | H86: =SUM('Model Assumptions'!M50*1000)*H21 -> 16666.667 | I86: =SUM('Model Assumptions'!N50*1000)*I21 -> 16666.667 | ... M86: =SUM('Model Assumptions'!R50*1000)*M21 -> 16666.667
A88: Partner
A89: Partner Cost | B89: =B70*'Model Assumptions'!E40 -> 0 | C89: =C70*'Model Assumptions'!F40 -> 0 | D89: =D70*'Model Assumptions'!G40 -> 0 | E89: =E70*'Model Assumptions'!H40 -> 0 | F89: =F70*'Model Assumptions'!I40 -> 0 | G89: =G70*'Model Assumptions'!J40 -> 0 | H89: =H70*'Model Assumptions'!K40 -> 0 | I89: =I70*'Model Assumptions'!L40 -> 0 | ... M89: =M70*'Model Assumptions'!P40 -> 0
A91: AE Cost
A92: # of AEs | B92: =ROUNDUP(B19,0) -> 2 | C92: =ROUNDUP(C19,0) -> 2 | D92: =ROUNDUP(D19,0) -> 2 | E92: =ROUNDUP(E19,0) -> 2 | F92: =ROUNDUP(F19,0) -> 2 | G92: =ROUNDUP(G19,0) -> 2 | H92: =ROUNDUP(H19,0) -> 3 | I92: =ROUNDUP(I19,0) -> 3 | ... M92: =ROUNDUP(M19,0) -> 5
A93: AE Cost | B93: =SUM(B92*'Model Assumptions'!G48*1000) -> 33333.333 | C93: =SUM(C92*'Model Assumptions'!H48*1000) -> 33333.333 | D93: =SUM(D92*'Model Assumptions'!I48*1000) -> 33333.333 | E93: =SUM(E92*'Model Assumptions'!J48*1000) -> 33333.333 | F93: =SUM(F92*'Model Assumptions'!K48*1000) -> 33333.333 | G93: =SUM(G92*'Model Assumptions'!L48*1000) -> 33333.333 | H93: =SUM(H92*'Model Assumptions'!M48*1000) -> 50000 | I93: =SUM(I92*'Model Assumptions'!N48*1000) -> 50000 | ... M93: =SUM(M92*'Model Assumptions'!R48*1000) -> 83333.333
A95: Total S&M CAC | B95: =SUM(B82+B82+B84+B86+B89+B93)+('Model Assumptions'!G49*B7*1000) -> 42109.813 | C95: =SUM(C82+C82+C84+C86+C89+C93)+('Model Assumptions'!H49*C7*1000) -> 42109.813 | D95: =SUM(D82+D82+D84+D86+D89+D93)+('Model Assumptions'!I49*D7*1000) -> 42109.813 | E95: =SUM(E82+E82+E84+E86+E89+E93)+('Model Assumptions'!J49*E7*1000) -> 68776.479 | F95: =SUM(F82+F82+F84+F86+F89+F93)+('Model Assumptions'!K49*F7*1000) -> 68776.479 | G95: =SUM(G82+G82+G84+G86+G89+G93)+('Model Assumptions'!L49*G7*1000) -> 77109.813 | H95: =SUM(H82+H82+H84+H86+H89+H93)+('Model Assumptions'!M49*H7*1000) -> 93970.356 | I95: =SUM(I82+I82+I84+I86+I89+I93)+('Model Assumptions'!N49*I7*1000) -> 94136.536 | ... M95: =SUM(M82+M82+M84+M86+M89+M93)+('Model Assumptions'!R49*M7*1000) -> 127857.62
A97: Gross Margin
A98: New ARR
A99: Sales Headcount Cost
A100: Marketing Cost
A101: CAC
A102: Gross Margin Adj. Magic Number
A103: Payback (Months)
A105: Outbound
A106: Gross Margin
A107: New ARR
A108: Sales Headcount Cost
A109: CAC
... A118: Aggregate Unit Economics
A119: Gross Margin | B119: ='Model Assumptions'!G14 -> 0.8 | C119: ='Model Assumptions'!H14 -> 0.8 | D119: ='Model Assumptions'!I14 -> 0.8 | E119: ='Model Assumptions'!J14 -> 0.8 | F119: ='Model Assumptions'!K14 -> 0.8 | G119: ='Model Assumptions'!L14 -> 0.8 | H119: ='Model Assumptions'!M14 -> 0.8 | I119: ='Model Assumptions'!N14 -> 0.8 | ... M119: ='Model Assumptions'!R14 -> 0.8
A120: New ARR | B120: =B27 -> 66000 | C120: =C27 -> 66000 | D120: =D27 -> 66000 | E120: =E27 -> 96000 | F120: =F27 -> 96000 | G120: =G27 -> 96000 | H120: =H27 -> 135375 | I120: =I27 -> 169125 | ... M120: =M27 -> 247875
A121: CAC | B121: =B95 -> 42109.813 | C121: =C95 -> 42109.813 | D121: =D95 -> 42109.813 | E121: =E95 -> 68776.479 | F121: =F95 -> 68776.479 | G121: =G95 -> 77109.813 | H121: =H95 -> 93970.356 | I121: =I95 -> 94136.536 | ... M121: =M95 -> 127857.62
A122: Gross Margin Adj. Magic Number | B122: =B119*B120/B121 -> 1.2538645 | C122: =C119*C120/C121 -> 1.2538645 | D122: =D119*D120/D121 -> 1.2538645 | E122: =E119*E120/E121 -> 1.1166608 | F122: =F119*F120/F121 -> 1.1166608 | G122: =G119*G120/G121 -> 0.99598219 | H122: =H119*H120/H121 -> 1.1524911 | I122: =I119*I120/I121 -> 1.437274 | ... M122: =M119*M120/M121 -> 1.5509439
A123: Payback (Months) | B123: =1/B122*12 -> 9.570412 | C123: =1/C122*12 -> 9.570412 | D123: =1/D122*12 -> 9.570412 | E123: =1/E122*12 -> 10.746325 | F123: =1/F122*12 -> 10.746325 | G123: =1/G122*12 -> 12.048408 | H123: =1/H122*12 -> 10.412228 | I123: =1/I122*12 -> 8.3491384 | ... M123: =1/M122*12 -> 7.7372237
A124: S/M as a % of New ARR | B124: =B95/B120 -> 0.63802747 | C124: =C95/C120 -> 0.63802747 | D124: =D95/D120 -> 0.63802747 | E124: =E95/E120 -> 0.71642166 | F124: =F95/F120 -> 0.71642166 | G124: =G95/G120 -> 0.80322722 | H124: =H95/H120 -> 0.69414852 | I124: =I95/I120 -> 0.55660923 | ... M124: =M95/M120 -> 0.51581491
A125: Leading Indicators of Unit Economics
A126: SQLs per AE | B126: =B39/B92 -> 5.625879 | C126: =C39/C92 -> 5.625879 | D126: =D39/D92 -> 5.625879 | E126: =E39/E92 -> 5.625879 | F126: =F39/F92 -> 5.625879 | G126: =G39/G92 -> 5.625879 | H126: =H39/H92 -> 5.3914674 | I126: =I39/I92 -> 6.7979372 | ... M126: =M39/M92 -> 6.04782
A127: Deals per AE | B127: =B29/B19 -> 2 | C127: =C29/C19 -> 2 | D127: =D29/D19 -> 2 | E127: =E29/E19 -> 2 | F127: =F29/F19 -> 2 | G127: =G29/G19 -> 2 | H127: =H29/H19 -> 2.5 | I127: =I29/I19 -> 2.5 | ... M127: =M29/M19 -> 2.5
A128: ACV | B128: =B30/B29 -> 15000 | C128: =C30/C29 -> 15000 | D128: =D30/D29 -> 15000 | E128: =E30/E29 -> 22500 | F128: =F30/F29 -> 22500 | G128: =G30/G29 -> 22500 | H128: =H30/H29 -> 22500 | I128: =I30/I29 -> 22500 | ... M128: =M30/M29 -> 22500
...

Sheet Rep and Marketing Details
B1: Rep & Marketing Details
B2: Fill in the fields in grey.
C5: 44562 | D5: =EDATE(C5,1) -> 44593 | E5: =EDATE(D5,1) -> 44621 | F5: =EDATE(E5,1) -> 44652 | G5: =EDATE(F5,1) -> 44682 | H5: =EDATE(G5,1) -> 44713 | I5: =EDATE(H5,1) -> 44743 | J5: =EDATE(I5,1) -> 44774 | K5: =EDATE(J5,1) -> 44805 | ... N5: =EDATE(M5,1) -> 44896
B6: Rep Quotas - $ ARR
B7: Rep 1 - Abby | C7: 33333 | D7: 33333 | E7: 33333 | F7: 33333 | G7: 33333 | H7: 33333 | I7: 33333 | J7: 33333 | K7: 33333 | L7: 33333 | M7: 33333 | N7: 33333
B8: Rep 2 - Danielle | G8: 33333 | H8: 33333 | I8: 33333 | J8: 33333 | K8: 33333 | L8: 33333 | M8: 33333 | N8: 33333
B9: Rep 3
B10: Total | C10: =SUM(C6:C9) -> 33333 | D10: =SUM(D6:D9) -> 33333 | E10: =SUM(E6:E9) -> 33333 | F10: =SUM(F6:F9) -> 33333 | G10: =SUM(G6:G9) -> 66666 | H10: =SUM(H6:H9) -> 66666 | I10: =SUM(I6:I9) -> 66666 | J10: =SUM(J6:J9) -> 66666 | ... N10: =SUM(N6:N9) -> 66666
B12: Rep Attainment - $ ARR
B13: Rep 1 - Abby | G13: 0
B14: Rep 2 - Danielle | G14: 0
B15: Rep 3
B17: Total (MRR) | C17: =SUM(C13:C15)/12 -> 0 | D17: =SUM(D13:D15)/12 -> 0 | E17: =SUM(E13:E15)/12 -> 0 | F17: =SUM(F13:F15)/12 -> 0 | G17: =SUM(G13:G15)/12 -> 0 | H17: =SUM(H13:H15)/12 -> 0 | I17: =SUM(I13:I15)/12 -> 0 | J17: =SUM(J13:J15)/12 -> 0 | ... N17: =SUM(N13:N15)/12 -> 0
B19: Rep 1 Attainment % | C19: =C13/C7 -> 0 | D19: =D13/D7 -> 0 | E19: =E13/E7 -> 0 | F19: =F13/F7 -> 0 | G19: =G13/G7 -> 0 | H19: =H13/H7 -> 0 | I19: =I13/I7 -> 0 | J19: =J13/J7 -> 0 | ... N19: =N13/N7 -> 0
B20: Rep 2 Attainment % | C20: =C14/C8 -> #DIV/0! | D20: =D14/D8 -> #DIV/0! | E20: =E14/E8 -> #DIV/0! | F20: =F14/F8 -> #DIV/0! | G20: =G14/G8 -> 0 | H20: =H14/H8 -> 0 | I20: =I14/I8 -> 0 | J20: =J14/J8 -> 0 | ... N20: =N14/N8 -> 0
B21: Rep 3 Attainment % | C21: =C15/C9 -> #DIV/0! | D21: =D15/D9 -> #DIV/0! | E21: =E15/E9 -> #DIV/0! | F21: =F15/F9 -> #DIV/0! | G21: =G15/G9 -> #DIV/0! | H21: =H15/H9 -> #DIV/0! | I21: =I15/I9 -> #DIV/0! | J21: =J15/J9 -> #DIV/0! | ... N21: =N15/N9 -> #DIV/0!
B22: Total Attainment % | C22: =C17/C10 -> 0 | D22: =D17/D10 -> 0 | E22: =E17/E10 -> 0 | F22: =F17/F10 -> 0 | G22: =G17/G10 -> 0 | H22: =H17/H10 -> 0 | I22: =I17/I10 -> 0 | J22: =J17/J10 -> 0 | ... N22: =N17/N10 -> 0
B24: Note: Rep OTE & Sales Costs
B25: Rep 1 - Abby | C25: 7476.66 | D25: 7476.66 | E25: 7476.66 | F25: 7476.66 | G25: 7476.66 | H25: 7867.34 | I25: 3738.33 | J25: 0 | K25: =J25 -> 0 | L25: =K25 -> 0 | M25: =L25 -> 0 | N25: =M25 -> 0
B26: Rep 2 - Danielle | C26: 8845.83 | D26: 8845.83 | E26: 8845.83 | F26: 8845.83 | G26: 8845.83 | H26: 9960.49 | I26: 9937.5 | J26: 9960.49 | K26: 9960.49 | L26: 9960.49 | M26: 9960.49 | N26: 9960.49
B27: Rep 3
B28: SDRs Total Cost - Lia | H28: 3736.21 | I28: 5439.96 | J28: 5439.96 | K28: 5439.96 | L28: 5439.96 | M28: 5439.96 | N28: 5439.96
B29: Managers and other total cost
B30: Total | C30: =SUM(C25:C29) -> 16322.49 | D30: =SUM(D25:D29) -> 16322.49 | E30: =SUM(E25:E29) -> 16322.49 | F30: =SUM(F25:F29) -> 16322.49 | G30: =SUM(G25:G29) -> 16322.49 | H30: =SUM(H25:H29) -> 21564.04 | I30: =SUM(I25:I29) -> 19115.79 | J30: =SUM(J25:J29) -> 15400.45 | ... N30: =SUM(N25:N29) -> 15400.45
B32: Rep Accounts Touched - #
B33: Rep 1 - Abby
B34: Rep 2 - Danielle
B35: Rep 3
B37: Total | C37: =SUM(C33:C35) -> 0 | D37: =SUM(D33:D35) -> 0 | E37: =SUM(E33:E35) -> 0 | F37: =SUM(F33:F35) -> 0 | G37: =SUM(G33:G35) -> 0 | H37: =SUM(H33:H35) -> 0 | I37: =SUM(I33:I35) -> 0 | J37: =SUM(J33:J35) -> 0 | ... N37: =SUM(N33:N35) -> 0
B39: Rep Deals - #
B40: Rep 1 - Abby | G40: 1
B41: Rep 2 - Danielle | G41: 5
B42: Rep 3
B43: Total | C43: =SUM(C40:C42) -> 0 | D43: =SUM(D40:D42) -> 0 | E43: =SUM(E40:E42) -> 0 | F43: =SUM(F40:F42) -> 0 | G43: =SUM(G40:G42) -> 6 | H43: =SUM(H40:H42) -> 0 | I43: =SUM(I40:I42) -> 0 | J43: =SUM(J40:J42) -> 0 | ... N43: =SUM(N40:N42) -> 0
B45: Closed Deals by Rep - #
B46: Rep 1 - Abby | C46: 2 | G46: 0
B47: Rep 2 - Danielle | G47: 0
B48: Rep 3
B50: Total | C50: =SUM(C46:C48) -> 2 | D50: =SUM(D46:D48) -> 0 | E50: =SUM(E46:E48) -> 0 | F50: =SUM(F46:F48) -> 0 | G50: =SUM(G46:G48) -> 0 | H50: =SUM(H46:H48) -> 0 | I50: =SUM(I46:I48) -> 0 | J50: =SUM(J46:J48) -> 0 | ... N50: =SUM(N46:N48) -> 0
B51: Rep 1 SQO to win rate | C51: =C46/C40 -> #DIV/0! | D51: =D46/D40 -> #DIV/0! | E51: =E46/E40 -> #DIV/0! | F51: =F46/F40 -> #DIV/0! | G51: =G46/G40 -> 0 | H51: =H46/H40 -> #DIV/0! | I51: =I46/I40 -> #DIV/0! | J51: =J46/J40 -> #DIV/0! | ... N51: =N46/N40 -> #DIV/0!
B52: Rep 2 SQO to win rate | C52: =C47/C41 -> #DIV/0! | D52: =D47/D41 -> #DIV/0! | E52: =E47/E41 -> #DIV/0! | F52: =F47/F41 -> #DIV/0! | G52: =G47/G41 -> 0 | H52: =H47/H41 -> #DIV/0! | I52: =I47/I41 -> #DIV/0! | J52: =J47/J41 -> #DIV/0! | ... N52: =N47/N41 -> #DIV/0!
B53: Rep 3 SQO to win rate | C53: =C48/C42 -> #DIV/0! | D53: =D48/D42 -> #DIV/0! | E53: =E48/E42 -> #DIV/0! | F53: =F48/F42 -> #DIV/0! | G53: =G48/G42 -> #DIV/0! | H53: =H48/H42 -> #DIV/0! | I53: =I48/I42 -> #DIV/0! | J53: =J48/J42 -> #DIV/0! | ... N53: =N48/N42 -> #DIV/0!
C54: =C49/C43 -> #DIV/0! | D54: =D49/D43 -> #DIV/0! | E54: =E49/E43 -> #DIV/0! | F54: =F49/F43 -> #DIV/0! | G54: =G49/G43 -> 0 | H54: =H49/H43 -> #DIV/0! | I54: =I49/I43 -> #DIV/0! | J54: =J49/J43 -> #DIV/0! | ... N54: =N49/N43 -> #DIV/0!
B55: Total demo to win rate | C55: =C50/C43 -> #DIV/0! | D55: =D50/D43 -> #DIV/0! | E55: =E50/E43 -> #DIV/0! | F55: =F50/F43 -> #DIV/0! | G55: =G50/G43 -> 0 | H55: =H50/H43 -> #DIV/0! | I55: =I50/I43 -> #DIV/0! | J55: =J50/J43 -> #DIV/0! | ... N55: =N50/N43 -> #DIV/0!
B57: Rep 1 TOFU leads to SQO | C57: =C40/C33 -> #DIV/0! | D57: =D40/D33 -> #DIV/0! | E57: =E40/E33 -> #DIV/0! | F57: =F40/F33 -> #DIV/0! | G57: =G40/G33 -> #DIV/0! | H57: =H40/H33 -> #DIV/0! | I57: =I40/I33 -> #DIV/0! | J57: =J40/J33 -> #DIV/0! | ... N57: =N40/N33 -> #DIV/0!
B58: Rep 2 TOFU leads to SQO | C58: =C41/C34 -> #DIV/0! | D58: =D41/D34 -> #DIV/0! | E58: =E41/E34 -> #DIV/0! | F58: =F41/F34 -> #DIV/0! | G58: =G41/G34 -> #DIV/0! | H58: =H41/H34 -> #DIV/0! | I58: =I41/I34 -> #DIV/0! | J58: =J41/J34 -> #DIV/0! | ... N58: =N41/N34 -> #DIV/0!
B59: Rep 3 TOFU leads to SQO | C59: =C42/C35 -> #DIV/0! | D59: =D42/D35 -> #DIV/0! | E59: =E42/E35 -> #DIV/0! | F59: =F42/F35 -> #DIV/0! | G59: =G42/G35 -> #DIV/0! | H59: =H42/H35 -> #DIV/0! | I59: =I42/I35 -> #DIV/0! | J59: =J42/J35 -> #DIV/0! | ... N59: =N42/N35 -> #DIV/0!
C60: =C43/C36 -> #DIV/0! | D60: =D43/D36 -> #DIV/0! | E60: =E43/E36 -> #DIV/0! | F60: =F43/F36 -> #DIV/0! | G60: =G43/G36 -> #DIV/0! | H60: =H43/H36 -> #DIV/0! | I60: =I43/I36 -> #DIV/0! | J60: =J43/J36 -> #DIV/0! | ... N60: =N43/N36 -> #DIV/0!
B61: Total contacts to win rate | C61: =C43/C37 -> #DIV/0! | D61: =D43/D37 -> #DIV/0! | E61: =E43/E37 -> #DIV/0! | F61: =F43/F37 -> #DIV/0! | G61: =G43/G37 -> #DIV/0! | H61: =H43/H37 -> #DIV/0! | I61: =I43/I37 -> #DIV/0! | J61: =J43/J37 -> #DIV/0! | ... N61: =N43/N37 -> #DIV/0!
B64: SDR Productivity
B65: # of SDRs | H65: 1
B66: TOFU leads (accounts worked)
B67: Discos
B68: Closed won (SDR generated)
B70: TOFU to SQO conversion | C70: =C67/C66 -> #DIV/0! | D70: =D67/D66 -> #DIV/0! | E70: =E67/E66 -> #DIV/0! | F70: =F67/F66 -> #DIV/0! | G70: =G67/G66 -> #DIV/0! | H70: =H67/H66 -> #DIV/0! | I70: =I67/I66 -> #DIV/0! | J70: =J67/J66 -> #DIV/0! | ... N70: =N67/N66 -> #DIV/0!
B71: SQO to Customer conversion | C71: =C68/C67 -> #DIV/0! | D71: =D68/D67 -> #DIV/0! | E71: =E68/E67 -> #DIV/0! | F71: =F68/F67 -> #DIV/0! | G71: =G68/G67 -> #DIV/0! | H71: =H68/H67 -> #DIV/0! | I71: =I68/I67 -> #DIV/0! | J71: =J68/J67 -> #DIV/0! | ... N71: =N68/N67 -> #DIV/0!
B73: Discos
B74: Marketing Spend by Channel and Funnel
B75: Outbound
B76: Partner Channel
B77: Salary & Other Expenses | C77: 6759 | D77: 6759 | E77: 6759 | F77: 6759 | G77: 6759 | H77: 7352.35 | I77: 6899.36 | J77: 6899.36 | K77: 6899.36 | L77: 6899.36 | M77: 6899.36 | N77: 6899.36
B78: Total | C78: =SUM(C75:C77) -> 6759 | D78: =SUM(D75:D77) -> 6759 | E78: =SUM(E75:E77) -> 6759 | F78: =SUM(F75:F77) -> 6759 | G78: =SUM(G75:G77) -> 6759 | H78: =SUM(H75:H77) -> 7352.35 | I78: =SUM(I75:I77) -> 6899.36 | J78: =SUM(J75:J77) -> 6899.36 | ... N78: =SUM(N75:N77) -> 6899.36
B80: Revenue by Channel
B81: Outbound
B82: Partner Channel
B83: Total | C83: =SUM(C81:C82) -> 0 | D83: =SUM(D81:D82) -> 0 | E83: =SUM(E81:E82) -> 0 | F83: =SUM(F81:F82) -> 0 | G83: =SUM(G81:G82) -> 0 | H83: =SUM(H81:H82) -> 0 | I83: =SUM(I81:I82) -> 0 | J83: =SUM(J81:J82) -> 0 | ... N83: =SUM(N81:N82) -> 0
B85: Top of Funnel Leads generated by channel
B86: Outbound
B87: Partner Channel
B88: Total | C88: =SUM(C86:C87) -> 0 | D88: =SUM(D86:D87) -> 0 | E88: =SUM(E86:E87) -> 0 | F88: =SUM(F86:F87) -> 0 | G88: =SUM(G86:G87) -> 0 | H88: =SUM(H86:H87) -> 0 | I88: =SUM(I86:I87) -> 0 | J88: =SUM(J86:J87) -> 0 | ... N88: =SUM(N86:N87) -> 0
B90: SQOs by Channel
B91: Outbound
B92: Partner Channel
B93: Total | C93: =SUM(C91:C92) -> 0 | D93: =SUM(D91:D92) -> 0 | E93: =SUM(E91:E92) -> 0 | F93: =SUM(F91:F92) -> 0 | G93: =SUM(G91:G92) -> 0 | H93: =SUM(H91:H92) -> 0 | I93: =SUM(I91:I92) -> 0 | J93: =SUM(J91:J92) -> 0 | ... N93: =SUM(N91:N92) -> 0
B94: Outbound lead to SQO | C94: =C91/C86 -> #DIV/0! | D94: =D91/D86 -> #DIV/0! | E94: =E91/E86 -> #DIV/0! | F94: =F91/F86 -> #DIV/0! | G94: =G91/G86 -> #DIV/0! | H94: =H91/H86 -> #DIV/0! | I94: =I91/I86 -> #DIV/0! | J94: =J91/J86 -> #DIV/0! | ... N94: =N91/N86 -> #DIV/0!
B95: Partner lead to SQO | C95: =C92/C87 -> #DIV/0! | D95: =D92/D87 -> #DIV/0! | E95: =E92/E87 -> #DIV/0! | F95: =F92/F87 -> #DIV/0! | G95: =G92/G87 -> #DIV/0! | H95: =H92/H87 -> #DIV/0! | I95: =I92/I87 -> #DIV/0! | J95: =J92/J87 -> #DIV/0! | ... N95: =N92/N87 -> #DIV/0!
B96: Total leads to SQOs | C96: =C93/C88 -> #DIV/0! | D96: =D93/D88 -> #DIV/0! | E96: =E93/E88 -> #DIV/0! | F96: =F93/F88 -> #DIV/0! | G96: =G93/G88 -> #DIV/0! | H96: =H93/H88 -> #DIV/0! | I96: =I93/I88 -> #DIV/0! | J96: =J93/J88 -> #DIV/0! | ... N96: =N93/N88 -> #DIV/0!
B98: Wins by Channel
B99: Outbound
B100: Partners
B101: Total | C101: =SUM(C99:C100) -> 0 | D101: =SUM(D99:D100) -> 0 | E101: =SUM(E99:E100) -> 0 | F101: =SUM(F99:F100) -> 0 | G101: =SUM(G99:G100) -> 0 | H101: =SUM(H99:H100) -> 0 | I101: =SUM(I99:I100) -> 0 | J101: =SUM(J99:J100) -> 0 | ... N101: =SUM(N99:N100) -> 0
B102: Outbound SQO to win | C102: =C99/C91 -> #DIV/0! | D102: =D99/D91 -> #DIV/0! | E102: =E99/E91 -> #DIV/0! | F102: =F99/F91 -> #DIV/0! | G102: =G99/G91 -> #DIV/0! | H102: =H99/H91 -> #DIV/0! | I102: =I99/I91 -> #DIV/0! | J102: =J99/J91 -> #DIV/0! | ... N102: =N99/N91 -> #DIV/0!
B103: Partner SQO to Win | C103: =C100/C92 -> #DIV/0! | D103: =D100/D92 -> #DIV/0! | E103: =E100/E92 -> #DIV/0! | F103: =F100/F92 -> #DIV/0! | G103: =G100/G92 -> #DIV/0! | H103: =H100/H92 -> #DIV/0! | I103: =I100/I92 -> #DIV/0! | J103: =J100/J92 -> #DIV/0! | ... N103: =N100/N92 -> #DIV/0!
B104: Total SQO to wins rate | C104: =C101/C93 -> #DIV/0! | D104: =D101/D93 -> #DIV/0! | E104: =E101/E93 -> #DIV/0! | F104: =F101/F93 -> #DIV/0! | G104: =G101/G93 -> #DIV/0! | H104: =H101/H93 -> #DIV/0! | I104: =I101/I93 -> #DIV/0! | J104: =J101/J93 -> #DIV/0! | ... N104: =N101/N93 -> #DIV/0!
B106: ACV by Channel
B107: Outbound | C107: =C81/C99 -> #DIV/0! | D107: =D81/D99 -> #DIV/0! | E107: =E81/E99 -> #DIV/0! | F107: =F81/F99 -> #DIV/0! | G107: =G81/G99 -> #DIV/0! | H107: =H81/H99 -> #DIV/0! | I107: =I81/I99 -> #DIV/0! | J107: =J81/J99 -> #DIV/0! | ... N107: =N81/N99 -> #DIV/0!
B108: Partners | C108: =C82/C100 -> #DIV/0! | D108: =D82/D100 -> #DIV/0! | E108: =E82/E100 -> #DIV/0! | F108: =F82/F100 -> #DIV/0! | G108: =G82/G100 -> #DIV/0! | H108: =H82/H100 -> #DIV/0! | I108: =I82/I100 -> #DIV/0! | J108: =J82/J100 -> #DIV/0! | ... N108: =N82/N100 -> #DIV/0!

Sheet Copy of Studies Published Data 
A1: https://app.amplitude.com/analytics/rallyuxr/chart/o5w4lyo/edit/69zjz4ud
A2: slug | B2: close date | C2: quarter | D2: ACV | E2: 44652 | F2: 44682 | G2: 44713 | H2: 44743 | I2: 44774 | J2: 44805 | K2: 44835 | L2: 44866 | M2: 44896 | N2: 44986 | O2: 45017 | P2: 45047 | Q2: 45078 | R2: 45108 | S2: 45139 | T2: 45170 | U2: 45200 | V2: 45231 | W2: 45261 | X2: 45292 | Y2: 45323 | Z2: 45352
A3: hellofresh | B3: 44645 | C3: ="Q" & INT((MONTH(B3)-1)/3) + 1 & " " & YEAR(B3) -> Q1 2022 | D3: 25000 | E3: 0 | F3: 0 | G3: 0 | H3: 0 | I3: 1 | J3: 0 | K3: 0 | L3: 4 | M3: 0 | N3: 2 | O3: 2 | P3: 2 | Q3: 2 | R3: 5 | S3: 10 | T3: 10 | U3: 14 | V3: 14 | W3: 15 | X3: 16 | Y3: 16 | Z3: 16
A4: consensys | B4: 44795 | C4: ="Q" & INT((MONTH(B4)-1)/3) + 1 & " " & YEAR(B4) -> Q3 2022 | D4: 3000 | E4: 0 | F4: 0 | G4: 0 | H4: 0 | I4: 3 | J4: 7 | K4: 0 | L4: 0 | M4: 0 | N4: 3 | O4: 5 | P4: 6 | Q4: 6 | R4: 6 | S4: 6 | T4: 6 | U4: 6 | V4: 7 | W4: 7 | X4: 7 | Y4: 7 | Z4: 7
A5: pandadoc | B5: 44795 | C5: ="Q" & INT((MONTH(B5)-1)/3) + 1 & " " & YEAR(B5) -> Q3 2022 | D5: 7500 | E5: 0 | F5: 0 | G5: 0 | H5: 0 | I5: 19 | J5: 12 | K5: 9 | L5: 17 | M5: 15 | N5: 3 | O5: 25 | P5: 36 | Q5: 48 | R5: 58 | S5: 62 | T5: 67 | U5: 82 | V5: 89 | W5: 96 | X5: 103 | Y5: 111 | Z5: 114
A6: xplor_technologies | B6: 44795 | C6: ="Q" & INT((MONTH(B6)-1)/3) + 1 & " " & YEAR(B6) -> Q3 2022 | D6: 8000 | E6: 0 | F6: 0 | G6: 0 | H6: 0 | I6: 5 | J6: 5 | K6: 6 | L6: 8 | M6: 4 | N6: 6 | O6: 11 | P6: 16 | Q6: 19 | R6: 22 | S6: 24 | T6: 28 | U6: 29 | V6: 31 | W6: 34 | X6: 35 | Y6: 38 | Z6: 41
A7: angi | B7: 44856 | C7: ="Q" & INT((MONTH(B7)-1)/3) + 1 & " " & YEAR(B7) -> Q4 2022 | D7: 10000 | E7: 0 | F7: 0 | G7: 0 | H7: 0 | I7: 0 | J7: 1 | K7: 4 | L7: 2 | M7: 4 | N7: 7 | O7: 8 | P7: 15 | Q7: 16 | R7: 19 | S7: 19 | T7: 24 | U7: 30 | V7: 30 | W7: 31 | X7: 34 | Y7: 36 | Z7: 42
A8: snowplow | B8: 44857 | C8: ="Q" & INT((MONTH(B8)-1)/3) + 1 & " " & YEAR(B8) -> Q4 2022 | D8: 2000 | E8: 0 | F8: 0 | G8: 0 | H8: 0 | I8: 0 | J8: 0 | K8: 0 | L8: 0 | M8: 0 | N8: 2 | O8: 2 | P8: 4 | Q8: 5 | R8: 6 | S8: 9 | T8: 11 | U8: 13 | V8: 14 | W8: 15 | X8: 15 | Y8: 18 | Z8: 18
A9: findmypast | B9: 44887 | C9: ="Q" & INT((MONTH(B9)-1)/3) + 1 & " " & YEAR(B9) -> Q4 2022 | D9: 1200 | E9: 0 | F9: 0 | G9: 0 | H9: 0 | I9: 0 | J9: 0 | K9: 0 | L9: 3 | M9: 3 | N9: 12 | O9: 12 | P9: 16 | Q9: 19 | R9: 19 | S9: 19 | T9: 20 | U9: 22 | V9: 23 | W9: 24 | X9: 24 | Y9: 26 | Z9: 30
A10: predictive_index | B10: 44887 | C10: ="Q" & INT((MONTH(B10)-1)/3) + 1 & " " & YEAR(B10) -> Q4 2022 | D10: 2000 | E10: 0 | F10: 0 | G10: 0 | H10: 0 | I10: 0 | J10: 0 | K10: 3 | L10: 2 | M10: 2 | N10: 7 | O10: 8 | P10: 12 | Q10: 12 | R10: 13 | S10: 16 | T10: 19 | U10: 20 | V10: 22 | W10: 23 | X10: 26 | Y10: 27 | Z10: 27
A11: biorender | B11: 44917 | C11: ="Q" & INT((MONTH(B11)-1)/3) + 1 & " " & YEAR(B11) -> Q4 2022 | D11: 2000 | E11: 0 | F11: 0 | G11: 0 | H11: 0 | I11: 0 | J11: 0 | K11: 0 | L11: 0 | M11: 0 | N11: 7 | O11: 10 | P11: 13 | Q11: 21 | R11: 23 | S11: 31 | T11: 38 | U11: 39 | V11: 43 | W11: 46 | X11: 48 | Y11: 53 | Z11: 58
A12: checkr | B12: 44917 | C12: ="Q" & INT((MONTH(B12)-1)/3) + 1 & " " & YEAR(B12) -> Q4 2022 | D12: 10000 | E12: 0 | F12: 0 | G12: 0 | H12: 0 | I12: 0 | J12: 0 | K12: 0 | L12: 0 | M12: 0 | N12: 2 | O12: 2 | P12: 3 | Q12: 5 | R12: 5 | S12: 10 | T12: 11 | U12: 15 | V12: 19 | W12: 20 | X12: 22 | Y12: 25 | Z12: 28
A13: g-p | B13: 44917 | C13: ="Q" & INT((MONTH(B13)-1)/3) + 1 & " " & YEAR(B13) -> Q4 2022 | D13: 10000 | E13: 0 | F13: 0 | G13: 0 | H13: 0 | I13: 0 | J13: 0 | K13: 0 | L13: 0 | M13: 0 | N13: 0 | O13: 0 | P13: 1 | Q13: 2 | R13: 4 | S13: 10 | T13: 13 | U13: 15 | V13: 22 | W13: 23 | X13: 24 | Y13: 28 | Z13: 29
A14: teachable | B14: 44917 | C14: ="Q" & INT((MONTH(B14)-1)/3) + 1 & " " & YEAR(B14) -> Q4 2022 | D14: 3000 | E14: 0 | F14: 0 | G14: 0 | H14: 0 | I14: 0 | J14: 0 | K14: 0 | L14: 0 | M14: 1 | N14: 8 | O14: 11 | P14: 19 | Q14: 21 | R14: 26 | S14: 31 | T14: 35 | U14: 36 | V14: 43 | W14: 46 | X14: 50 | Y14: 55 | Z14: 57
... A48: cloudflare | B48: 45375 | C48: ="Q" & INT((MONTH(B48)-1)/3) + 1 & " " & YEAR(B48) -> Q1 2024 | D48: 20000 | E48: 0 | F48: 0 | G48: 0 | H48: 0 | I48: 0 | J48: 0 | K48: 0 | L48: 0 | M48: 0 | N48: 0 | O48: 0 | P48: 0 | Q48: 0 | R48: 0 | S48: 0 | T48: 0 | U48: 0 | V48: 0 | W48: 0 | X48: 0 | Y48: 0 | Z48: 1

Sheet Sheet5
A1: https://app.amplitude.com/analytics/rallyuxr/chart/o5w4lyo/edit/69zjz4ud
A2: slug | B2: close date | C2: quarter | D2: ACV | E2: 44652 | F2: 44682 | G2: 44713 | H2: 44743 | I2: 44774 | J2: 44805 | K2: 44835 | L2: 44866 | M2: 44896 | N2: 44986 | O2: 45017 | P2: 45047 | Q2: 45078 | R2: 45108 | S2: 45139 | T2: 45170 | U2: 45200 | V2: 45231 | W2: 45261 | X2: 45292 | Y2: 45323 | Z2: 45352
A3: hellofresh | B3: 44645 | C3: ="Q" & INT((MONTH(B3)-1)/3) + 1 & " " & YEAR(B3) -> Q1 2022 | D3: 25000 | E3: 0 | F3: 0 | G3: 0 | H3: 0 | I3: 1 | J3: 0 | K3: 0 | L3: 4 | M3: 0 | N3: 2 | O3: 0 | P3: 0 | Q3: 0 | R3: 3 | S3: 5 | T3: 0 | U3: 4 | V3: 0 | W3: 1 | X3: 1 | Y3: 0 | Z3: 0
A4: consensys | B4: 44795 | C4: ="Q" & INT((MONTH(B4)-1)/3) + 1 & " " & YEAR(B4) -> Q3 2022 | D4: 3000 | E4: 0 | F4: 0 | G4: 0 | H4: 0 | I4: 3 | J4: 7 | K4: 0 | L4: 0 | M4: 0 | N4: 3 | O4: 2 | P4: 1 | Q4: 0 | R4: 0 | S4: 0 | T4: 0 | U4: 0 | V4: 1 | W4: 0 | X4: 0 | Y4: 0 | Z4: 0
A5: pandadoc | B5: 44795 | C5: ="Q" & INT((MONTH(B5)-1)/3) + 1 & " " & YEAR(B5) -> Q3 2022 | D5: 7500 | E5: 0 | F5: 0 | G5: 0 | H5: 0 | I5: 19 | J5: 12 | K5: 9 | L5: 17 | M5: 15 | N5: 3 | O5: 22 | P5: 11 | Q5: 12 | R5: 10 | S5: 4 | T5: 5 | U5: 15 | V5: 7 | W5: 7 | X5: 7 | Y5: 8 | Z5: 3
A6: xplor_technologies | B6: 44795 | C6: ="Q" & INT((MONTH(B6)-1)/3) + 1 & " " & YEAR(B6) -> Q3 2022 | D6: 8000 | E6: 0 | F6: 0 | G6: 0 | H6: 0 | I6: 5 | J6: 5 | K6: 6 | L6: 8 | M6: 4 | N6: 6 | O6: 5 | P6: 5 | Q6: 3 | R6: 3 | S6: 2 | T6: 4 | U6: 1 | V6: 2 | W6: 3 | X6: 1 | Y6: 3 | Z6: 3
A7: angi | B7: 44856 | C7: ="Q" & INT((MONTH(B7)-1)/3) + 1 & " " & YEAR(B7) -> Q4 2022 | D7: 10000 | E7: 0 | F7: 0 | G7: 0 | H7: 0 | I7: 0 | J7: 1 | K7: 4 | L7: 2 | M7: 4 | N7: 7 | O7: 1 | P7: 7 | Q7: 1 | R7: 3 | S7: 0 | T7: 5 | U7: 6 | V7: 0 | W7: 1 | X7: 3 | Y7: 2 | Z7: 6
A8: snowplow | B8: 44857 | C8: ="Q" & INT((MONTH(B8)-1)/3) + 1 & " " & YEAR(B8) -> Q4 2022 | D8: 2000 | E8: 0 | F8: 0 | G8: 0 | H8: 0 | I8: 0 | J8: 0 | K8: 0 | L8: 0 | M8: 0 | N8: 2 | O8: 0 | P8: 2 | Q8: 1 | R8: 1 | S8: 3 | T8: 2 | U8: 2 | V8: 1 | W8: 1 | X8: 0 | Y8: 3 | Z8: 0
A9: findmypast | B9: 44887 | C9: ="Q" & INT((MONTH(B9)-1)/3) + 1 & " " & YEAR(B9) -> Q4 2022 | D9: 1200 | E9: 0 | F9: 0 | G9: 0 | H9: 0 | I9: 0 | J9: 0 | K9: 0 | L9: 3 | M9: 3 | N9: 12 | O9: 0 | P9: 4 | Q9: 3 | R9: 0 | S9: 0 | T9: 1 | U9: 2 | V9: 1 | W9: 1 | X9: 0 | Y9: 2 | Z9: 4
A10: predictive_index | B10: 44887 | C10: ="Q" & INT((MONTH(B10)-1)/3) + 1 & " " & YEAR(B10) -> Q4 2022 | D10: 2000 | E10: 0 | F10: 0 | G10: 0 | H10: 0 | I10: 0 | J10: 0 | K10: 3 | L10: 2 | M10: 2 | N10: 7 | O10: 1 | P10: 4 | Q10: 0 | R10: 1 | S10: 3 | T10: 3 | U10: 1 | V10: 2 | W10: 1 | X10: 3 | Y10: 1 | Z10: 0
A11: biorender | B11: 44917 | C11: ="Q" & INT((MONTH(B11)-1)/3) + 1 & " " & YEAR(B11) -> Q4 2022 | D11: 2000 | E11: 0 | F11: 0 | G11: 0 | H11: 0 | I11: 0 | J11: 0 | K11: 0 | L11: 0 | M11: 0 | N11: 7 | O11: 3 | P11: 3 | Q11: 8 | R11: 2 | S11: 8 | T11: 7 | U11: 1 | V11: 4 | W11: 3 | X11: 2 | Y11: 5 | Z11: 5
A12: checkr | B12: 44917 | C12: ="Q" & INT((MONTH(B12)-1)/3) + 1 & " " & YEAR(B12) -> Q4 2022 | D12: 10000 | E12: 0 | F12: 0 | G12: 0 | H12: 0 | I12: 0 | J12: 0 | K12: 0 | L12: 0 | M12: 0 | N12: 2 | O12: 0 | P12: 1 | Q12: 2 | R12: 0 | S12: 5 | T12: 1 | U12: 4 | V12: 4 | W12: 1 | X12: 2 | Y12: 3 | Z12: 3
A13: g-p | B13: 44917 | C13: ="Q" & INT((MONTH(B13)-1)/3) + 1 & " " & YEAR(B13) -> Q4 2022 | D13: 10000 | E13: 0 | F13: 0 | G13: 0 | H13: 0 | I13: 0 | J13: 0 | K13: 0 | L13: 0 | M13: 0 | N13: 0 | O13: 0 | P13: 1 | Q13: 1 | R13: 2 | S13: 6 | T13: 3 | U13: 2 | V13: 7 | W13: 1 | X13: 1 | Y13: 4 | Z13: 1
A14: teachable | B14: 44917 | C14: ="Q" & INT((MONTH(B14)-1)/3) + 1 & " " & YEAR(B14) -> Q4 2022 | D14: 3000 | E14: 0 | F14: 0 | G14: 0 | H14: 0 | I14: 0 | J14: 0 | K14: 0 | L14: 0 | M14: 1 | N14: 8 | O14: 3 | P14: 8 | Q14: 2 | R14: 5 | S14: 5 | T14: 4 | U14: 1 | V14: 7 | W14: 3 | X14: 4 | Y14: 5 | Z14: 2
... A48: cloudflare | B48: 45375 | C48: ="Q" & INT((MONTH(B48)-1)/3) + 1 & " " & YEAR(B48) -> Q1 2024 | D48: 20000 | E48: 0 | F48: 0 | G48: 0 | H48: 0 | I48: 0 | J48: 0 | K48: 0 | L48: 0 | M48: 0 | N48: 0 | O48: 0 | P48: 0 | Q48: 0 | R48: 0 | S48: 0 | T48: 0 | U48: 0 | V48: 0 | W48: 0 | X48: 0 | Y48: 0 | Z48: 1

Sheet Copy of ICP Customers
A1: slug | B1: close date | C1: quarter | D1: ACV
A2: hellofresh | B2: 44645 | C2: ="Q" & INT((MONTH(B2)-1)/3) + 1 & " " & YEAR(B2) -> Q1 2022 | D2: 25000
A3: consensys | B3: 44795 | C3: ="Q" & INT((MONTH(B3)-1)/3) + 1 & " " & YEAR(B3) -> Q3 2022 | D3: 3000
A4: pandadoc | B4: 44795 | C4: ="Q" & INT((MONTH(B4)-1)/3) + 1 & " " & YEAR(B4) -> Q3 2022 | D4: 7500
A5: xplor_technologies | B5: 44795 | C5: ="Q" & INT((MONTH(B5)-1)/3) + 1 & " " & YEAR(B5) -> Q3 2022 | D5: 8000
A6: angi | B6: 44856 | C6: ="Q" & INT((MONTH(B6)-1)/3) + 1 & " " & YEAR(B6) -> Q4 2022 | D6: 10000
A7: snowplow | B7: 44857 | C7: ="Q" & INT((MONTH(B7)-1)/3) + 1 & " " & YEAR(B7) -> Q4 2022 | D7: 2000
A8: findmypast | B8: 44887 | C8: ="Q" & INT((MONTH(B8)-1)/3) + 1 & " " & YEAR(B8) -> Q4 2022 | D8: 1200
A9: predictive_index | B9: 44887 | C9: ="Q" & INT((MONTH(B9)-1)/3) + 1 & " " & YEAR(B9) -> Q4 2022 | D9: 2000
A10: biorender | B10: 44917 | C10: ="Q" & INT((MONTH(B10)-1)/3) + 1 & " " & YEAR(B10) -> Q4 2022 | D10: 2000
A11: checkr | B11: 44917 | C11: ="Q" & INT((MONTH(B11)-1)/3) + 1 & " " & YEAR(B11) -> Q4 2022 | D11: 10000
A12: g-p | B12: 44917 | C12: ="Q" & INT((MONTH(B12)-1)/3) + 1 & " " & YEAR(B12) -> Q4 2022 | D12: 10000
A13: teachable | B13: 44917 | C13: ="Q" & INT((MONTH(B13)-1)/3) + 1 & " " & YEAR(B13) -> Q4 2022 | D13: 3000
... A47: cloudflare | B47: 45375 | C47: ="Q" & INT((MONTH(B47)-1)/3) + 1 & " " & YEAR(B47) -> Q1 2024 | D47: 20000

Sheet 📈 LIR 
C1: LIR - Studies Published Monthly
C3: KEY | H3: GOAL
C4: 1 | D4: Threshold | K4: % Customers Achieving LIR | L4: =SUM(V11:V51)/COUNT(V11:V51) -> #N/A
D5: LIR Achieved | K5: Goal | L5: 0.7
D6: LIR Not Achieved
C10: Company | D10: Month Closed | E10: ACV | F10: Contract Year | G10: ICP? | H10: <LIR Metric> | I10: Month 1 | J10: Month 2 | K10: Month 3 | L10: Month 4 | M10: Month 5 | N10: Month 6 | O10: Month 7 | P10: Month 8 | Q10: Month 9 | R10: Month 10 | S10: Month 11 | T10: Month 12 | V10: Current LIR | W10: Notes
D11: ='Studies (Monthly) RAW'!B4 -> 45047 | E11: ='Studies (Cum) RAW'!C4 -> 15000 | F11: 1 | G11: TRUE | H11: ='Studies (Monthly) RAW'!E4 -> 2 | I11: =IF(EQ('Studies (Monthly) RAW'!F4,""),"", (IF(('Studies (Monthly) RAW'!F4/$H11)<$C$4, 0, 1))) -> #NAME? | J11: =IF(EQ('Studies (Monthly) RAW'!G4, ""),"", (IF(('Studies (Monthly) RAW'!G4/$H11)<$C$4, 0, 1))) -> #NAME? | K11: =IF(EQ('Studies (Monthly) RAW'!H4,""),"", (IF(('Studies (Monthly) RAW'!H4/$H11)<$C$4, 0, 1))) -> #NAME? | L11: =IF(EQ('Studies (Monthly) RAW'!I4, ""),"", (IF(('Studies (Monthly) RAW'!I4/$H11)<$C$4, 0, 1))) -> #NAME? | M11: =IF(EQ('Studies (Monthly) RAW'!J4,""),"", (IF(('Studies (Monthly) RAW'!J4/$H11)<$C$4, 0, 1))) -> #NAME? | N11: =IF(EQ('Studies (Monthly) RAW'!K4, ""),"", (IF(('Studies (Monthly) RAW'!K4/$H11)<$C$4, 0, 1))) -> #NAME? | O11: =IF(EQ('Studies (Monthly) RAW'!L4,""),"", (IF(('Studies (Monthly) RAW'!L4/$H11)<$C$4, 0, 1))) -> #NAME? | P11: =IF(EQ('Studies (Monthly) RAW'!M4, ""),"", (IF(('Studies (Monthly) RAW'!M4/$H11)<$C$4, 0, 1))) -> #NAME? | Q11: =IF(EQ('Studies (Monthly) RAW'!N4,""),"", (IF(('Studies (Monthly) RAW'!N4/$H11)<$C$4, 0, 1))) -> #NAME? | R11: =IF(EQ('Studies (Monthly) RAW'!O4, ""),"", (IF(('Studies (Monthly) RAW'!O4/$H11)<$C$4, 0, 1))) -> #NAME? | S11: =IF(EQ('Studies (Monthly) RAW'!P4,""),"", (IF(('Studies (Monthly) RAW'!P4/$H11)<$C$4, 0, 1))) -> #NAME? | T11: =IF(EQ('Studies (Monthly) RAW'!Q4, ""),"", (IF(('Studies (Monthly) RAW'!Q4/$H11)<$C$4, 0, 1))) -> #NAME? | V11: {=LOOKUP(2,1/(H11:U11<>""),H11:U11)} -> 2
G12: FALSE | V12: {=LOOKUP(2,1/(H12:U12<>""),H12:U12)} -> #N/A
G13: TRUE | V13: {=LOOKUP(2,1/(H13:U13<>""),H13:U13)} -> #N/A
G14: TRUE | V14: {=LOOKUP(2,1/(H14:U14<>""),H14:U14)} -> #N/A
G15: TRUE | V15: {=LOOKUP(2,1/(H15:U15<>""),H15:U15)} -> #N/A
G16: TRUE | V16: {=LOOKUP(2,1/(H16:U16<>""),H16:U16)} -> #N/A
G17: TRUE | V17: {=LOOKUP(2,1/(H17:U17<>""),H17:U17)} -> #N/A
G18: FALSE | V18: {=LOOKUP(2,1/(H18:U18<>""),H18:U18)} -> #N/A
G19: TRUE | V19: {=LOOKUP(2,1/(H19:U19<>""),H19:U19)} -> #N/A
G20: TRUE | V20: {=LOOKUP(2,1/(H20:U20<>""),H20:U20)} -> #N/A
G21: FALSE | V21: {=LOOKUP(2,1/(H21:U21<>""),H21:U21)} -> #N/A
G22: TRUE | V22: {=LOOKUP(2,1/(H22:U22<>""),H22:U22)} -> #N/A
G23: TRUE | V23: {=LOOKUP(2,1/(H23:U23<>""),H23:U23)} -> #N/A
... G51: FALSE | V51: {=LOOKUP(2,1/(H51:U51<>""),H51:U51)} -> #N/A
C52: ='Studies (Monthly) RAW'!A45 -> 0 | D52: ='Studies (Monthly) RAW'!B45 -> #VALUE! | E52: ='Studies (Monthly) RAW'!C45 -> 0 | H52: ='Studies (Monthly) RAW'!E45 -> 0 | I52: =IF(EQ('Studies (Monthly) RAW'!F45,""),"", (IF(('Studies (Monthly) RAW'!F45/$H52)<$C$4, 0, 1))) -> #NAME? | J52: =IF(EQ('Studies (Monthly) RAW'!G45, ""),"", (IF(('Studies (Monthly) RAW'!G45/$H52)<$C$4, 0, 1))) -> #NAME? | K52: =IF(EQ('Studies (Monthly) RAW'!H45,""),"", (IF(('Studies (Monthly) RAW'!H45/$H52)<$C$4, 0, 1))) -> #NAME? | L52: =IF(EQ('Studies (Monthly) RAW'!I45, ""),"", (IF(('Studies (Monthly) RAW'!I45/$H52)<$C$4, 0, 1))) -> #NAME? | M52: =IF(EQ('Studies (Monthly) RAW'!J45,""),"", (IF(('Studies (Monthly) RAW'!J45/$H52)<$C$4, 0, 1))) -> #NAME? | N52: =IF(EQ('Studies (Monthly) RAW'!K45, ""),"", (IF(('Studies (Monthly) RAW'!K45/$H52)<$C$4, 0, 1))) -> #NAME? | O52: =IF(EQ('Studies (Monthly) RAW'!L45,""),"", (IF(('Studies (Monthly) RAW'!L45/$H52)<$C$4, 0, 1))) -> #NAME? | P52: =IF(EQ('Studies (Monthly) RAW'!M45, ""),"", (IF(('Studies (Monthly) RAW'!M45/$H52)<$C$4, 0, 1))) -> #NAME? | Q52: =IF(EQ('Studies (Monthly) RAW'!N45,""),"", (IF(('Studies (Monthly) RAW'!N45/$H52)<$C$4, 0, 1))) -> #NAME? | R52: =IF(EQ('Studies (Monthly) RAW'!O45, ""),"", (IF(('Studies (Monthly) RAW'!O45/$H52)<$C$4, 0, 1))) -> #NAME? | S52: =IF(EQ('Studies (Monthly) RAW'!P45,""),"", (IF(('Studies (Monthly) RAW'!P45/$H52)<$C$4, 0, 1))) -> #NAME? | T52: =IF(EQ('Studies (Monthly) RAW'!Q45, ""),"", (IF(('Studies (Monthly) RAW'!Q45/$H52)<$C$4, 0, 1))) -> #NAME?
C53: ='Studies (Monthly) RAW'!A46 -> 0 | D53: ='Studies (Monthly) RAW'!B46 -> #VALUE! | E53: ='Studies (Monthly) RAW'!C46 -> 0 | G53: ='Studies (Monthly) RAW'!D46 -> 0 | H53: ='Studies (Monthly) RAW'!E46 -> 0 | I53: =IF(EQ('Studies (Monthly) RAW'!F46,""),"", (IF(('Studies (Monthly) RAW'!F46/$H53)<$C$4, 0, 1))) -> #NAME? | J53: =IF(EQ('Studies (Monthly) RAW'!G46, ""),"", (IF(('Studies (Monthly) RAW'!G46/$H53)<$C$4, 0, 1))) -> #NAME? | K53: =IF(EQ('Studies (Monthly) RAW'!H46,""),"", (IF(('Studies (Monthly) RAW'!H46/$H53)<$C$4, 0, 1))) -> #NAME? | L53: =IF(EQ('Studies (Monthly) RAW'!I46, ""),"", (IF(('Studies (Monthly) RAW'!I46/$H53)<$C$4, 0, 1))) -> #NAME? | M53: =IF(EQ('Studies (Monthly) RAW'!J46,""),"", (IF(('Studies (Monthly) RAW'!J46/$H53)<$C$4, 0, 1))) -> #NAME? | N53: =IF(EQ('Studies (Monthly) RAW'!K46, ""),"", (IF(('Studies (Monthly) RAW'!K46/$H53)<$C$4, 0, 1))) -> #NAME? | O53: =IF(EQ('Studies (Monthly) RAW'!L46,""),"", (IF(('Studies (Monthly) RAW'!L46/$H53)<$C$4, 0, 1))) -> #NAME? | P53: =IF(EQ('Studies (Monthly) RAW'!M46, ""),"", (IF(('Studies (Monthly) RAW'!M46/$H53)<$C$4, 0, 1))) -> #NAME? | Q53: =IF(EQ('Studies (Monthly) RAW'!N46,""),"", (IF(('Studies (Monthly) RAW'!N46/$H53)<$C$4, 0, 1))) -> #NAME? | R53: =IF(EQ('Studies (Monthly) RAW'!O46, ""),"", (IF(('Studies (Monthly) RAW'!O46/$H53)<$C$4, 0, 1))) -> #NAME? | S53: =IF(EQ('Studies (Monthly) RAW'!P46,""),"", (IF(('Studies (Monthly) RAW'!P46/$H53)<$C$4, 0, 1))) -> #NAME? | T53: =IF(EQ('Studies (Monthly) RAW'!Q46, ""),"", (IF(('Studies (Monthly) RAW'!Q46/$H53)<$C$4, 0, 1))) -> #NAME?
C54: ='Studies (Monthly) RAW'!A47 -> 0 | D54: ='Studies (Monthly) RAW'!B47 -> #VALUE! | E54: ='Studies (Monthly) RAW'!C47 -> 0 | G54: ='Studies (Monthly) RAW'!D47 -> 0 | H54: ='Studies (Monthly) RAW'!E47 -> 0 | I54: =IF(EQ('Studies (Monthly) RAW'!F47,""),"", (IF(('Studies (Monthly) RAW'!F47/$H54)<$C$4, 0, 1))) -> #NAME? | J54: =IF(EQ('Studies (Monthly) RAW'!G47, ""),"", (IF(('Studies (Monthly) RAW'!G47/$H54)<$C$4, 0, 1))) -> #NAME? | K54: =IF(EQ('Studies (Monthly) RAW'!H47,""),"", (IF(('Studies (Monthly) RAW'!H47/$H54)<$C$4, 0, 1))) -> #NAME? | L54: =IF(EQ('Studies (Monthly) RAW'!I47, ""),"", (IF(('Studies (Monthly) RAW'!I47/$H54)<$C$4, 0, 1))) -> #NAME? | M54: =IF(EQ('Studies (Monthly) RAW'!J47,""),"", (IF(('Studies (Monthly) RAW'!J47/$H54)<$C$4, 0, 1))) -> #NAME? | N54: =IF(EQ('Studies (Monthly) RAW'!K47, ""),"", (IF(('Studies (Monthly) RAW'!K47/$H54)<$C$4, 0, 1))) -> #NAME? | O54: =IF(EQ('Studies (Monthly) RAW'!L47,""),"", (IF(('Studies (Monthly) RAW'!L47/$H54)<$C$4, 0, 1))) -> #NAME? | P54: =IF(EQ('Studies (Monthly) RAW'!M47, ""),"", (IF(('Studies (Monthly) RAW'!M47/$H54)<$C$4, 0, 1))) -> #NAME? | Q54: =IF(EQ('Studies (Monthly) RAW'!N47,""),"", (IF(('Studies (Monthly) RAW'!N47/$H54)<$C$4, 0, 1))) -> #NAME? | R54: =IF(EQ('Studies (Monthly) RAW'!O47, ""),"", (IF(('Studies (Monthly) RAW'!O47/$H54)<$C$4, 0, 1))) -> #NAME? | S54: =IF(EQ('Studies (Monthly) RAW'!P47,""),"", (IF(('Studies (Monthly) RAW'!P47/$H54)<$C$4, 0, 1))) -> #NAME? | T54: =IF(EQ('Studies (Monthly) RAW'!Q47, ""),"", (IF(('Studies (Monthly) RAW'!Q47/$H54)<$C$4, 0, 1))) -> #NAME?
C55: ='Studies (Monthly) RAW'!A48 -> 0 | D55: ='Studies (Monthly) RAW'!B48 -> #VALUE! | E55: ='Studies (Monthly) RAW'!C48 -> 0 | G55: ='Studies (Monthly) RAW'!D48 -> 0 | H55: ='Studies (Monthly) RAW'!E48 -> 0 | I55: =IF(EQ('Studies (Monthly) RAW'!F48,""),"", (IF(('Studies (Monthly) RAW'!F48/$H55)<$C$4, 0, 1))) -> #NAME? | J55: =IF(EQ('Studies (Monthly) RAW'!G48, ""),"", (IF(('Studies (Monthly) RAW'!G48/$H55)<$C$4, 0, 1))) -> #NAME? | K55: =IF(EQ('Studies (Monthly) RAW'!H48,""),"", (IF(('Studies (Monthly) RAW'!H48/$H55)<$C$4, 0, 1))) -> #NAME? | L55: =IF(EQ('Studies (Monthly) RAW'!I48, ""),"", (IF(('Studies (Monthly) RAW'!I48/$H55)<$C$4, 0, 1))) -> #NAME? | M55: =IF(EQ('Studies (Monthly) RAW'!J48,""),"", (IF(('Studies (Monthly) RAW'!J48/$H55)<$C$4, 0, 1))) -> #NAME? | N55: =IF(EQ('Studies (Monthly) RAW'!K48, ""),"", (IF(('Studies (Monthly) RAW'!K48/$H55)<$C$4, 0, 1))) -> #NAME? | O55: =IF(EQ('Studies (Monthly) RAW'!L48,""),"", (IF(('Studies (Monthly) RAW'!L48/$H55)<$C$4, 0, 1))) -> #NAME? | P55: =IF(EQ('Studies (Monthly) RAW'!M48, ""),"", (IF(('Studies (Monthly) RAW'!M48/$H55)<$C$4, 0, 1))) -> #NAME? | Q55: =IF(EQ('Studies (Monthly) RAW'!N48,""),"", (IF(('Studies (Monthly) RAW'!N48/$H55)<$C$4, 0, 1))) -> #NAME? | R55: =IF(EQ('Studies (Monthly) RAW'!O48, ""),"", (IF(('Studies (Monthly) RAW'!O48/$H55)<$C$4, 0, 1))) -> #NAME? | S55: =IF(EQ('Studies (Monthly) RAW'!P48,""),"", (IF(('Studies (Monthly) RAW'!P48/$H55)<$C$4, 0, 1))) -> #NAME? | T55: =IF(EQ('Studies (Monthly) RAW'!Q48, ""),"", (IF(('Studies (Monthly) RAW'!Q48/$H55)<$C$4, 0, 1))) -> #NAME?
C56: ='Studies (Monthly) RAW'!A49 -> 0 | D56: ='Studies (Monthly) RAW'!B49 -> #VALUE! | E56: ='Studies (Monthly) RAW'!C49 -> 0 | G56: ='Studies (Monthly) RAW'!D49 -> 0 | H56: ='Studies (Monthly) RAW'!E49 -> 0 | I56: =IF(EQ('Studies (Monthly) RAW'!F49,""),"", (IF(('Studies (Monthly) RAW'!F49/$H56)<$C$4, 0, 1))) -> #NAME? | J56: =IF(EQ('Studies (Monthly) RAW'!G49, ""),"", (IF(('Studies (Monthly) RAW'!G49/$H56)<$C$4, 0, 1))) -> #NAME? | K56: =IF(EQ('Studies (Monthly) RAW'!H49,""),"", (IF(('Studies (Monthly) RAW'!H49/$H56)<$C$4, 0, 1))) -> #NAME? | L56: =IF(EQ('Studies (Monthly) RAW'!I49, ""),"", (IF(('Studies (Monthly) RAW'!I49/$H56)<$C$4, 0, 1))) -> #NAME? | M56: =IF(EQ('Studies (Monthly) RAW'!J49,""),"", (IF(('Studies (Monthly) RAW'!J49/$H56)<$C$4, 0, 1))) -> #NAME? | N56: =IF(EQ('Studies (Monthly) RAW'!K49, ""),"", (IF(('Studies (Monthly) RAW'!K49/$H56)<$C$4, 0, 1))) -> #NAME? | O56: =IF(EQ('Studies (Monthly) RAW'!L49,""),"", (IF(('Studies (Monthly) RAW'!L49/$H56)<$C$4, 0, 1))) -> #NAME? | P56: =IF(EQ('Studies (Monthly) RAW'!M49, ""),"", (IF(('Studies (Monthly) RAW'!M49/$H56)<$C$4, 0, 1))) -> #NAME? | Q56: =IF(EQ('Studies (Monthly) RAW'!N49,""),"", (IF(('Studies (Monthly) RAW'!N49/$H56)<$C$4, 0, 1))) -> #NAME? | R56: =IF(EQ('Studies (Monthly) RAW'!O49, ""),"", (IF(('Studies (Monthly) RAW'!O49/$H56)<$C$4, 0, 1))) -> #NAME? | S56: =IF(EQ('Studies (Monthly) RAW'!P49,""),"", (IF(('Studies (Monthly) RAW'!P49/$H56)<$C$4, 0, 1))) -> #NAME? | T56: =IF(EQ('Studies (Monthly) RAW'!Q49, ""),"", (IF(('Studies (Monthly) RAW'!Q49/$H56)<$C$4, 0, 1))) -> #NAME?
C57: ='Studies (Monthly) RAW'!A50 -> 0 | D57: ='Studies (Monthly) RAW'!B50 -> #VALUE! | E57: ='Studies (Monthly) RAW'!C50 -> 0 | G57: ='Studies (Monthly) RAW'!D50 -> 0 | H57: ='Studies (Monthly) RAW'!E50 -> 0 | I57: =IF(EQ('Studies (Monthly) RAW'!F50,""),"", (IF(('Studies (Monthly) RAW'!F50/$H57)<$C$4, 0, 1))) -> #NAME? | J57: =IF(EQ('Studies (Monthly) RAW'!G50, ""),"", (IF(('Studies (Monthly) RAW'!G50/$H57)<$C$4, 0, 1))) -> #NAME? | K57: =IF(EQ('Studies (Monthly) RAW'!H50,""),"", (IF(('Studies (Monthly) RAW'!H50/$H57)<$C$4, 0, 1))) -> #NAME? | L57: =IF(EQ('Studies (Monthly) RAW'!I50, ""),"", (IF(('Studies (Monthly) RAW'!I50/$H57)<$C$4, 0, 1))) -> #NAME? | M57: =IF(EQ('Studies (Monthly) RAW'!J50,""),"", (IF(('Studies (Monthly) RAW'!J50/$H57)<$C$4, 0, 1))) -> #NAME? | N57: =IF(EQ('Studies (Monthly) RAW'!K50, ""),"", (IF(('Studies (Monthly) RAW'!K50/$H57)<$C$4, 0, 1))) -> #NAME? | O57: =IF(EQ('Studies (Monthly) RAW'!L50,""),"", (IF(('Studies (Monthly) RAW'!L50/$H57)<$C$4, 0, 1))) -> #NAME? | P57: =IF(EQ('Studies (Monthly) RAW'!M50, ""),"", (IF(('Studies (Monthly) RAW'!M50/$H57)<$C$4, 0, 1))) -> #NAME? | Q57: =IF(EQ('Studies (Monthly) RAW'!N50,""),"", (IF(('Studies (Monthly) RAW'!N50/$H57)<$C$4, 0, 1))) -> #NAME? | R57: =IF(EQ('Studies (Monthly) RAW'!O50, ""),"", (IF(('Studies (Monthly) RAW'!O50/$H57)<$C$4, 0, 1))) -> #NAME? | S57: =IF(EQ('Studies (Monthly) RAW'!P50,""),"", (IF(('Studies (Monthly) RAW'!P50/$H57)<$C$4, 0, 1))) -> #NAME? | T57: =IF(EQ('Studies (Monthly) RAW'!Q50, ""),"", (IF(('Studies (Monthly) RAW'!Q50/$H57)<$C$4, 0, 1))) -> #NAME?
C58: ='Studies (Monthly) RAW'!A51 -> 0 | D58: ='Studies (Monthly) RAW'!B51 -> #VALUE! | E58: ='Studies (Monthly) RAW'!C51 -> 0 | G58: ='Studies (Monthly) RAW'!D51 -> 0 | H58: ='Studies (Monthly) RAW'!E51 -> 0 | I58: =IF(EQ('Studies (Monthly) RAW'!F51,""),"", (IF(('Studies (Monthly) RAW'!F51/$H58)<$C$4, 0, 1))) -> #NAME? | J58: =IF(EQ('Studies (Monthly) RAW'!G51, ""),"", (IF(('Studies (Monthly) RAW'!G51/$H58)<$C$4, 0, 1))) -> #NAME? | K58: =IF(EQ('Studies (Monthly) RAW'!H51,""),"", (IF(('Studies (Monthly) RAW'!H51/$H58)<$C$4, 0, 1))) -> #NAME? | L58: =IF(EQ('Studies (Monthly) RAW'!I51, ""),"", (IF(('Studies (Monthly) RAW'!I51/$H58)<$C$4, 0, 1))) -> #NAME? | M58: =IF(EQ('Studies (Monthly) RAW'!J51,""),"", (IF(('Studies (Monthly) RAW'!J51/$H58)<$C$4, 0, 1))) -> #NAME? | N58: =IF(EQ('Studies (Monthly) RAW'!K51, ""),"", (IF(('Studies (Monthly) RAW'!K51/$H58)<$C$4, 0, 1))) -> #NAME? | O58: =IF(EQ('Studies (Monthly) RAW'!L51,""),"", (IF(('Studies (Monthly) RAW'!L51/$H58)<$C$4, 0, 1))) -> #NAME? | P58: =IF(EQ('Studies (Monthly) RAW'!M51, ""),"", (IF(('Studies (Monthly) RAW'!M51/$H58)<$C$4, 0, 1))) -> #NAME? | Q58: =IF(EQ('Studies (Monthly) RAW'!N51,""),"", (IF(('Studies (Monthly) RAW'!N51/$H58)<$C$4, 0, 1))) -> #NAME? | R58: =IF(EQ('Studies (Monthly) RAW'!O51, ""),"", (IF(('Studies (Monthly) RAW'!O51/$H58)<$C$4, 0, 1))) -> #NAME? | S58: =IF(EQ('Studies (Monthly) RAW'!P51,""),"", (IF(('Studies (Monthly) RAW'!P51/$H58)<$C$4, 0, 1))) -> #NAME? | T58: =IF(EQ('Studies (Monthly) RAW'!Q51, ""),"", (IF(('Studies (Monthly) RAW'!Q51/$H58)<$C$4, 0, 1))) -> #NAME?
C59: ='Studies (Monthly) RAW'!A52 -> 0 | D59: ='Studies (Monthly) RAW'!B52 -> #VALUE! | E59: ='Studies (Monthly) RAW'!C52 -> 0 | G59: ='Studies (Monthly) RAW'!D52 -> 0 | H59: ='Studies (Monthly) RAW'!E52 -> 0 | I59: =IF(EQ('Studies (Monthly) RAW'!F52,""),"", (IF(('Studies (Monthly) RAW'!F52/$H59)<$C$4, 0, 1))) -> #NAME? | J59: =IF(EQ('Studies (Monthly) RAW'!G52, ""),"", (IF(('Studies (Monthly) RAW'!G52/$H59)<$C$4, 0, 1))) -> #NAME? | K59: =IF(EQ('Studies (Monthly) RAW'!H52,""),"", (IF(('Studies (Monthly) RAW'!H52/$H59)<$C$4, 0, 1))) -> #NAME? | L59: =IF(EQ('Studies (Monthly) RAW'!I52, ""),"", (IF(('Studies (Monthly) RAW'!I52/$H59)<$C$4, 0, 1))) -> #NAME? | M59: =IF(EQ('Studies (Monthly) RAW'!J52,""),"", (IF(('Studies (Monthly) RAW'!J52/$H59)<$C$4, 0, 1))) -> #NAME? | N59: =IF(EQ('Studies (Monthly) RAW'!K52, ""),"", (IF(('Studies (Monthly) RAW'!K52/$H59)<$C$4, 0, 1))) -> #NAME? | O59: =IF(EQ('Studies (Monthly) RAW'!L52,""),"", (IF(('Studies (Monthly) RAW'!L52/$H59)<$C$4, 0, 1))) -> #NAME? | P59: =IF(EQ('Studies (Monthly) RAW'!M52, ""),"", (IF(('Studies (Monthly) RAW'!M52/$H59)<$C$4, 0, 1))) -> #NAME? | Q59: =IF(EQ('Studies (Monthly) RAW'!N52,""),"", (IF(('Studies (Monthly) RAW'!N52/$H59)<$C$4, 0, 1))) -> #NAME? | R59: =IF(EQ('Studies (Monthly) RAW'!O52, ""),"", (IF(('Studies (Monthly) RAW'!O52/$H59)<$C$4, 0, 1))) -> #NAME? | S59: =IF(EQ('Studies (Monthly) RAW'!P52,""),"", (IF(('Studies (Monthly) RAW'!P52/$H59)<$C$4, 0, 1))) -> #NAME? | T59: =IF(EQ('Studies (Monthly) RAW'!Q52, ""),"", (IF(('Studies (Monthly) RAW'!Q52/$H59)<$C$4, 0, 1))) -> #NAME?
C60: ='Studies (Monthly) RAW'!A53 -> 0 | D60: ='Studies (Monthly) RAW'!B53 -> #VALUE! | E60: ='Studies (Monthly) RAW'!C53 -> 0 | G60: ='Studies (Monthly) RAW'!D53 -> 0 | H60: ='Studies (Monthly) RAW'!E53 -> 0 | I60: =IF(EQ('Studies (Monthly) RAW'!F53,""),"", (IF(('Studies (Monthly) RAW'!F53/$H60)<$C$4, 0, 1))) -> #NAME? | J60: =IF(EQ('Studies (Monthly) RAW'!G53, ""),"", (IF(('Studies (Monthly) RAW'!G53/$H60)<$C$4, 0, 1))) -> #NAME? | K60: =IF(EQ('Studies (Monthly) RAW'!H53,""),"", (IF(('Studies (Monthly) RAW'!H53/$H60)<$C$4, 0, 1))) -> #NAME? | L60: =IF(EQ('Studies (Monthly) RAW'!I53, ""),"", (IF(('Studies (Monthly) RAW'!I53/$H60)<$C$4, 0, 1))) -> #NAME? | M60: =IF(EQ('Studies (Monthly) RAW'!J53,""),"", (IF(('Studies (Monthly) RAW'!J53/$H60)<$C$4, 0, 1))) -> #NAME? | N60: =IF(EQ('Studies (Monthly) RAW'!K53, ""),"", (IF(('Studies (Monthly) RAW'!K53/$H60)<$C$4, 0, 1))) -> #NAME? | O60: =IF(EQ('Studies (Monthly) RAW'!L53,""),"", (IF(('Studies (Monthly) RAW'!L53/$H60)<$C$4, 0, 1))) -> #NAME? | P60: =IF(EQ('Studies (Monthly) RAW'!M53, ""),"", (IF(('Studies (Monthly) RAW'!M53/$H60)<$C$4, 0, 1))) -> #NAME? | Q60: =IF(EQ('Studies (Monthly) RAW'!N53,""),"", (IF(('Studies (Monthly) RAW'!N53/$H60)<$C$4, 0, 1))) -> #NAME? | R60: =IF(EQ('Studies (Monthly) RAW'!O53, ""),"", (IF(('Studies (Monthly) RAW'!O53/$H60)<$C$4, 0, 1))) -> #NAME? | S60: =IF(EQ('Studies (Monthly) RAW'!P53,""),"", (IF(('Studies (Monthly) RAW'!P53/$H60)<$C$4, 0, 1))) -> #NAME? | T60: =IF(EQ('Studies (Monthly) RAW'!Q53, ""),"", (IF(('Studies (Monthly) RAW'!Q53/$H60)<$C$4, 0, 1))) -> #NAME?
C61: ='Studies (Monthly) RAW'!A54 -> 0 | D61: ='Studies (Monthly) RAW'!B54 -> #VALUE! | E61: ='Studies (Monthly) RAW'!C54 -> 0 | G61: ='Studies (Monthly) RAW'!D54 -> 0 | H61: ='Studies (Monthly) RAW'!E54 -> 0 | I61: =IF(EQ('Studies (Monthly) RAW'!F54,""),"", (IF(('Studies (Monthly) RAW'!F54/$H61)<$C$4, 0, 1))) -> #NAME? | J61: =IF(EQ('Studies (Monthly) RAW'!G54, ""),"", (IF(('Studies (Monthly) RAW'!G54/$H61)<$C$4, 0, 1))) -> #NAME? | K61: =IF(EQ('Studies (Monthly) RAW'!H54,""),"", (IF(('Studies (Monthly) RAW'!H54/$H61)<$C$4, 0, 1))) -> #NAME? | L61: =IF(EQ('Studies (Monthly) RAW'!I54, ""),"", (IF(('Studies (Monthly) RAW'!I54/$H61)<$C$4, 0, 1))) -> #NAME? | M61: =IF(EQ('Studies (Monthly) RAW'!J54,""),"", (IF(('Studies (Monthly) RAW'!J54/$H61)<$C$4, 0, 1))) -> #NAME? | N61: =IF(EQ('Studies (Monthly) RAW'!K54, ""),"", (IF(('Studies (Monthly) RAW'!K54/$H61)<$C$4, 0, 1))) -> #NAME? | O61: =IF(EQ('Studies (Monthly) RAW'!L54,""),"", (IF(('Studies (Monthly) RAW'!L54/$H61)<$C$4, 0, 1))) -> #NAME? | P61: =IF(EQ('Studies (Monthly) RAW'!M54, ""),"", (IF(('Studies (Monthly) RAW'!M54/$H61)<$C$4, 0, 1))) -> #NAME? | Q61: =IF(EQ('Studies (Monthly) RAW'!N54,""),"", (IF(('Studies (Monthly) RAW'!N54/$H61)<$C$4, 0, 1))) -> #NAME? | R61: =IF(EQ('Studies (Monthly) RAW'!O54, ""),"", (IF(('Studies (Monthly) RAW'!O54/$H61)<$C$4, 0, 1))) -> #NAME? | S61: =IF(EQ('Studies (Monthly) RAW'!P54,""),"", (IF(('Studies (Monthly) RAW'!P54/$H61)<$C$4, 0, 1))) -> #NAME? | T61: =IF(EQ('Studies (Monthly) RAW'!Q54, ""),"", (IF(('Studies (Monthly) RAW'!Q54/$H61)<$C$4, 0, 1))) -> #NAME?
C62: ='Studies (Monthly) RAW'!A55 -> 0 | D62: ='Studies (Monthly) RAW'!B55 -> #VALUE! | E62: ='Studies (Monthly) RAW'!C55 -> 0 | G62: ='Studies (Monthly) RAW'!D55 -> 0 | H62: ='Studies (Monthly) RAW'!E55 -> 0 | I62: =IF(EQ('Studies (Monthly) RAW'!F55,""),"", (IF(('Studies (Monthly) RAW'!F55/$H62)<$C$4, 0, 1))) -> #NAME? | J62: =IF(EQ('Studies (Monthly) RAW'!G55, ""),"", (IF(('Studies (Monthly) RAW'!G55/$H62)<$C$4, 0, 1))) -> #NAME? | K62: =IF(EQ('Studies (Monthly) RAW'!H55,""),"", (IF(('Studies (Monthly) RAW'!H55/$H62)<$C$4, 0, 1))) -> #NAME? | L62: =IF(EQ('Studies (Monthly) RAW'!I55, ""),"", (IF(('Studies (Monthly) RAW'!I55/$H62)<$C$4, 0, 1))) -> #NAME? | M62: =IF(EQ('Studies (Monthly) RAW'!J55,""),"", (IF(('Studies (Monthly) RAW'!J55/$H62)<$C$4, 0, 1))) -> #NAME? | N62: =IF(EQ('Studies (Monthly) RAW'!K55, ""),"", (IF(('Studies (Monthly) RAW'!K55/$H62)<$C$4, 0, 1))) -> #NAME? | O62: =IF(EQ('Studies (Monthly) RAW'!L55,""),"", (IF(('Studies (Monthly) RAW'!L55/$H62)<$C$4, 0, 1))) -> #NAME? | P62: =IF(EQ('Studies (Monthly) RAW'!M55, ""),"", (IF(('Studies (Monthly) RAW'!M55/$H62)<$C$4, 0, 1))) -> #NAME? | Q62: =IF(EQ('Studies (Monthly) RAW'!N55,""),"", (IF(('Studies (Monthly) RAW'!N55/$H62)<$C$4, 0, 1))) -> #NAME? | R62: =IF(EQ('Studies (Monthly) RAW'!O55, ""),"", (IF(('Studies (Monthly) RAW'!O55/$H62)<$C$4, 0, 1))) -> #NAME? | S62: =IF(EQ('Studies (Monthly) RAW'!P55,""),"", (IF(('Studies (Monthly) RAW'!P55/$H62)<$C$4, 0, 1))) -> #NAME? | T62: =IF(EQ('Studies (Monthly) RAW'!Q55, ""),"", (IF(('Studies (Monthly) RAW'!Q55/$H62)<$C$4, 0, 1))) -> #NAME?
C63: ='Studies (Monthly) RAW'!A56 -> 0 | D63: ='Studies (Monthly) RAW'!B56 -> #VALUE! | E63: ='Studies (Monthly) RAW'!C56 -> 0 | G63: ='Studies (Monthly) RAW'!D56 -> 0 | H63: ='Studies (Monthly) RAW'!E56 -> 0 | I63: =IF(EQ('Studies (Monthly) RAW'!F56,""),"", (IF(('Studies (Monthly) RAW'!F56/$H63)<$C$4, 0, 1))) -> #NAME? | J63: =IF(EQ('Studies (Monthly) RAW'!G56, ""),"", (IF(('Studies (Monthly) RAW'!G56/$H63)<$C$4, 0, 1))) -> #NAME? | K63: =IF(EQ('Studies (Monthly) RAW'!H56,""),"", (IF(('Studies (Monthly) RAW'!H56/$H63)<$C$4, 0, 1))) -> #NAME? | L63: =IF(EQ('Studies (Monthly) RAW'!I56, ""),"", (IF(('Studies (Monthly) RAW'!I56/$H63)<$C$4, 0, 1))) -> #NAME? | M63: =IF(EQ('Studies (Monthly) RAW'!J56,""),"", (IF(('Studies (Monthly) RAW'!J56/$H63)<$C$4, 0, 1))) -> #NAME? | N63: =IF(EQ('Studies (Monthly) RAW'!K56, ""),"", (IF(('Studies (Monthly) RAW'!K56/$H63)<$C$4, 0, 1))) -> #NAME? | O63: =IF(EQ('Studies (Monthly) RAW'!L56,""),"", (IF(('Studies (Monthly) RAW'!L56/$H63)<$C$4, 0, 1))) -> #NAME? | P63: =IF(EQ('Studies (Monthly) RAW'!M56, ""),"", (IF(('Studies (Monthly) RAW'!M56/$H63)<$C$4, 0, 1))) -> #NAME? | Q63: =IF(EQ('Studies (Monthly) RAW'!N56,""),"", (IF(('Studies (Monthly) RAW'!N56/$H63)<$C$4, 0, 1))) -> #NAME? | R63: =IF(EQ('Studies (Monthly) RAW'!O56, ""),"", (IF(('Studies (Monthly) RAW'!O56/$H63)<$C$4, 0, 1))) -> #NAME? | S63: =IF(EQ('Studies (Monthly) RAW'!P56,""),"", (IF(('Studies (Monthly) RAW'!P56/$H63)<$C$4, 0, 1))) -> #NAME? | T63: =IF(EQ('Studies (Monthly) RAW'!Q56, ""),"", (IF(('Studies (Monthly) RAW'!Q56/$H63)<$C$4, 0, 1))) -> #NAME?
C64: ='Studies (Monthly) RAW'!A57 -> 0 | D64: ='Studies (Monthly) RAW'!B57 -> #VALUE! | E64: ='Studies (Monthly) RAW'!C57 -> 0 | G64: ='Studies (Monthly) RAW'!D57 -> 0 | H64: ='Studies (Monthly) RAW'!E57 -> 0 | I64: =IF(EQ('Studies (Monthly) RAW'!F57,""),"", (IF(('Studies (Monthly) RAW'!F57/$H64)<$C$4, 0, 1))) -> #NAME? | J64: =IF(EQ('Studies (Monthly) RAW'!G57, ""),"", (IF(('Studies (Monthly) RAW'!G57/$H64)<$C$4, 0, 1))) -> #NAME? | K64: =IF(EQ('Studies (Monthly) RAW'!H57,""),"", (IF(('Studies (Monthly) RAW'!H57/$H64)<$C$4, 0, 1))) -> #NAME? | L64: =IF(EQ('Studies (Monthly) RAW'!I57, ""),"", (IF(('Studies (Monthly) RAW'!I57/$H64)<$C$4, 0, 1))) -> #NAME? | M64: =IF(EQ('Studies (Monthly) RAW'!J57,""),"", (IF(('Studies (Monthly) RAW'!J57/$H64)<$C$4, 0, 1))) -> #NAME? | N64: =IF(EQ('Studies (Monthly) RAW'!K57, ""),"", (IF(('Studies (Monthly) RAW'!K57/$H64)<$C$4, 0, 1))) -> #NAME? | O64: =IF(EQ('Studies (Monthly) RAW'!L57,""),"", (IF(('Studies (Monthly) RAW'!L57/$H64)<$C$4, 0, 1))) -> #NAME? | P64: =IF(EQ('Studies (Monthly) RAW'!M57, ""),"", (IF(('Studies (Monthly) RAW'!M57/$H64)<$C$4, 0, 1))) -> #NAME? | Q64: =IF(EQ('Studies (Monthly) RAW'!N57,""),"", (IF(('Studies (Monthly) RAW'!N57/$H64)<$C$4, 0, 1))) -> #NAME? | R64: =IF(EQ('Studies (Monthly) RAW'!O57, ""),"", (IF(('Studies (Monthly) RAW'!O57/$H64)<$C$4, 0, 1))) -> #NAME? | S64: =IF(EQ('Studies (Monthly) RAW'!P57,""),"", (IF(('Studies (Monthly) RAW'!P57/$H64)<$C$4, 0, 1))) -> #NAME? | T64: =IF(EQ('Studies (Monthly) RAW'!Q57, ""),"", (IF(('Studies (Monthly) RAW'!Q57/$H64)<$C$4, 0, 1))) -> #NAME?
... C99: ='Studies (Monthly) RAW'!A92 -> 0 | D99: ='Studies (Monthly) RAW'!B92 -> #VALUE! | E99: ='Studies (Monthly) RAW'!C92 -> 0 | G99: ='Studies (Monthly) RAW'!D92 -> 0 | H99: ='Studies (Monthly) RAW'!E92 -> 0 | I99: =IF(EQ('Studies (Monthly) RAW'!F92,""),"", (IF(('Studies (Monthly) RAW'!F92/$H99)<$C$4, 0, 1))) -> #NAME? | J99: =IF(EQ('Studies (Monthly) RAW'!G92, ""),"", (IF(('Studies (Monthly) RAW'!G92/$H99)<$C$4, 0, 1))) -> #NAME? | K99: =IF(EQ('Studies (Monthly) RAW'!H92,""),"", (IF(('Studies (Monthly) RAW'!H92/$H99)<$C$4, 0, 1))) -> #NAME? | L99: =IF(EQ('Studies (Monthly) RAW'!I92, ""),"", (IF(('Studies (Monthly) RAW'!I92/$H99)<$C$4, 0, 1))) -> #NAME? | M99: =IF(EQ('Studies (Monthly) RAW'!J92,""),"", (IF(('Studies (Monthly) RAW'!J92/$H99)<$C$4, 0, 1))) -> #NAME? | N99: =IF(EQ('Studies (Monthly) RAW'!K92, ""),"", (IF(('Studies (Monthly) RAW'!K92/$H99)<$C$4, 0, 1))) -> #NAME? | O99: =IF(EQ('Studies (Monthly) RAW'!L92,""),"", (IF(('Studies (Monthly) RAW'!L92/$H99)<$C$4, 0, 1))) -> #NAME? | P99: =IF(EQ('Studies (Monthly) RAW'!M92, ""),"", (IF(('Studies (Monthly) RAW'!M92/$H99)<$C$4, 0, 1))) -> #NAME? | Q99: =IF(EQ('Studies (Monthly) RAW'!N92,""),"", (IF(('Studies (Monthly) RAW'!N92/$H99)<$C$4, 0, 1))) -> #NAME? | R99: =IF(EQ('Studies (Monthly) RAW'!O92, ""),"", (IF(('Studies (Monthly) RAW'!O92/$H99)<$C$4, 0, 1))) -> #NAME? | S99: =IF(EQ('Studies (Monthly) RAW'!P92,""),"", (IF(('Studies (Monthly) RAW'!P92/$H99)<$C$4, 0, 1))) -> #NAME? | T99: =IF(EQ('Studies (Monthly) RAW'!Q92, ""),"", (IF(('Studies (Monthly) RAW'!Q92/$H99)<$C$4, 0, 1))) -> #NAME?

Sheet Customer Data - Source of Truth
A1: slug | B1: Expected 1st Year Studies Published | C1: Logo | D1: Contract Start Date | E1: Contract Year | F1: # of Seats | G1: ARR | H1: Category | I1: Sub-Category | J1: Source | K1: # of Employees | L1: Size of PWDR team (PM + Design) | M1: Size of UXR Team | N1: Size of ReOps Team
A2: 8x8 | B2: 24 | C2: 8x8 | D2: 45047 | E2: 1 | F2: 7 | G2: 15000 | H2: B2B | I2: Contact center | J2: Inbound | K2: 2500 | L2: 68 | M2: 6 | N2: 0
A3: adobe | B3: 36 | C3: Adobe | D3: 45292 | E3: 1 | F3: 5 | G3: 35000 | H3: B2C/B2B | I3: Creative, Marketing, Document Management | J3: Conference | K3: 30000 | L3: 3000 | M3: 35 | N3: 4
A4: adobe_community | B4: 36 | C4: Adobe Community | D4: 45292 | E4: 1 | F4: 5 | G4: 35000 | H4: B2C/B2B | I4: Creative, Marketing, Document Management | J4: Conference | K4: 30000 | L4: 3000 | M4: 35 | N4: 4
A5: angi | B5: 24 | C5: Angi | D5: 45200 | E5: 2 | F5: 3 | G5: 10000 | H5: Marketplace | I5: Community | J5: Inbound | K5: 3500 | L5: 102 | M5: 4 | N5: 0
A6: biorender | B6: 24 | C6: BioRender | D6: 45261 | E6: 2 | F6: 3 | G6: 15000 | H6: B2B | I6: Design | J6: Design Partner | K6: 207 | L6: 16 | M6: 2 | N6: 0
A7: blackbaud | B7: 48 | C7: Blackbaud | D7: 45292 | E7: 2 | F7: 80 | G7: 52500 | H7: B2B | I7: Education, non-profit | J7: Design Partner | K7: 3200 | L7: 143 | M7: 4 | N7: 0
A8: braze | B8: 24 | C8: Braze | D8: 45352 | E8: 2 | F8: -1 | G8: 25000 | H8: B2B | I8: Martech | J8: Inbound | K8: 1600 | L8: 90 | M8: 7 | N8: 0
A9: checkr | B9: 24 | C9: Checkr | D9: 45261 | E9: 2 | F9: 5 | G9: 12500 | H9: B2B | I9: background checks | J9: Inbound | K9: 1300 | L9: 34 | M9: 2 | N9: 0
A10: chegg | B10: 24 | C10: Chegg | D10: 45139 | E10: 1 | F10: 7 | G10: 25000 | H10: B2C | I10: Education, non-profit | J10: Inbound | K10: 11000 | L10: 218 | M10: 8 | N10: 0
A11: cloudflare | B11: 24 | C11: Cloudflare | D11: 45352 | E11: 1 | F11: 3 | G11: 20000 | H11: B2B | I11: IT / Cyber | J11: Inbound | K11: 4000 | L11: 120 | M11: 2 | N11: 0
A12: consensys | B12: 12 | C12: Consensys | D12: 45505 | E12: 2 | F12: 2 | G12: 2000 | H12: Web3 | I12: Crypto | J12: NA | K12: 853 | L12: 70 | M12: 4 | N12: 0
A13: convera | B13: 12 | C13: Convera | D13: 45047 | E13: 1 | F13: 5 | G13: 5000 | H13: B2B | I13: Fintech | J13: Inbound | K13: 1500 | L13: 46 | M13: 1 | N13: 0
... A45: zwift | B45: 12 | C45: Zwift | D45: 45170 | E45: 1 | F45: 5 | G45: 15000 | H45: B2C | I45: Exercise | J45: Design Partner | K45: 505 | L45: 32 | M45: 0 | N45: 0

Sheet Most Recent Import
A1: workspace | B1: arr | C1: contractStartDate | D1: numberOfPaidSeats | E1: Expected 1st Year Studies Published | F1: M0 | G1: M1 | H1: M2 | I1: M3 | J1: M4 | K1: M5 | L1: M6 | M1: M7 | N1: M8 | O1: M9 | P1: M10 | Q1: M11
A2: safe | B2: 1000 | C2: 202302 | D2: 10 | E2: 12 | F2: 1 | G2: 0 | H2: 3 | I2: 1 | J2: 1 | K2: 0 | L2: 1 | M2: 2 | N2: 1 | O2: 0 | P2: 2 | Q2: 0
A3: 8x8 | B3: 15000 | C3: 202305 | D3: 9 | E3: 24 | F3: 3 | G3: 2 | H3: 2 | I3: 0 | J3: 4 | K3: 7 | L3: 4 | M3: 4 | N3: 1 | O3: 3 | P3: 0 | Q3: 0
A4: convera | B4: 5000 | C4: 202305 | D4: 5 | E4: 12 | F4: 1 | G4: 0 | H4: 0 | I4: 0 | J4: 0 | K4: 0 | L4: 1 | M4: 0 | N4: 0 | O4: 0 | P4: 0 | Q4: 0
A5: glovo | B5: 30000 | C5: 202305 | D5: 5 | E5: 36 | F5: 9 | G5: 21 | H5: 15 | I5: 8 | J5: 24 | K5: 8 | L5: 11 | M5: 15 | N5: 29 | O5: 6 | P5: 1 | Q5: 0
A6: webflow | B6: 20000 | C6: 202305 | D6: 10 | E6: 24 | F6: 2 | G6: 6 | H6: 3 | I6: 5 | J6: 6 | K6: 4 | L6: 6 | M6: 9 | N6: 7 | O6: 6 | P6: 1 | Q6: 0
A7: gitlab | B7: 25000 | C7: 202306 | D7: 4 | E7: 36 | F7: 10 | G7: 8 | H7: 9 | I7: 3 | J7: 2 | K7: 3 | L7: 4 | M7: 5 | N7: 0 | O7: 0 | P7: 0 | Q7: 0
A8: chegg | B8: 25000 | C8: 202308 | D8: 7 | E8: 24 | F8: 3 | G8: 0 | H8: 4 | I8: 5 | J8: 4 | K8: 1 | L8: 7 | M8: 1 | N8: 0 | O8: 0 | P8: 0 | Q8: 0
A9: ezcater | B9: 20000 | C9: 202308 | D9: 10 | E9: 24 | F9: 15 | G9: 17 | H9: 10 | I9: 2 | J9: 6 | K9: 7 | L9: 5 | M9: 8 | N9: 0 | O9: 0 | P9: 0 | Q9: 0
A10: impact | B10: 5000 | C10: 202308 | D10: 2 | E10: 12 | F10: 0 | G10: 4 | H10: 0 | I10: 0 | J10: 1 | K10: 6 | L10: 4 | M10: 1 | N10: 0 | O10: 0 | P10: 0 | Q10: 0
A11: usertesting | B11: 15000 | C11: 202308 | D11: 5 | E11: 24 | F11: 17 | G11: 13 | H11: 6 | I11: 6 | J11: 22 | K11: 15 | L11: 2 | M11: 4 | N11: 0 | O11: 0 | P11: 0 | Q11: 0
A12: xplor_technologies | B12: 8000 | C12: 202308 | D12: 6 | E12: 24 | F12: 5 | G12: 3 | H12: 1 | I12: 3 | J12: 2 | K12: 1 | L12: 4 | M12: 2 | N12: 3 | O12: 3 | P12: 5 | Q12: 5
A13: consensys | B13: 3000 | C13: 202308 | D13: 2 | E13: 12 | F13: 0 | G13: 0 | H13: 0 | I13: 0 | J13: 1 | K13: 0 | L13: 0 | M13: 0 | N13: 0 | O13: 0 | P13: 1 | Q13: 2
... A43: xometry | B43: 10000 | C43: 202404 | D43: 3 | E43: 12 | F43: 9 | G43: 7 | H43: 1 | I43: 1 | J43: 3 | K43: 4 | L43: 2 | M43: 7 | N43: 2 | O43: 1 | P43: 5 | Q43: 4

Sheet Studies (Monthly) RAW
B2: Month Closed | C2: ACV | D2: ICP | E2: Expected Year 1 Usage | F2: Month 1 | G2: Month 2 | H2: Month 3 | I2: Month 4 | J2: Month 5 | K2: Month 6 | L2: Month 7 | M2: Month 8 | N2: Month 9 | O2: Month 10 | P2: Month 11 | Q2: Month 12
A3: ='Normalized Import'!A2 -> safe | B3: ='Normalized Import'!B2 -> 44958 | C3: ='Normalized Import'!C2 -> 1000 | E3: ='Studies (Cum) RAW'!E3/12 -> 1 | F3: ='Normalized Import'!E2 -> 0 | G3: ='Normalized Import'!F2 -> 2 | H3: ='Normalized Import'!G2 -> 0 | I3: ='Normalized Import'!H2 -> 1 | J3: ='Normalized Import'!I2 -> 2 | K3: ='Normalized Import'!J2 -> 1 | L3: ='Normalized Import'!K2 -> 0 | M3: ='Normalized Import'!L2 -> 1 | ... Q3: ='Normalized Import'!P2 -> 1
A4: ='Normalized Import'!A3 -> 8x8 | B4: ='Normalized Import'!B3 -> 45047 | C4: ='Normalized Import'!C3 -> 15000 | E4: ='Studies (Cum) RAW'!E4/12 -> 2 | F4: ='Normalized Import'!E3 -> 0 | G4: ='Normalized Import'!F3 -> 0 | H4: ='Normalized Import'!G3 -> 3 | I4: ='Normalized Import'!H3 -> 1 | J4: ='Normalized Import'!I3 -> 4 | K4: ='Normalized Import'!J3 -> 4 | L4: ='Normalized Import'!K3 -> 7 | M4: ='Normalized Import'!L3 -> 4 | ... Q4: ='Normalized Import'!P3 -> 3
A5: ='Normalized Import'!A4 -> convera | B5: ='Normalized Import'!B4 -> 45047 | C5: ='Normalized Import'!C4 -> 5000 | E5: ='Studies (Cum) RAW'!E5/12 -> 1 | F5: ='Normalized Import'!E4 -> 0 | G5: ='Normalized Import'!F4 -> 0 | H5: ='Normalized Import'!G4 -> 0 | I5: ='Normalized Import'!H4 -> 0 | J5: ='Normalized Import'!I4 -> 0 | K5: ='Normalized Import'!J4 -> 1 | L5: ='Normalized Import'!K4 -> 0 | M5: ='Normalized Import'!L4 -> 0 | ... Q5: ='Normalized Import'!P4 -> 1
A6: ='Normalized Import'!A5 -> glovo | B6: ='Normalized Import'!B5 -> 45047 | C6: ='Normalized Import'!C5 -> 30000 | E6: ='Studies (Cum) RAW'!E6/12 -> 3 | F6: ='Normalized Import'!E5 -> 0 | G6: ='Normalized Import'!F5 -> 1 | H6: ='Normalized Import'!G5 -> 6 | I6: ='Normalized Import'!H5 -> 29 | J6: ='Normalized Import'!I5 -> 15 | K6: ='Normalized Import'!J5 -> 11 | L6: ='Normalized Import'!K5 -> 8 | M6: ='Normalized Import'!L5 -> 24 | ... Q6: ='Normalized Import'!P5 -> 9
A7: ='Normalized Import'!A6 -> webflow | B7: ='Normalized Import'!B6 -> 45047 | C7: ='Normalized Import'!C6 -> 20000 | E7: ='Studies (Cum) RAW'!E7/12 -> 2 | F7: ='Normalized Import'!E6 -> 0 | G7: ='Normalized Import'!F6 -> 1 | H7: ='Normalized Import'!G6 -> 6 | I7: ='Normalized Import'!H6 -> 7 | J7: ='Normalized Import'!I6 -> 9 | K7: ='Normalized Import'!J6 -> 6 | L7: ='Normalized Import'!K6 -> 4 | M7: ='Normalized Import'!L6 -> 6 | ... Q7: ='Normalized Import'!P6 -> 2
A8: ='Normalized Import'!A7 -> gitlab | B8: ='Normalized Import'!B7 -> 45078 | C8: ='Normalized Import'!C7 -> 25000 | E8: ='Studies (Cum) RAW'!E8/12 -> 3 | F8: ='Normalized Import'!E7 -> 0 | G8: ='Normalized Import'!F7 -> 0 | H8: ='Normalized Import'!G7 -> 0 | I8: ='Normalized Import'!H7 -> 0 | J8: ='Normalized Import'!I7 -> 5 | K8: ='Normalized Import'!J7 -> 4 | L8: ='Normalized Import'!K7 -> 3 | M8: ='Normalized Import'!L7 -> 2 | ... Q8: ='Normalized Import'!P7 -> 10
A9: ='Normalized Import'!A8 -> chegg | B9: ='Normalized Import'!B8 -> 45139 | C9: ='Normalized Import'!C8 -> 25000 | E9: ='Studies (Cum) RAW'!E9/12 -> 2 | F9: ='Normalized Import'!E8 -> 0 | G9: ='Normalized Import'!F8 -> 0 | H9: ='Normalized Import'!G8 -> 0 | I9: ='Normalized Import'!H8 -> 0 | J9: ='Normalized Import'!I8 -> 1 | K9: ='Normalized Import'!J8 -> 7 | L9: ='Normalized Import'!K8 -> 1 | M9: ='Normalized Import'!L8 -> 4 | ... Q9: ='Normalized Import'!P8 -> 3
A10: ='Normalized Import'!A9 -> ezcater | B10: ='Normalized Import'!B9 -> 45139 | C10: ='Normalized Import'!C9 -> 20000 | E10: ='Studies (Cum) RAW'!E10/12 -> 2 | F10: ='Normalized Import'!E9 -> 0 | G10: ='Normalized Import'!F9 -> 0 | H10: ='Normalized Import'!G9 -> 0 | I10: ='Normalized Import'!H9 -> 0 | J10: ='Normalized Import'!I9 -> 8 | K10: ='Normalized Import'!J9 -> 5 | L10: ='Normalized Import'!K9 -> 7 | M10: ='Normalized Import'!L9 -> 6 | ... Q10: ='Normalized Import'!P9 -> 15
A11: ='Normalized Import'!A10 -> impact | B11: ='Normalized Import'!B10 -> 45139 | C11: ='Normalized Import'!C10 -> 5000 | E11: ='Studies (Cum) RAW'!E11/12 -> 1 | F11: ='Normalized Import'!E10 -> 0 | G11: ='Normalized Import'!F10 -> 0 | H11: ='Normalized Import'!G10 -> 0 | I11: ='Normalized Import'!H10 -> 0 | J11: ='Normalized Import'!I10 -> 1 | K11: ='Normalized Import'!J10 -> 4 | L11: ='Normalized Import'!K10 -> 6 | M11: ='Normalized Import'!L10 -> 1 | ... Q11: ='Normalized Import'!P10 -> 0
A12: ='Normalized Import'!A11 -> usertesting | B12: ='Normalized Import'!B11 -> 45139 | C12: ='Normalized Import'!C11 -> 15000 | E12: ='Studies (Cum) RAW'!E12/12 -> 2 | F12: ='Normalized Import'!E11 -> 0 | G12: ='Normalized Import'!F11 -> 0 | H12: ='Normalized Import'!G11 -> 0 | I12: ='Normalized Import'!H11 -> 0 | J12: ='Normalized Import'!I11 -> 4 | K12: ='Normalized Import'!J11 -> 2 | L12: ='Normalized Import'!K11 -> 15 | M12: ='Normalized Import'!L11 -> 22 | ... Q12: ='Normalized Import'!P11 -> 17
A13: ='Normalized Import'!A12 -> xplor_technologies | B13: ='Normalized Import'!B12 -> 45139 | C13: ='Normalized Import'!C12 -> 8000 | E13: ='Studies (Cum) RAW'!E13/12 -> 2 | F13: ='Normalized Import'!E12 -> 5 | G13: ='Normalized Import'!F12 -> 5 | H13: ='Normalized Import'!G12 -> 3 | I13: ='Normalized Import'!H12 -> 3 | J13: ='Normalized Import'!I12 -> 2 | K13: ='Normalized Import'!J12 -> 4 | L13: ='Normalized Import'!K12 -> 1 | M13: ='Normalized Import'!L12 -> 2 | ... Q13: ='Normalized Import'!P12 -> 5
A14: ='Normalized Import'!A13 -> consensys | B14: ='Normalized Import'!B13 -> 45139 | C14: ='Normalized Import'!C13 -> 3000 | E14: ='Studies (Cum) RAW'!E14/12 -> 1 | F14: ='Normalized Import'!E13 -> 2 | G14: ='Normalized Import'!F13 -> 1 | H14: ='Normalized Import'!G13 -> 0 | I14: ='Normalized Import'!H13 -> 0 | J14: ='Normalized Import'!I13 -> 0 | K14: ='Normalized Import'!J13 -> 0 | L14: ='Normalized Import'!K13 -> 0 | M14: ='Normalized Import'!L13 -> 1 | ... Q14: ='Normalized Import'!P13 -> 0
... A17: ='Normalized Import'!A16 -> sonos | B17: ='Normalized Import'!B16 -> 45170 | C17: ='Normalized Import'!C16 -> 23000 | E17: ='Studies (Cum) RAW'!E17/12 -> 2 | F17: ='Normalized Import'!E16 -> 0 | G17: ='Normalized Import'!F16 -> 0 | H17: ='Normalized Import'!G16 -> 0 | I17: ='Normalized Import'!H16 -> 0 | J17: ='Normalized Import'!I16 -> 0 | K17: ='Normalized Import'!J16 -> 0 | L17: ='Normalized Import'!K16 -> 7 | M17: ='Normalized Import'!L16 -> 9 | ... Q17: ='Normalized Import'!P16 -> 11
A18: ='Normalized Import'!A17 -> soundtrap | B18: ='Normalized Import'!B17 -> 45170 | C18: ='Normalized Import'!C17 -> 5000 | E18: ='Studies (Cum) RAW'!E18/12 -> 1 | F18: ='Normalized Import'!E17 -> 0 | G18: ='Normalized Import'!F17 -> 0 | H18: ='Normalized Import'!G17 -> 0 | I18: ='Normalized Import'!H17 -> 0 | J18: ='Normalized Import'!I17 -> 0 | K18: ='Normalized Import'!J17 -> 0 | L18: ='Normalized Import'!K17 -> 1 | M18: ='Normalized Import'!L17 -> 1 | ... Q18: ='Normalized Import'!P17 -> 1 | T18: #REF! | U18: #REF! | V18: #REF! | W18: #REF! | X18: #REF! | Y18: #REF!
A19: ='Normalized Import'!A18 -> yahoo | B19: ='Normalized Import'!B18 -> 45170 | C19: ='Normalized Import'!C18 -> 32000 | E19: ='Studies (Cum) RAW'!E19/12 -> 2 | F19: ='Normalized Import'!E18 -> 0 | G19: ='Normalized Import'!F18 -> 0 | H19: ='Normalized Import'!G18 -> 0 | I19: ='Normalized Import'!H18 -> 0 | J19: ='Normalized Import'!I18 -> 0 | K19: ='Normalized Import'!J18 -> 1 | L19: ='Normalized Import'!K18 -> 2 | M19: ='Normalized Import'!L18 -> 2 | ... Q19: ='Normalized Import'!P18 -> 2 | T19: #REF! | U19: #REF! | V19: #REF! | W19: #REF! | X19: #REF! | Y19: #REF!
A20: ='Normalized Import'!A19 -> zwift | B20: ='Normalized Import'!B19 -> 45170 | C20: ='Normalized Import'!C19 -> 15000 | E20: ='Studies (Cum) RAW'!E20/12 -> 1 | F20: ='Normalized Import'!E19 -> 0 | G20: ='Normalized Import'!F19 -> 0 | H20: ='Normalized Import'!G19 -> 0 | I20: ='Normalized Import'!H19 -> 0 | J20: ='Normalized Import'!I19 -> 0 | K20: ='Normalized Import'!J19 -> 0 | L20: ='Normalized Import'!K19 -> 4 | M20: ='Normalized Import'!L19 -> 1 | ... Q20: ='Normalized Import'!P19 -> 0 | T20: #REF! | U20: #REF! | V20: #REF! | W20: #REF! | X20: #REF! | Y20: #REF!
A21: ='Normalized Import'!A20 -> angi | B21: ='Normalized Import'!B20 -> 45200 | C21: ='Normalized Import'!C20 -> 10000 | E21: ='Studies (Cum) RAW'!E21/12 -> 2 | F21: ='Normalized Import'!E20 -> 1 | G21: ='Normalized Import'!F20 -> 7 | H21: ='Normalized Import'!G20 -> 1 | I21: ='Normalized Import'!H20 -> 3 | J21: ='Normalized Import'!I20 -> 0 | K21: ='Normalized Import'!J20 -> 5 | L21: ='Normalized Import'!K20 -> 6 | M21: ='Normalized Import'!L20 -> 0 | ... Q21: ='Normalized Import'!P20 -> 6 | T21: #REF! | U21: #REF! | V21: #REF! | W21: #REF! | X21: #REF! | Y21: #REF!
A22: ='Normalized Import'!A21 -> rockwell | B22: ='Normalized Import'!B21 -> 45200 | C22: ='Normalized Import'!C21 -> 20000 | E22: ='Studies (Cum) RAW'!E22/12 -> 2 | F22: ='Normalized Import'!E21 -> 0 | G22: ='Normalized Import'!F21 -> 0 | H22: ='Normalized Import'!G21 -> 0 | I22: ='Normalized Import'!H21 -> 0 | J22: ='Normalized Import'!I21 -> 0 | K22: ='Normalized Import'!J21 -> 0 | L22: ='Normalized Import'!K21 -> 1 | M22: ='Normalized Import'!L21 -> 12 | ... Q22: ='Normalized Import'!P21 -> 5 | T22: #REF! | U22: #REF! | V22: #REF! | W22: #REF! | X22: #REF! | Y22: #REF!
A23: ='Normalized Import'!A22 -> snowplow | B23: ='Normalized Import'!B22 -> 45200 | C23: ='Normalized Import'!C22 -> 2000 | E23: ='Studies (Cum) RAW'!E23/12 -> 1 | F23: ='Normalized Import'!E22 -> 0 | G23: ='Normalized Import'!F22 -> 0 | H23: ='Normalized Import'!G22 -> 0 | I23: ='Normalized Import'!H22 -> 0 | J23: ='Normalized Import'!I22 -> 0 | K23: ='Normalized Import'!J22 -> 0 | L23: ='Normalized Import'!K22 -> 2 | M23: ='Normalized Import'!L22 -> 1 | ... Q23: ='Normalized Import'!P22 -> 0 | T23: #REF! | U23: #REF! | V23: #REF! | W23: #REF! | X23: #REF! | Y23: #REF!
A24: ='Normalized Import'!A23 -> predictive_index | B24: ='Normalized Import'!B23 -> 45231 | C24: ='Normalized Import'!C23 -> 2000 | E24: ='Studies (Cum) RAW'!E24/12 -> 1 | F24: ='Normalized Import'!E23 -> 1 | G24: ='Normalized Import'!F23 -> 4 | H24: ='Normalized Import'!G23 -> 0 | I24: ='Normalized Import'!H23 -> 1 | J24: ='Normalized Import'!I23 -> 3 | K24: ='Normalized Import'!J23 -> 3 | L24: ='Normalized Import'!K23 -> 1 | M24: ='Normalized Import'!L23 -> 2 | ... Q24: ='Normalized Import'!P23 -> 1 | T24: #REF! | U24: #REF! | V24: #REF! | W24: #REF! | X24: #REF! | Y24: #REF!
A25: ='Normalized Import'!A24 -> biorender | B25: ='Normalized Import'!B24 -> 45261 | C25: ='Normalized Import'!C24 -> 2000 | E25: ='Studies (Cum) RAW'!E25/12 -> 2 | F25: ='Normalized Import'!E24 -> 3 | G25: ='Normalized Import'!F24 -> 3 | H25: ='Normalized Import'!G24 -> 8 | I25: ='Normalized Import'!H24 -> 2 | J25: ='Normalized Import'!I24 -> 8 | K25: ='Normalized Import'!J24 -> 7 | L25: ='Normalized Import'!K24 -> 1 | M25: ='Normalized Import'!L24 -> 4 | ... Q25: ='Normalized Import'!P24 -> 9 | T25: #REF! | U25: #REF! | V25: #REF! | W25: #REF! | X25: #REF! | Y25: #REF!
A26: ='Normalized Import'!A25 -> checkr | B26: ='Normalized Import'!B25 -> 45261 | C26: ='Normalized Import'!C25 -> 10000 | E26: ='Studies (Cum) RAW'!E26/12 -> 2 | F26: ='Normalized Import'!E25 -> 0 | G26: ='Normalized Import'!F25 -> 1 | H26: ='Normalized Import'!G25 -> 2 | I26: ='Normalized Import'!H25 -> 0 | J26: ='Normalized Import'!I25 -> 5 | K26: ='Normalized Import'!J25 -> 1 | L26: ='Normalized Import'!K25 -> 4 | M26: ='Normalized Import'!L25 -> 4 | ... Q26: ='Normalized Import'!P25 -> 3 | T26: #REF! | U26: #REF! | V26: #REF! | W26: #REF! | X26: #REF! | Y26: #REF!
A27: ='Normalized Import'!A26 -> gp-research | B27: ='Normalized Import'!B26 -> 45261 | C27: ='Normalized Import'!C26 -> 10000 | E27: ='Studies (Cum) RAW'!E27/12 -> 2 | F27: ='Normalized Import'!E26 -> 0 | G27: ='Normalized Import'!F26 -> 0 | H27: ='Normalized Import'!G26 -> 0 | I27: ='Normalized Import'!H26 -> 2 | J27: ='Normalized Import'!I26 -> 6 | K27: ='Normalized Import'!J26 -> 3 | L27: ='Normalized Import'!K26 -> 2 | M27: ='Normalized Import'!L26 -> 7 | ... Q27: ='Normalized Import'!P26 -> 3 | T27: #REF! | U27: #REF! | V27: #REF! | W27: #REF! | X27: #REF! | Y27: #REF!
A28: ='Normalized Import'!A27 -> sailpoint | B28: ='Normalized Import'!B27 -> 45261 | C28: ='Normalized Import'!C27 -> 12000 | E28: ='Studies (Cum) RAW'!E28/12 -> 1 | F28: ='Normalized Import'!E27 -> 0 | G28: ='Normalized Import'!F27 -> 0 | H28: ='Normalized Import'!G27 -> 0 | I28: ='Normalized Import'!H27 -> 0 | J28: ='Normalized Import'!I27 -> 0 | K28: ='Normalized Import'!J27 -> 0 | L28: ='Normalized Import'!K27 -> 0 | M28: ='Normalized Import'!L27 -> 0 | ... Q28: ='Normalized Import'!P27 -> 2 | T28: #REF! | U28: #REF! | V28: #REF! | W28: #REF! | X28: #REF! | Y28: #REF!
A29: ='Normalized Import'!A28 -> stack_overflow | B29: ='Normalized Import'!B28 -> 45261 | C29: ='Normalized Import'!C28 -> 22500 | E29: ='Studies (Cum) RAW'!E29/12 -> 2 | F29: ='Normalized Import'!E28 -> 0 | G29: ='Normalized Import'!F28 -> 0 | H29: ='Normalized Import'!G28 -> 0 | I29: ='Normalized Import'!H28 -> 0 | J29: ='Normalized Import'!I28 -> 0 | K29: ='Normalized Import'!J28 -> 0 | L29: ='Normalized Import'!K28 -> 0 | M29: ='Normalized Import'!L28 -> 0 | ... Q29: ='Normalized Import'!P28 -> 5 | T29: #REF! | U29: #REF! | V29: #REF! | W29: #REF! | X29: #REF! | Y29: #REF!
... A40: ='Normalized Import'!A39 -> braze | B40: ='Normalized Import'!B39 -> 45352 | C40: ='Normalized Import'!C39 -> 25000 | E40: ='Studies (Cum) RAW'!E40/12 -> 2 | F40: ='Normalized Import'!E39 -> 3 | G40: ='Normalized Import'!F39 -> 1 | H40: ='Normalized Import'!G39 -> 1 | I40: ='Normalized Import'!H39 -> 12 | J40: ='Normalized Import'!I39 -> 4 | K40: ='Normalized Import'!J39 -> 5 | L40: ='Normalized Import'!K39 -> 8 | M40: ='Normalized Import'!L39 -> 8 | ... Q40: ='Normalized Import'!P39 -> 16 | T40: #REF! | U40: #REF! | V40: #REF! | W40: #REF! | X40: #REF! | Y40: #REF!
A41: ='Normalized Import'!A40 -> cloudflare | B41: ='Normalized Import'!B40 -> 45352 | C41: ='Normalized Import'!C40 -> 20000 | E41: ='Studies (Cum) RAW'!E41/12 -> 2 | F41: ='Normalized Import'!E40 -> 0 | G41: ='Normalized Import'!F40 -> 0 | H41: ='Normalized Import'!G40 -> 0 | I41: ='Normalized Import'!H40 -> 0 | J41: ='Normalized Import'!I40 -> 0 | K41: ='Normalized Import'!J40 -> 0 | L41: ='Normalized Import'!K40 -> 0 | M41: ='Normalized Import'!L40 -> 0 | ... Q41: ='Normalized Import'!P40 -> 2
A42: ='Normalized Import'!A41 -> hellofresh | B42: ='Normalized Import'!B41 -> 45352 | C42: ='Normalized Import'!C41 -> 10000 | E42: ='Studies (Cum) RAW'!E42/12 -> 1 | F42: ='Normalized Import'!E41 -> 0 | G42: ='Normalized Import'!F41 -> 0 | H42: ='Normalized Import'!G41 -> 0 | I42: ='Normalized Import'!H41 -> 3 | J42: ='Normalized Import'!I41 -> 5 | K42: ='Normalized Import'!J41 -> 0 | L42: ='Normalized Import'!K41 -> 4 | M42: ='Normalized Import'!L41 -> 0 | ... Q42: ='Normalized Import'!P41 -> 5
A43: ='Normalized Import'!A42 -> mongodb | B43: ='Normalized Import'!B42 -> 45352 | C43: ='Normalized Import'!C42 -> 20000 | E43: ='Studies (Cum) RAW'!E43/12 -> 3 | F43: ='Normalized Import'!E42 -> 1 | G43: ='Normalized Import'!F42 -> 1 | H43: ='Normalized Import'!G42 -> 1 | I43: ='Normalized Import'!H42 -> 5 | J43: ='Normalized Import'!I42 -> 5 | K43: ='Normalized Import'!J42 -> 5 | L43: ='Normalized Import'!K42 -> 5 | M43: ='Normalized Import'!L42 -> 13 | ... Q43: ='Normalized Import'!P42 -> 10
A44: ='Normalized Import'!A43 -> xometry | B44: ='Normalized Import'!B43 -> 45383 | C44: ='Normalized Import'!C43 -> 10000 | E44: ='Studies (Cum) RAW'!E44/12 -> 1 | F44: ='Normalized Import'!E43 -> 4 | G44: ='Normalized Import'!F43 -> 5 | H44: ='Normalized Import'!G43 -> 1 | I44: ='Normalized Import'!H43 -> 2 | J44: ='Normalized Import'!I43 -> 7 | K44: ='Normalized Import'!J43 -> 2 | L44: ='Normalized Import'!K43 -> 4 | M44: ='Normalized Import'!L43 -> 3 | ... Q44: ='Normalized Import'!P43 -> 9
A45: ='Normalized Import'!A44 -> 0 | B45: ='Normalized Import'!B44 -> #VALUE! | C45: ='Normalized Import'!C44 -> 0 | F45: ='Normalized Import'!E44 -> #VALUE! | G45: ='Normalized Import'!F44 -> #VALUE! | H45: ='Normalized Import'!G44 -> #VALUE! | I45: ='Normalized Import'!H44 -> #VALUE! | J45: ='Normalized Import'!I44 -> #VALUE! | K45: ='Normalized Import'!J44 -> #VALUE! | L45: ='Normalized Import'!K44 -> #VALUE! | M45: ='Normalized Import'!L44 -> #VALUE! | ... Q45: ='Normalized Import'!P44 -> #VALUE!
A46: ='Normalized Import'!A45 -> 0 | B46: ='Normalized Import'!B45 -> #VALUE! | C46: ='Normalized Import'!C45 -> 0 | F46: ='Normalized Import'!E45 -> #VALUE! | G46: ='Normalized Import'!F45 -> #VALUE! | H46: ='Normalized Import'!G45 -> #VALUE! | I46: ='Normalized Import'!H45 -> #VALUE! | J46: ='Normalized Import'!I45 -> #VALUE! | K46: ='Normalized Import'!J45 -> #VALUE! | L46: ='Normalized Import'!K45 -> #VALUE! | M46: ='Normalized Import'!L45 -> #VALUE! | ... Q46: ='Normalized Import'!P45 -> #VALUE!
A47: ='Normalized Import'!A46 -> 0 | B47: ='Normalized Import'!B46 -> #VALUE! | C47: ='Normalized Import'!C46 -> 0 | F47: ='Normalized Import'!E46 -> #VALUE! | G47: ='Normalized Import'!F46 -> #VALUE! | H47: ='Normalized Import'!G46 -> #VALUE! | I47: ='Normalized Import'!H46 -> #VALUE! | J47: ='Normalized Import'!I46 -> #VALUE! | K47: ='Normalized Import'!J46 -> #VALUE! | L47: ='Normalized Import'!K46 -> #VALUE! | M47: ='Normalized Import'!L46 -> #VALUE! | ... Q47: ='Normalized Import'!P46 -> #VALUE!
A48: ='Normalized Import'!A47 -> 0 | B48: ='Normalized Import'!B47 -> #VALUE! | C48: ='Normalized Import'!C47 -> 0 | F48: ='Normalized Import'!E47 -> #VALUE! | G48: ='Normalized Import'!F47 -> #VALUE! | H48: ='Normalized Import'!G47 -> #VALUE! | I48: ='Normalized Import'!H47 -> #VALUE! | J48: ='Normalized Import'!I47 -> #VALUE! | K48: ='Normalized Import'!J47 -> #VALUE! | L48: ='Normalized Import'!K47 -> #VALUE! | M48: ='Normalized Import'!L47 -> #VALUE! | ... Q48: ='Normalized Import'!P47 -> #VALUE!
A49: ='Normalized Import'!A48 -> 0 | B49: ='Normalized Import'!B48 -> #VALUE! | C49: ='Normalized Import'!C48 -> 0 | F49: ='Normalized Import'!E48 -> #VALUE! | G49: ='Normalized Import'!F48 -> #VALUE! | H49: ='Normalized Import'!G48 -> #VALUE! | I49: ='Normalized Import'!H48 -> #VALUE! | J49: ='Normalized Import'!I48 -> #VALUE! | K49: ='Normalized Import'!J48 -> #VALUE! | L49: ='Normalized Import'!K48 -> #VALUE! | M49: ='Normalized Import'!L48 -> #VALUE! | ... Q49: ='Normalized Import'!P48 -> #VALUE!
A50: ='Normalized Import'!A49 -> 0 | B50: ='Normalized Import'!B49 -> #VALUE! | C50: ='Normalized Import'!C49 -> 0 | F50: ='Normalized Import'!E49 -> #VALUE! | G50: ='Normalized Import'!F49 -> #VALUE! | H50: ='Normalized Import'!G49 -> #VALUE! | I50: ='Normalized Import'!H49 -> #VALUE! | J50: ='Normalized Import'!I49 -> #VALUE! | K50: ='Normalized Import'!J49 -> #VALUE! | L50: ='Normalized Import'!K49 -> #VALUE! | M50: ='Normalized Import'!L49 -> #VALUE! | ... Q50: ='Normalized Import'!P49 -> #VALUE!
A51: ='Normalized Import'!A50 -> 0 | B51: ='Normalized Import'!B50 -> #VALUE! | C51: ='Normalized Import'!C50 -> 0 | F51: ='Normalized Import'!E50 -> #VALUE! | G51: ='Normalized Import'!F50 -> #VALUE! | H51: ='Normalized Import'!G50 -> #VALUE! | I51: ='Normalized Import'!H50 -> #VALUE! | J51: ='Normalized Import'!I50 -> #VALUE! | K51: ='Normalized Import'!J50 -> #VALUE! | L51: ='Normalized Import'!K50 -> #VALUE! | M51: ='Normalized Import'!L50 -> #VALUE! | ... Q51: ='Normalized Import'!P50 -> #VALUE!
A52: ='Normalized Import'!A51 -> 0 | B52: ='Normalized Import'!B51 -> #VALUE! | C52: ='Normalized Import'!C51 -> 0 | F52: ='Normalized Import'!E51 -> #VALUE! | G52: ='Normalized Import'!F51 -> #VALUE! | H52: ='Normalized Import'!G51 -> #VALUE! | I52: ='Normalized Import'!H51 -> #VALUE! | J52: ='Normalized Import'!I51 -> #VALUE! | K52: ='Normalized Import'!J51 -> #VALUE! | L52: ='Normalized Import'!K51 -> #VALUE! | M52: ='Normalized Import'!L51 -> #VALUE! | ... Q52: ='Normalized Import'!P51 -> #VALUE!
A53: ='Normalized Import'!A52 -> 0 | B53: ='Normalized Import'!B52 -> #VALUE! | C53: ='Normalized Import'!C52 -> 0 | F53: ='Normalized Import'!E52 -> #VALUE! | G53: ='Normalized Import'!F52 -> #VALUE! | H53: ='Normalized Import'!G52 -> #VALUE! | I53: ='Normalized Import'!H52 -> #VALUE! | J53: ='Normalized Import'!I52 -> #VALUE! | K53: ='Normalized Import'!J52 -> #VALUE! | L53: ='Normalized Import'!K52 -> #VALUE! | M53: ='Normalized Import'!L52 -> #VALUE! | ... Q53: ='Normalized Import'!P52 -> #VALUE!
A54: ='Normalized Import'!A53 -> 0 | B54: ='Normalized Import'!B53 -> #VALUE! | C54: ='Normalized Import'!C53 -> 0 | F54: ='Normalized Import'!E53 -> #VALUE! | G54: ='Normalized Import'!F53 -> #VALUE! | H54: ='Normalized Import'!G53 -> #VALUE! | I54: ='Normalized Import'!H53 -> #VALUE! | J54: ='Normalized Import'!I53 -> #VALUE! | K54: ='Normalized Import'!J53 -> #VALUE! | L54: ='Normalized Import'!K53 -> #VALUE! | M54: ='Normalized Import'!L53 -> #VALUE! | ... Q54: ='Normalized Import'!P53 -> #VALUE!
A55: ='Normalized Import'!A54 -> 0 | B55: ='Normalized Import'!B54 -> #VALUE! | C55: ='Normalized Import'!C54 -> 0 | F55: ='Normalized Import'!E54 -> #VALUE! | G55: ='Normalized Import'!F54 -> #VALUE! | H55: ='Normalized Import'!G54 -> #VALUE! | I55: ='Normalized Import'!H54 -> #VALUE! | J55: ='Normalized Import'!I54 -> #VALUE! | K55: ='Normalized Import'!J54 -> #VALUE! | L55: ='Normalized Import'!K54 -> #VALUE! | M55: ='Normalized Import'!L54 -> #VALUE! | ... Q55: ='Normalized Import'!P54 -> #VALUE!
A56: ='Normalized Import'!A55 -> 0 | B56: ='Normalized Import'!B55 -> #VALUE! | C56: ='Normalized Import'!C55 -> 0 | F56: ='Normalized Import'!E55 -> #VALUE! | G56: ='Normalized Import'!F55 -> #VALUE! | H56: ='Normalized Import'!G55 -> #VALUE! | I56: ='Normalized Import'!H55 -> #VALUE! | J56: ='Normalized Import'!I55 -> #VALUE! | K56: ='Normalized Import'!J55 -> #VALUE! | L56: ='Normalized Import'!K55 -> #VALUE! | M56: ='Normalized Import'!L55 -> #VALUE! | ... Q56: ='Normalized Import'!P55 -> #VALUE!
... A100: ='Normalized Import'!A99 -> 0 | B100: ='Normalized Import'!B99 -> #VALUE! | C100: ='Normalized Import'!C99 -> 0 | F100: ='Normalized Import'!E99 -> #VALUE! | G100: ='Normalized Import'!F99 -> #VALUE! | H100: ='Normalized Import'!G99 -> #VALUE! | I100: ='Normalized Import'!H99 -> #VALUE! | J100: ='Normalized Import'!I99 -> #VALUE! | K100: ='Normalized Import'!J99 -> #VALUE! | L100: ='Normalized Import'!K99 -> #VALUE! | M100: ='Normalized Import'!L99 -> #VALUE! | ... Q100: ='Normalized Import'!P99 -> #VALUE!

Sheet Studies (Cum) RAW
B2: Month Closed | C2: ACV | D2: ICP | E2: Expected Year 1 Usage | F2: Month 1 | G2: Month 2 | H2: Month 3 | I2: Month 4 | J2: Month 5 | K2: Month 6 | L2: Month 7 | M2: Month 8 | N2: Month 9 | O2: Month 10 | P2: Month 11 | Q2: Month 12
A3: ='Normalized Import'!A2 -> safe | B3: ='Normalized Import'!B2 -> 44958 | C3: ='Normalized Import'!C2 -> 1000 | E3: ='Most Recent Import'!E2 -> 12 | F3: ='Normalized Import'!E2 -> 0 | G3: =IF(EQ('Normalized Import'!F2, ""),"", 'Normalized Import'!F2+F3) -> #NAME? | H3: =IF(EQ('Normalized Import'!G2, ""), "", 'Normalized Import'!G2+G3) -> #NAME? | I3: =IF(EQ('Normalized Import'!H2, ""),"", 'Normalized Import'!H2+H3) -> #NAME? | J3: =IF(EQ('Normalized Import'!I2, ""), "", 'Normalized Import'!I2+I3) -> #NAME? | K3: =IF(EQ('Normalized Import'!J2, ""),"", 'Normalized Import'!J2+J3) -> #NAME? | L3: =IF(EQ('Normalized Import'!K2, ""), "", 'Normalized Import'!K2+K3) -> #NAME? | M3: =IF(EQ('Normalized Import'!L2, ""),"", 'Normalized Import'!L2+L3) -> #NAME? | N3: =IF(EQ('Normalized Import'!M2, ""), "", 'Normalized Import'!M2+M3) -> #NAME? | O3: =IF(EQ('Normalized Import'!N2, ""),"", 'Normalized Import'!N2+N3) -> #NAME? | P3: =IF(EQ('Normalized Import'!O2, ""), "", 'Normalized Import'!O2+O3) -> #NAME? | Q3: =IF(EQ('Normalized Import'!P2, ""),"", 'Normalized Import'!P2+P3) -> #NAME?
A4: ='Normalized Import'!A3 -> 8x8 | B4: ='Normalized Import'!B3 -> 45047 | C4: ='Normalized Import'!C3 -> 15000 | E4: ='Most Recent Import'!E3 -> 24 | F4: ='Normalized Import'!E3 -> 0 | G4: =IF(EQ('Normalized Import'!F3, ""),"", 'Normalized Import'!F3+F4) -> #NAME? | H4: =IF(EQ('Normalized Import'!G3, ""), "", 'Normalized Import'!G3+G4) -> #NAME? | I4: =IF(EQ('Normalized Import'!H3, ""),"", 'Normalized Import'!H3+H4) -> #NAME? | J4: =IF(EQ('Normalized Import'!I3, ""), "", 'Normalized Import'!I3+I4) -> #NAME? | K4: =IF(EQ('Normalized Import'!J3, ""),"", 'Normalized Import'!J3+J4) -> #NAME? | L4: =IF(EQ('Normalized Import'!K3, ""), "", 'Normalized Import'!K3+K4) -> #NAME? | M4: =IF(EQ('Normalized Import'!L3, ""),"", 'Normalized Import'!L3+L4) -> #NAME? | N4: =IF(EQ('Normalized Import'!M3, ""), "", 'Normalized Import'!M3+M4) -> #NAME? | O4: =IF(EQ('Normalized Import'!N3, ""),"", 'Normalized Import'!N3+N4) -> #NAME? | P4: =IF(EQ('Normalized Import'!O3, ""), "", 'Normalized Import'!O3+O4) -> #NAME? | Q4: =IF(EQ('Normalized Import'!P3, ""),"", 'Normalized Import'!P3+P4) -> #NAME?
A5: ='Normalized Import'!A4 -> convera | B5: ='Normalized Import'!B4 -> 45047 | C5: ='Normalized Import'!C4 -> 5000 | E5: ='Most Recent Import'!E4 -> 12 | F5: ='Normalized Import'!E4 -> 0 | G5: =IF(EQ('Normalized Import'!F4, ""),"", 'Normalized Import'!F4+F5) -> #NAME? | H5: =IF(EQ('Normalized Import'!G4, ""), "", 'Normalized Import'!G4+G5) -> #NAME? | I5: =IF(EQ('Normalized Import'!H4, ""),"", 'Normalized Import'!H4+H5) -> #NAME? | J5: =IF(EQ('Normalized Import'!I4, ""), "", 'Normalized Import'!I4+I5) -> #NAME? | K5: =IF(EQ('Normalized Import'!J4, ""),"", 'Normalized Import'!J4+J5) -> #NAME? | L5: =IF(EQ('Normalized Import'!K4, ""), "", 'Normalized Import'!K4+K5) -> #NAME? | M5: =IF(EQ('Normalized Import'!L4, ""),"", 'Normalized Import'!L4+L5) -> #NAME? | N5: =IF(EQ('Normalized Import'!M4, ""), "", 'Normalized Import'!M4+M5) -> #NAME? | O5: =IF(EQ('Normalized Import'!N4, ""),"", 'Normalized Import'!N4+N5) -> #NAME? | P5: =IF(EQ('Normalized Import'!O4, ""), "", 'Normalized Import'!O4+O5) -> #NAME? | Q5: =IF(EQ('Normalized Import'!P4, ""),"", 'Normalized Import'!P4+P5) -> #NAME?
A6: ='Normalized Import'!A5 -> glovo | B6: ='Normalized Import'!B5 -> 45047 | C6: ='Normalized Import'!C5 -> 30000 | E6: ='Most Recent Import'!E5 -> 36 | F6: ='Normalized Import'!E5 -> 0 | G6: =IF(EQ('Normalized Import'!F5, ""),"", 'Normalized Import'!F5+F6) -> #NAME? | H6: =IF(EQ('Normalized Import'!G5, ""), "", 'Normalized Import'!G5+G6) -> #NAME? | I6: =IF(EQ('Normalized Import'!H5, ""),"", 'Normalized Import'!H5+H6) -> #NAME? | J6: =IF(EQ('Normalized Import'!I5, ""), "", 'Normalized Import'!I5+I6) -> #NAME? | K6: =IF(EQ('Normalized Import'!J5, ""),"", 'Normalized Import'!J5+J6) -> #NAME? | L6: =IF(EQ('Normalized Import'!K5, ""), "", 'Normalized Import'!K5+K6) -> #NAME? | M6: =IF(EQ('Normalized Import'!L5, ""),"", 'Normalized Import'!L5+L6) -> #NAME? | N6: =IF(EQ('Normalized Import'!M5, ""), "", 'Normalized Import'!M5+M6) -> #NAME? | O6: =IF(EQ('Normalized Import'!N5, ""),"", 'Normalized Import'!N5+N6) -> #NAME? | P6: =IF(EQ('Normalized Import'!O5, ""), "", 'Normalized Import'!O5+O6) -> #NAME? | Q6: =IF(EQ('Normalized Import'!P5, ""),"", 'Normalized Import'!P5+P6) -> #NAME?
A7: ='Normalized Import'!A6 -> webflow | B7: ='Normalized Import'!B6 -> 45047 | C7: ='Normalized Import'!C6 -> 20000 | E7: ='Most Recent Import'!E6 -> 24 | F7: ='Normalized Import'!E6 -> 0 | G7: =IF(EQ('Normalized Import'!F6, ""),"", 'Normalized Import'!F6+F7) -> #NAME? | H7: =IF(EQ('Normalized Import'!G6, ""), "", 'Normalized Import'!G6+G7) -> #NAME? | I7: =IF(EQ('Normalized Import'!H6, ""),"", 'Normalized Import'!H6+H7) -> #NAME? | J7: =IF(EQ('Normalized Import'!I6, ""), "", 'Normalized Import'!I6+I7) -> #NAME? | K7: =IF(EQ('Normalized Import'!J6, ""),"", 'Normalized Import'!J6+J7) -> #NAME? | L7: =IF(EQ('Normalized Import'!K6, ""), "", 'Normalized Import'!K6+K7) -> #NAME? | M7: =IF(EQ('Normalized Import'!L6, ""),"", 'Normalized Import'!L6+L7) -> #NAME? | N7: =IF(EQ('Normalized Import'!M6, ""), "", 'Normalized Import'!M6+M7) -> #NAME? | O7: =IF(EQ('Normalized Import'!N6, ""),"", 'Normalized Import'!N6+N7) -> #NAME? | P7: =IF(EQ('Normalized Import'!O6, ""), "", 'Normalized Import'!O6+O7) -> #NAME? | Q7: =IF(EQ('Normalized Import'!P6, ""),"", 'Normalized Import'!P6+P7) -> #NAME?
A8: ='Normalized Import'!A7 -> gitlab | B8: ='Normalized Import'!B7 -> 45078 | C8: ='Normalized Import'!C7 -> 25000 | E8: ='Most Recent Import'!E7 -> 36 | F8: ='Normalized Import'!E7 -> 0 | G8: =IF(EQ('Normalized Import'!F7, ""),"", 'Normalized Import'!F7+F8) -> #NAME? | H8: =IF(EQ('Normalized Import'!G7, ""), "", 'Normalized Import'!G7+G8) -> #NAME? | I8: =IF(EQ('Normalized Import'!H7, ""),"", 'Normalized Import'!H7+H8) -> #NAME? | J8: =IF(EQ('Normalized Import'!I7, ""), "", 'Normalized Import'!I7+I8) -> #NAME? | K8: =IF(EQ('Normalized Import'!J7, ""),"", 'Normalized Import'!J7+J8) -> #NAME? | L8: =IF(EQ('Normalized Import'!K7, ""), "", 'Normalized Import'!K7+K8) -> #NAME? | M8: =IF(EQ('Normalized Import'!L7, ""),"", 'Normalized Import'!L7+L8) -> #NAME? | N8: =IF(EQ('Normalized Import'!M7, ""), "", 'Normalized Import'!M7+M8) -> #NAME? | O8: =IF(EQ('Normalized Import'!N7, ""),"", 'Normalized Import'!N7+N8) -> #NAME? | P8: =IF(EQ('Normalized Import'!O7, ""), "", 'Normalized Import'!O7+O8) -> #NAME? | Q8: =IF(EQ('Normalized Import'!P7, ""),"", 'Normalized Import'!P7+P8) -> #NAME?
A9: ='Normalized Import'!A8 -> chegg | B9: ='Normalized Import'!B8 -> 45139 | C9: ='Normalized Import'!C8 -> 25000 | E9: ='Most Recent Import'!E8 -> 24 | F9: ='Normalized Import'!E8 -> 0 | G9: =IF(EQ('Normalized Import'!F8, ""),"", 'Normalized Import'!F8+F9) -> #NAME? | H9: =IF(EQ('Normalized Import'!G8, ""), "", 'Normalized Import'!G8+G9) -> #NAME? | I9: =IF(EQ('Normalized Import'!H8, ""),"", 'Normalized Import'!H8+H9) -> #NAME? | J9: =IF(EQ('Normalized Import'!I8, ""), "", 'Normalized Import'!I8+I9) -> #NAME? | K9: =IF(EQ('Normalized Import'!J8, ""),"", 'Normalized Import'!J8+J9) -> #NAME? | L9: =IF(EQ('Normalized Import'!K8, ""), "", 'Normalized Import'!K8+K9) -> #NAME? | M9: =IF(EQ('Normalized Import'!L8, ""),"", 'Normalized Import'!L8+L9) -> #NAME? | N9: =IF(EQ('Normalized Import'!M8, ""), "", 'Normalized Import'!M8+M9) -> #NAME? | O9: =IF(EQ('Normalized Import'!N8, ""),"", 'Normalized Import'!N8+N9) -> #NAME? | P9: =IF(EQ('Normalized Import'!O8, ""), "", 'Normalized Import'!O8+O9) -> #NAME? | Q9: =IF(EQ('Normalized Import'!P8, ""),"", 'Normalized Import'!P8+P9) -> #NAME?
A10: ='Normalized Import'!A9 -> ezcater | B10: ='Normalized Import'!B9 -> 45139 | C10: ='Normalized Import'!C9 -> 20000 | E10: ='Most Recent Import'!E9 -> 24 | F10: ='Normalized Import'!E9 -> 0 | G10: =IF(EQ('Normalized Import'!F9, ""),"", 'Normalized Import'!F9+F10) -> #NAME? | H10: =IF(EQ('Normalized Import'!G9, ""), "", 'Normalized Import'!G9+G10) -> #NAME? | I10: =IF(EQ('Normalized Import'!H9, ""),"", 'Normalized Import'!H9+H10) -> #NAME? | J10: =IF(EQ('Normalized Import'!I9, ""), "", 'Normalized Import'!I9+I10) -> #NAME? | K10: =IF(EQ('Normalized Import'!J9, ""),"", 'Normalized Import'!J9+J10) -> #NAME? | L10: =IF(EQ('Normalized Import'!K9, ""), "", 'Normalized Import'!K9+K10) -> #NAME? | M10: =IF(EQ('Normalized Import'!L9, ""),"", 'Normalized Import'!L9+L10) -> #NAME? | N10: =IF(EQ('Normalized Import'!M9, ""), "", 'Normalized Import'!M9+M10) -> #NAME? | O10: =IF(EQ('Normalized Import'!N9, ""),"", 'Normalized Import'!N9+N10) -> #NAME? | P10: =IF(EQ('Normalized Import'!O9, ""), "", 'Normalized Import'!O9+O10) -> #NAME? | Q10: =IF(EQ('Normalized Import'!P9, ""),"", 'Normalized Import'!P9+P10) -> #NAME?
A11: ='Normalized Import'!A10 -> impact | B11: ='Normalized Import'!B10 -> 45139 | C11: ='Normalized Import'!C10 -> 5000 | E11: ='Most Recent Import'!E10 -> 12 | F11: ='Normalized Import'!E10 -> 0 | G11: =IF(EQ('Normalized Import'!F10, ""),"", 'Normalized Import'!F10+F11) -> #NAME? | H11: =IF(EQ('Normalized Import'!G10, ""), "", 'Normalized Import'!G10+G11) -> #NAME? | I11: =IF(EQ('Normalized Import'!H10, ""),"", 'Normalized Import'!H10+H11) -> #NAME? | J11: =IF(EQ('Normalized Import'!I10, ""), "", 'Normalized Import'!I10+I11) -> #NAME? | K11: =IF(EQ('Normalized Import'!J10, ""),"", 'Normalized Import'!J10+J11) -> #NAME? | L11: =IF(EQ('Normalized Import'!K10, ""), "", 'Normalized Import'!K10+K11) -> #NAME? | M11: =IF(EQ('Normalized Import'!L10, ""),"", 'Normalized Import'!L10+L11) -> #NAME? | N11: =IF(EQ('Normalized Import'!M10, ""), "", 'Normalized Import'!M10+M11) -> #NAME? | O11: =IF(EQ('Normalized Import'!N10, ""),"", 'Normalized Import'!N10+N11) -> #NAME? | P11: =IF(EQ('Normalized Import'!O10, ""), "", 'Normalized Import'!O10+O11) -> #NAME? | Q11: =IF(EQ('Normalized Import'!P10, ""),"", 'Normalized Import'!P10+P11) -> #NAME?
A12: ='Normalized Import'!A11 -> usertesting | B12: ='Normalized Import'!B11 -> 45139 | C12: ='Normalized Import'!C11 -> 15000 | E12: ='Most Recent Import'!E11 -> 24 | F12: ='Normalized Import'!E11 -> 0 | G12: =IF(EQ('Normalized Import'!F11, ""),"", 'Normalized Import'!F11+F12) -> #NAME? | H12: =IF(EQ('Normalized Import'!G11, ""), "", 'Normalized Import'!G11+G12) -> #NAME? | I12: =IF(EQ('Normalized Import'!H11, ""),"", 'Normalized Import'!H11+H12) -> #NAME? | J12: =IF(EQ('Normalized Import'!I11, ""), "", 'Normalized Import'!I11+I12) -> #NAME? | K12: =IF(EQ('Normalized Import'!J11, ""),"", 'Normalized Import'!J11+J12) -> #NAME? | L12: =IF(EQ('Normalized Import'!K11, ""), "", 'Normalized Import'!K11+K12) -> #NAME? | M12: =IF(EQ('Normalized Import'!L11, ""),"", 'Normalized Import'!L11+L12) -> #NAME? | N12: =IF(EQ('Normalized Import'!M11, ""), "", 'Normalized Import'!M11+M12) -> #NAME? | O12: =IF(EQ('Normalized Import'!N11, ""),"", 'Normalized Import'!N11+N12) -> #NAME? | P12: =IF(EQ('Normalized Import'!O11, ""), "", 'Normalized Import'!O11+O12) -> #NAME? | Q12: =IF(EQ('Normalized Import'!P11, ""),"", 'Normalized Import'!P11+P12) -> #NAME?
A13: ='Normalized Import'!A12 -> xplor_technologies | B13: ='Normalized Import'!B12 -> 45139 | C13: ='Normalized Import'!C12 -> 8000 | E13: ='Most Recent Import'!E12 -> 24 | F13: ='Normalized Import'!E12 -> 5 | G13: =IF(EQ('Normalized Import'!F12, ""),"", 'Normalized Import'!F12+F13) -> #NAME? | H13: =IF(EQ('Normalized Import'!G12, ""), "", 'Normalized Import'!G12+G13) -> #NAME? | I13: =IF(EQ('Normalized Import'!H12, ""),"", 'Normalized Import'!H12+H13) -> #NAME? | J13: =IF(EQ('Normalized Import'!I12, ""), "", 'Normalized Import'!I12+I13) -> #NAME? | K13: =IF(EQ('Normalized Import'!J12, ""),"", 'Normalized Import'!J12+J13) -> #NAME? | L13: =IF(EQ('Normalized Import'!K12, ""), "", 'Normalized Import'!K12+K13) -> #NAME? | M13: =IF(EQ('Normalized Import'!L12, ""),"", 'Normalized Import'!L12+L13) -> #NAME? | N13: =IF(EQ('Normalized Import'!M12, ""), "", 'Normalized Import'!M12+M13) -> #NAME? | O13: =IF(EQ('Normalized Import'!N12, ""),"", 'Normalized Import'!N12+N13) -> #NAME? | P13: =IF(EQ('Normalized Import'!O12, ""), "", 'Normalized Import'!O12+O13) -> #NAME? | Q13: =IF(EQ('Normalized Import'!P12, ""),"", 'Normalized Import'!P12+P13) -> #NAME?
A14: ='Normalized Import'!A13 -> consensys | B14: ='Normalized Import'!B13 -> 45139 | C14: ='Normalized Import'!C13 -> 3000 | E14: ='Most Recent Import'!E13 -> 12 | F14: ='Normalized Import'!E13 -> 2 | G14: =IF(EQ('Normalized Import'!F13, ""),"", 'Normalized Import'!F13+F14) -> #NAME? | H14: =IF(EQ('Normalized Import'!G13, ""), "", 'Normalized Import'!G13+G14) -> #NAME? | I14: =IF(EQ('Normalized Import'!H13, ""),"", 'Normalized Import'!H13+H14) -> #NAME? | J14: =IF(EQ('Normalized Import'!I13, ""), "", 'Normalized Import'!I13+I14) -> #NAME? | K14: =IF(EQ('Normalized Import'!J13, ""),"", 'Normalized Import'!J13+J14) -> #NAME? | L14: =IF(EQ('Normalized Import'!K13, ""), "", 'Normalized Import'!K13+K14) -> #NAME? | M14: =IF(EQ('Normalized Import'!L13, ""),"", 'Normalized Import'!L13+L14) -> #NAME? | N14: =IF(EQ('Normalized Import'!M13, ""), "", 'Normalized Import'!M13+M14) -> #NAME? | O14: =IF(EQ('Normalized Import'!N13, ""),"", 'Normalized Import'!N13+N14) -> #NAME? | P14: =IF(EQ('Normalized Import'!O13, ""), "", 'Normalized Import'!O13+O14) -> #NAME? | Q14: =IF(EQ('Normalized Import'!P13, ""),"", 'Normalized Import'!P13+P14) -> #NAME?
... A17: ='Normalized Import'!A16 -> sonos | B17: ='Normalized Import'!B16 -> 45170 | C17: ='Normalized Import'!C16 -> 23000 | E17: ='Most Recent Import'!E16 -> 24 | F17: ='Normalized Import'!E16 -> 0 | G17: =IF(EQ('Normalized Import'!F16, ""),"", 'Normalized Import'!F16+F17) -> #NAME? | H17: =IF(EQ('Normalized Import'!G16, ""), "", 'Normalized Import'!G16+G17) -> #NAME? | I17: =IF(EQ('Normalized Import'!H16, ""),"", 'Normalized Import'!H16+H17) -> #NAME? | J17: =IF(EQ('Normalized Import'!I16, ""), "", 'Normalized Import'!I16+I17) -> #NAME? | K17: =IF(EQ('Normalized Import'!J16, ""),"", 'Normalized Import'!J16+J17) -> #NAME? | L17: =IF(EQ('Normalized Import'!K16, ""), "", 'Normalized Import'!K16+K17) -> #NAME? | M17: =IF(EQ('Normalized Import'!L16, ""),"", 'Normalized Import'!L16+L17) -> #NAME? | N17: =IF(EQ('Normalized Import'!M16, ""), "", 'Normalized Import'!M16+M17) -> #NAME? | O17: =IF(EQ('Normalized Import'!N16, ""),"", 'Normalized Import'!N16+N17) -> #NAME? | P17: =IF(EQ('Normalized Import'!O16, ""), "", 'Normalized Import'!O16+O17) -> #NAME? | Q17: =IF(EQ('Normalized Import'!P16, ""),"", 'Normalized Import'!P16+P17) -> #NAME?
A18: ='Normalized Import'!A17 -> soundtrap | B18: ='Normalized Import'!B17 -> 45170 | C18: ='Normalized Import'!C17 -> 5000 | E18: ='Most Recent Import'!E17 -> 12 | F18: ='Normalized Import'!E17 -> 0 | G18: =IF(EQ('Normalized Import'!F17, ""),"", 'Normalized Import'!F17+F18) -> #NAME? | H18: =IF(EQ('Normalized Import'!G17, ""), "", 'Normalized Import'!G17+G18) -> #NAME? | I18: =IF(EQ('Normalized Import'!H17, ""),"", 'Normalized Import'!H17+H18) -> #NAME? | J18: =IF(EQ('Normalized Import'!I17, ""), "", 'Normalized Import'!I17+I18) -> #NAME? | K18: =IF(EQ('Normalized Import'!J17, ""),"", 'Normalized Import'!J17+J18) -> #NAME? | L18: =IF(EQ('Normalized Import'!K17, ""), "", 'Normalized Import'!K17+K18) -> #NAME? | M18: =IF(EQ('Normalized Import'!L17, ""),"", 'Normalized Import'!L17+L18) -> #NAME? | N18: =IF(EQ('Normalized Import'!M17, ""), "", 'Normalized Import'!M17+M18) -> #NAME? | O18: =IF(EQ('Normalized Import'!N17, ""),"", 'Normalized Import'!N17+N18) -> #NAME? | P18: =IF(EQ('Normalized Import'!O17, ""), "", 'Normalized Import'!O17+O18) -> #NAME? | Q18: =IF(EQ('Normalized Import'!P17, ""),"", 'Normalized Import'!P17+P18) -> #NAME? | T18: #REF! | U18: #REF! | V18: #REF! | W18: #REF! | X18: #REF! | Y18: #REF!
A19: ='Normalized Import'!A18 -> yahoo | B19: ='Normalized Import'!B18 -> 45170 | C19: ='Normalized Import'!C18 -> 32000 | E19: ='Most Recent Import'!E18 -> 24 | F19: ='Normalized Import'!E18 -> 0 | G19: =IF(EQ('Normalized Import'!F18, ""),"", 'Normalized Import'!F18+F19) -> #NAME? | H19: =IF(EQ('Normalized Import'!G18, ""), "", 'Normalized Import'!G18+G19) -> #NAME? | I19: =IF(EQ('Normalized Import'!H18, ""),"", 'Normalized Import'!H18+H19) -> #NAME? | J19: =IF(EQ('Normalized Import'!I18, ""), "", 'Normalized Import'!I18+I19) -> #NAME? | K19: =IF(EQ('Normalized Import'!J18, ""),"", 'Normalized Import'!J18+J19) -> #NAME? | L19: =IF(EQ('Normalized Import'!K18, ""), "", 'Normalized Import'!K18+K19) -> #NAME? | M19: =IF(EQ('Normalized Import'!L18, ""),"", 'Normalized Import'!L18+L19) -> #NAME? | N19: =IF(EQ('Normalized Import'!M18, ""), "", 'Normalized Import'!M18+M19) -> #NAME? | O19: =IF(EQ('Normalized Import'!N18, ""),"", 'Normalized Import'!N18+N19) -> #NAME? | P19: =IF(EQ('Normalized Import'!O18, ""), "", 'Normalized Import'!O18+O19) -> #NAME? | Q19: =IF(EQ('Normalized Import'!P18, ""),"", 'Normalized Import'!P18+P19) -> #NAME? | T19: #REF! | U19: #REF! | V19: #REF! | W19: #REF! | X19: #REF! | Y19: #REF!
A20: ='Normalized Import'!A19 -> zwift | B20: ='Normalized Import'!B19 -> 45170 | C20: ='Normalized Import'!C19 -> 15000 | E20: ='Most Recent Import'!E19 -> 12 | F20: ='Normalized Import'!E19 -> 0 | G20: =IF(EQ('Normalized Import'!F19, ""),"", 'Normalized Import'!F19+F20) -> #NAME? | H20: =IF(EQ('Normalized Import'!G19, ""), "", 'Normalized Import'!G19+G20) -> #NAME? | I20: =IF(EQ('Normalized Import'!H19, ""),"", 'Normalized Import'!H19+H20) -> #NAME? | J20: =IF(EQ('Normalized Import'!I19, ""), "", 'Normalized Import'!I19+I20) -> #NAME? | K20: =IF(EQ('Normalized Import'!J19, ""),"", 'Normalized Import'!J19+J20) -> #NAME? | L20: =IF(EQ('Normalized Import'!K19, ""), "", 'Normalized Import'!K19+K20) -> #NAME? | M20: =IF(EQ('Normalized Import'!L19, ""),"", 'Normalized Import'!L19+L20) -> #NAME? | N20: =IF(EQ('Normalized Import'!M19, ""), "", 'Normalized Import'!M19+M20) -> #NAME? | O20: =IF(EQ('Normalized Import'!N19, ""),"", 'Normalized Import'!N19+N20) -> #NAME? | P20: =IF(EQ('Normalized Import'!O19, ""), "", 'Normalized Import'!O19+O20) -> #NAME? | Q20: =IF(EQ('Normalized Import'!P19, ""),"", 'Normalized Import'!P19+P20) -> #NAME? | T20: #REF! | U20: #REF! | V20: #REF! | W20: #REF! | X20: #REF! | Y20: #REF!
A21: ='Normalized Import'!A20 -> angi | B21: ='Normalized Import'!B20 -> 45200 | C21: ='Normalized Import'!C20 -> 10000 | E21: ='Most Recent Import'!E20 -> 24 | F21: ='Normalized Import'!E20 -> 1 | G21: =IF(EQ('Normalized Import'!F20, ""),"", 'Normalized Import'!F20+F21) -> #NAME? | H21: =IF(EQ('Normalized Import'!G20, ""), "", 'Normalized Import'!G20+G21) -> #NAME? | I21: =IF(EQ('Normalized Import'!H20, ""),"", 'Normalized Import'!H20+H21) -> #NAME? | J21: =IF(EQ('Normalized Import'!I20, ""), "", 'Normalized Import'!I20+I21) -> #NAME? | K21: =IF(EQ('Normalized Import'!J20, ""),"", 'Normalized Import'!J20+J21) -> #NAME? | L21: =IF(EQ('Normalized Import'!K20, ""), "", 'Normalized Import'!K20+K21) -> #NAME? | M21: =IF(EQ('Normalized Import'!L20, ""),"", 'Normalized Import'!L20+L21) -> #NAME? | N21: =IF(EQ('Normalized Import'!M20, ""), "", 'Normalized Import'!M20+M21) -> #NAME? | O21: =IF(EQ('Normalized Import'!N20, ""),"", 'Normalized Import'!N20+N21) -> #NAME? | P21: =IF(EQ('Normalized Import'!O20, ""), "", 'Normalized Import'!O20+O21) -> #NAME? | Q21: =IF(EQ('Normalized Import'!P20, ""),"", 'Normalized Import'!P20+P21) -> #NAME? | T21: #REF! | U21: #REF! | V21: #REF! | W21: #REF! | X21: #REF! | Y21: #REF!
A22: ='Normalized Import'!A21 -> rockwell | B22: ='Normalized Import'!B21 -> 45200 | C22: ='Normalized Import'!C21 -> 20000 | E22: ='Most Recent Import'!E21 -> 24 | F22: ='Normalized Import'!E21 -> 0 | G22: =IF(EQ('Normalized Import'!F21, ""),"", 'Normalized Import'!F21+F22) -> #NAME? | H22: =IF(EQ('Normalized Import'!G21, ""), "", 'Normalized Import'!G21+G22) -> #NAME? | I22: =IF(EQ('Normalized Import'!H21, ""),"", 'Normalized Import'!H21+H22) -> #NAME? | J22: =IF(EQ('Normalized Import'!I21, ""), "", 'Normalized Import'!I21+I22) -> #NAME? | K22: =IF(EQ('Normalized Import'!J21, ""),"", 'Normalized Import'!J21+J22) -> #NAME? | L22: =IF(EQ('Normalized Import'!K21, ""), "", 'Normalized Import'!K21+K22) -> #NAME? | M22: =IF(EQ('Normalized Import'!L21, ""),"", 'Normalized Import'!L21+L22) -> #NAME? | N22: =IF(EQ('Normalized Import'!M21, ""), "", 'Normalized Import'!M21+M22) -> #NAME? | O22: =IF(EQ('Normalized Import'!N21, ""),"", 'Normalized Import'!N21+N22) -> #NAME? | P22: =IF(EQ('Normalized Import'!O21, ""), "", 'Normalized Import'!O21+O22) -> #NAME? | Q22: =IF(EQ('Normalized Import'!P21, ""),"", 'Normalized Import'!P21+P22) -> #NAME? | T22: #REF! | U22: #REF! | V22: #REF! | W22: #REF! | X22: #REF! | Y22: #REF!
A23: ='Normalized Import'!A22 -> snowplow | B23: ='Normalized Import'!B22 -> 45200 | C23: ='Normalized Import'!C22 -> 2000 | E23: ='Most Recent Import'!E22 -> 12 | F23: ='Normalized Import'!E22 -> 0 | G23: =IF(EQ('Normalized Import'!F22, ""),"", 'Normalized Import'!F22+F23) -> #NAME? | H23: =IF(EQ('Normalized Import'!G22, ""), "", 'Normalized Import'!G22+G23) -> #NAME? | I23: =IF(EQ('Normalized Import'!H22, ""),"", 'Normalized Import'!H22+H23) -> #NAME? | J23: =IF(EQ('Normalized Import'!I22, ""), "", 'Normalized Import'!I22+I23) -> #NAME? | K23: =IF(EQ('Normalized Import'!J22, ""),"", 'Normalized Import'!J22+J23) -> #NAME? | L23: =IF(EQ('Normalized Import'!K22, ""), "", 'Normalized Import'!K22+K23) -> #NAME? | M23: =IF(EQ('Normalized Import'!L22, ""),"", 'Normalized Import'!L22+L23) -> #NAME? | N23: =IF(EQ('Normalized Import'!M22, ""), "", 'Normalized Import'!M22+M23) -> #NAME? | O23: =IF(EQ('Normalized Import'!N22, ""),"", 'Normalized Import'!N22+N23) -> #NAME? | P23: =IF(EQ('Normalized Import'!O22, ""), "", 'Normalized Import'!O22+O23) -> #NAME? | Q23: =IF(EQ('Normalized Import'!P22, ""),"", 'Normalized Import'!P22+P23) -> #NAME? | T23: #REF! | U23: #REF! | V23: #REF! | W23: #REF! | X23: #REF! | Y23: #REF!
A24: ='Normalized Import'!A23 -> predictive_index | B24: ='Normalized Import'!B23 -> 45231 | C24: ='Normalized Import'!C23 -> 2000 | E24: ='Most Recent Import'!E23 -> 12 | F24: ='Normalized Import'!E23 -> 1 | G24: =IF(EQ('Normalized Import'!F23, ""),"", 'Normalized Import'!F23+F24) -> #NAME? | H24: =IF(EQ('Normalized Import'!G23, ""), "", 'Normalized Import'!G23+G24) -> #NAME? | I24: =IF(EQ('Normalized Import'!H23, ""),"", 'Normalized Import'!H23+H24) -> #NAME? | J24: =IF(EQ('Normalized Import'!I23, ""), "", 'Normalized Import'!I23+I24) -> #NAME? | K24: =IF(EQ('Normalized Import'!J23, ""),"", 'Normalized Import'!J23+J24) -> #NAME? | L24: =IF(EQ('Normalized Import'!K23, ""), "", 'Normalized Import'!K23+K24) -> #NAME? | M24: =IF(EQ('Normalized Import'!L23, ""),"", 'Normalized Import'!L23+L24) -> #NAME? | N24: =IF(EQ('Normalized Import'!M23, ""), "", 'Normalized Import'!M23+M24) -> #NAME? | O24: =IF(EQ('Normalized Import'!N23, ""),"", 'Normalized Import'!N23+N24) -> #NAME? | P24: =IF(EQ('Normalized Import'!O23, ""), "", 'Normalized Import'!O23+O24) -> #NAME? | Q24: =IF(EQ('Normalized Import'!P23, ""),"", 'Normalized Import'!P23+P24) -> #NAME? | T24: #REF! | U24: #REF! | V24: #REF! | W24: #REF! | X24: #REF! | Y24: #REF!
A25: ='Normalized Import'!A24 -> biorender | B25: ='Normalized Import'!B24 -> 45261 | C25: ='Normalized Import'!C24 -> 2000 | E25: ='Most Recent Import'!E24 -> 24 | F25: ='Normalized Import'!E24 -> 3 | G25: =IF(EQ('Normalized Import'!F24, ""),"", 'Normalized Import'!F24+F25) -> #NAME? | H25: =IF(EQ('Normalized Import'!G24, ""), "", 'Normalized Import'!G24+G25) -> #NAME? | I25: =IF(EQ('Normalized Import'!H24, ""),"", 'Normalized Import'!H24+H25) -> #NAME? | J25: =IF(EQ('Normalized Import'!I24, ""), "", 'Normalized Import'!I24+I25) -> #NAME? | K25: =IF(EQ('Normalized Import'!J24, ""),"", 'Normalized Import'!J24+J25) -> #NAME? | L25: =IF(EQ('Normalized Import'!K24, ""), "", 'Normalized Import'!K24+K25) -> #NAME? | M25: =IF(EQ('Normalized Import'!L24, ""),"", 'Normalized Import'!L24+L25) -> #NAME? | N25: =IF(EQ('Normalized Import'!M24, ""), "", 'Normalized Import'!M24+M25) -> #NAME? | O25: =IF(EQ('Normalized Import'!N24, ""),"", 'Normalized Import'!N24+N25) -> #NAME? | P25: =IF(EQ('Normalized Import'!O24, ""), "", 'Normalized Import'!O24+O25) -> #NAME? | Q25: =IF(EQ('Normalized Import'!P24, ""),"", 'Normalized Import'!P24+P25) -> #NAME? | T25: #REF! | U25: #REF! | V25: #REF! | W25: #REF! | X25: #REF! | Y25: #REF!
A26: ='Normalized Import'!A25 -> checkr | B26: ='Normalized Import'!B25 -> 45261 | C26: ='Normalized Import'!C25 -> 10000 | E26: ='Most Recent Import'!E25 -> 24 | F26: ='Normalized Import'!E25 -> 0 | G26: =IF(EQ('Normalized Import'!F25, ""),"", 'Normalized Import'!F25+F26) -> #NAME? | H26: =IF(EQ('Normalized Import'!G25, ""), "", 'Normalized Import'!G25+G26) -> #NAME? | I26: =IF(EQ('Normalized Import'!H25, ""),"", 'Normalized Import'!H25+H26) -> #NAME? | J26: =IF(EQ('Normalized Import'!I25, ""), "", 'Normalized Import'!I25+I26) -> #NAME? | K26: =IF(EQ('Normalized Import'!J25, ""),"", 'Normalized Import'!J25+J26) -> #NAME? | L26: =IF(EQ('Normalized Import'!K25, ""), "", 'Normalized Import'!K25+K26) -> #NAME? | M26: =IF(EQ('Normalized Import'!L25, ""),"", 'Normalized Import'!L25+L26) -> #NAME? | N26: =IF(EQ('Normalized Import'!M25, ""), "", 'Normalized Import'!M25+M26) -> #NAME? | O26: =IF(EQ('Normalized Import'!N25, ""),"", 'Normalized Import'!N25+N26) -> #NAME? | P26: =IF(EQ('Normalized Import'!O25, ""), "", 'Normalized Import'!O25+O26) -> #NAME? | Q26: =IF(EQ('Normalized Import'!P25, ""),"", 'Normalized Import'!P25+P26) -> #NAME? | T26: #REF! | U26: #REF! | V26: #REF! | W26: #REF! | X26: #REF! | Y26: #REF!
A27: ='Normalized Import'!A26 -> gp-research | B27: ='Normalized Import'!B26 -> 45261 | C27: ='Normalized Import'!C26 -> 10000 | E27: ='Most Recent Import'!E26 -> 24 | F27: ='Normalized Import'!E26 -> 0 | G27: =IF(EQ('Normalized Import'!F26, ""),"", 'Normalized Import'!F26+F27) -> #NAME? | H27: =IF(EQ('Normalized Import'!G26, ""), "", 'Normalized Import'!G26+G27) -> #NAME? | I27: =IF(EQ('Normalized Import'!H26, ""),"", 'Normalized Import'!H26+H27) -> #NAME? | J27: =IF(EQ('Normalized Import'!I26, ""), "", 'Normalized Import'!I26+I27) -> #NAME? | K27: =IF(EQ('Normalized Import'!J26, ""),"", 'Normalized Import'!J26+J27) -> #NAME? | L27: =IF(EQ('Normalized Import'!K26, ""), "", 'Normalized Import'!K26+K27) -> #NAME? | M27: =IF(EQ('Normalized Import'!L26, ""),"", 'Normalized Import'!L26+L27) -> #NAME? | N27: =IF(EQ('Normalized Import'!M26, ""), "", 'Normalized Import'!M26+M27) -> #NAME? | O27: =IF(EQ('Normalized Import'!N26, ""),"", 'Normalized Import'!N26+N27) -> #NAME? | P27: =IF(EQ('Normalized Import'!O26, ""), "", 'Normalized Import'!O26+O27) -> #NAME? | Q27: =IF(EQ('Normalized Import'!P26, ""),"", 'Normalized Import'!P26+P27) -> #NAME? | T27: #REF! | U27: #REF! | V27: #REF! | W27: #REF! | X27: #REF! | Y27: #REF!
A28: ='Normalized Import'!A27 -> sailpoint | B28: ='Normalized Import'!B27 -> 45261 | C28: ='Normalized Import'!C27 -> 12000 | E28: ='Most Recent Import'!E27 -> 12 | F28: ='Normalized Import'!E27 -> 0 | G28: =IF(EQ('Normalized Import'!F27, ""),"", 'Normalized Import'!F27+F28) -> #NAME? | H28: =IF(EQ('Normalized Import'!G27, ""), "", 'Normalized Import'!G27+G28) -> #NAME? | I28: =IF(EQ('Normalized Import'!H27, ""),"", 'Normalized Import'!H27+H28) -> #NAME? | J28: =IF(EQ('Normalized Import'!I27, ""), "", 'Normalized Import'!I27+I28) -> #NAME? | K28: =IF(EQ('Normalized Import'!J27, ""),"", 'Normalized Import'!J27+J28) -> #NAME? | L28: =IF(EQ('Normalized Import'!K27, ""), "", 'Normalized Import'!K27+K28) -> #NAME? | M28: =IF(EQ('Normalized Import'!L27, ""),"", 'Normalized Import'!L27+L28) -> #NAME? | N28: =IF(EQ('Normalized Import'!M27, ""), "", 'Normalized Import'!M27+M28) -> #NAME? | O28: =IF(EQ('Normalized Import'!N27, ""),"", 'Normalized Import'!N27+N28) -> #NAME? | P28: =IF(EQ('Normalized Import'!O27, ""), "", 'Normalized Import'!O27+O28) -> #NAME? | Q28: =IF(EQ('Normalized Import'!P27, ""),"", 'Normalized Import'!P27+P28) -> #NAME? | T28: #REF! | U28: #REF! | V28: #REF! | W28: #REF! | X28: #REF! | Y28: #REF!
A29: ='Normalized Import'!A28 -> stack_overflow | B29: ='Normalized Import'!B28 -> 45261 | C29: ='Normalized Import'!C28 -> 22500 | E29: ='Most Recent Import'!E28 -> 24 | F29: ='Normalized Import'!E28 -> 0 | G29: =IF(EQ('Normalized Import'!F28, ""),"", 'Normalized Import'!F28+F29) -> #NAME? | H29: =IF(EQ('Normalized Import'!G28, ""), "", 'Normalized Import'!G28+G29) -> #NAME? | I29: =IF(EQ('Normalized Import'!H28, ""),"", 'Normalized Import'!H28+H29) -> #NAME? | J29: =IF(EQ('Normalized Import'!I28, ""), "", 'Normalized Import'!I28+I29) -> #NAME? | K29: =IF(EQ('Normalized Import'!J28, ""),"", 'Normalized Import'!J28+J29) -> #NAME? | L29: =IF(EQ('Normalized Import'!K28, ""), "", 'Normalized Import'!K28+K29) -> #NAME? | M29: =IF(EQ('Normalized Import'!L28, ""),"", 'Normalized Import'!L28+L29) -> #NAME? | N29: =IF(EQ('Normalized Import'!M28, ""), "", 'Normalized Import'!M28+M29) -> #NAME? | O29: =IF(EQ('Normalized Import'!N28, ""),"", 'Normalized Import'!N28+N29) -> #NAME? | P29: =IF(EQ('Normalized Import'!O28, ""), "", 'Normalized Import'!O28+O29) -> #NAME? | Q29: =IF(EQ('Normalized Import'!P28, ""),"", 'Normalized Import'!P28+P29) -> #NAME? | T29: #REF! | U29: #REF! | V29: #REF! | W29: #REF! | X29: #REF! | Y29: #REF!
... A40: ='Normalized Import'!A39 -> braze | B40: ='Normalized Import'!B39 -> 45352 | C40: ='Normalized Import'!C39 -> 25000 | E40: ='Most Recent Import'!E39 -> 24 | F40: ='Normalized Import'!E39 -> 3 | G40: =IF(EQ('Normalized Import'!F39, ""),"", 'Normalized Import'!F39+F40) -> #NAME? | H40: =IF(EQ('Normalized Import'!G39, ""), "", 'Normalized Import'!G39+G40) -> #NAME? | I40: =IF(EQ('Normalized Import'!H39, ""),"", 'Normalized Import'!H39+H40) -> #NAME? | J40: =IF(EQ('Normalized Import'!I39, ""), "", 'Normalized Import'!I39+I40) -> #NAME? | K40: =IF(EQ('Normalized Import'!J39, ""),"", 'Normalized Import'!J39+J40) -> #NAME? | L40: =IF(EQ('Normalized Import'!K39, ""), "", 'Normalized Import'!K39+K40) -> #NAME? | M40: =IF(EQ('Normalized Import'!L39, ""),"", 'Normalized Import'!L39+L40) -> #NAME? | N40: =IF(EQ('Normalized Import'!M39, ""), "", 'Normalized Import'!M39+M40) -> #NAME? | O40: =IF(EQ('Normalized Import'!N39, ""),"", 'Normalized Import'!N39+N40) -> #NAME? | P40: =IF(EQ('Normalized Import'!O39, ""), "", 'Normalized Import'!O39+O40) -> #NAME? | Q40: =IF(EQ('Normalized Import'!P39, ""),"", 'Normalized Import'!P39+P40) -> #NAME? | T40: #REF! | U40: #REF! | V40: #REF! | W40: #REF! | X40: #REF! | Y40: #REF!
A41: ='Normalized Import'!A40 -> cloudflare | B41: ='Normalized Import'!B40 -> 45352 | C41: ='Normalized Import'!C40 -> 20000 | E41: ='Most Recent Import'!E40 -> 24 | F41: ='Normalized Import'!E40 -> 0 | G41: =IF(EQ('Normalized Import'!F40, ""),"", 'Normalized Import'!F40+F41) -> #NAME? | H41: =IF(EQ('Normalized Import'!G40, ""), "", 'Normalized Import'!G40+G41) -> #NAME? | I41: =IF(EQ('Normalized Import'!H40, ""),"", 'Normalized Import'!H40+H41) -> #NAME? | J41: =IF(EQ('Normalized Import'!I40, ""), "", 'Normalized Import'!I40+I41) -> #NAME? | K41: =IF(EQ('Normalized Import'!J40, ""),"", 'Normalized Import'!J40+J41) -> #NAME? | L41: =IF(EQ('Normalized Import'!K40, ""), "", 'Normalized Import'!K40+K41) -> #NAME? | M41: =IF(EQ('Normalized Import'!L40, ""),"", 'Normalized Import'!L40+L41) -> #NAME? | N41: =IF(EQ('Normalized Import'!M40, ""), "", 'Normalized Import'!M40+M41) -> #NAME? | O41: =IF(EQ('Normalized Import'!N40, ""),"", 'Normalized Import'!N40+N41) -> #NAME? | P41: =IF(EQ('Normalized Import'!O40, ""), "", 'Normalized Import'!O40+O41) -> #NAME? | Q41: =IF(EQ('Normalized Import'!P40, ""),"", 'Normalized Import'!P40+P41) -> #NAME?
A42: ='Normalized Import'!A41 -> hellofresh | B42: ='Normalized Import'!B41 -> 45352 | C42: ='Normalized Import'!C41 -> 10000 | E42: ='Most Recent Import'!E41 -> 12 | F42: ='Normalized Import'!E41 -> 0 | G42: =IF(EQ('Normalized Import'!F41, ""),"", 'Normalized Import'!F41+F42) -> #NAME? | H42: =IF(EQ('Normalized Import'!G41, ""), "", 'Normalized Import'!G41+G42) -> #NAME? | I42: =IF(EQ('Normalized Import'!H41, ""),"", 'Normalized Import'!H41+H42) -> #NAME? | J42: =IF(EQ('Normalized Import'!I41, ""), "", 'Normalized Import'!I41+I42) -> #NAME? | K42: =IF(EQ('Normalized Import'!J41, ""),"", 'Normalized Import'!J41+J42) -> #NAME? | L42: =IF(EQ('Normalized Import'!K41, ""), "", 'Normalized Import'!K41+K42) -> #NAME? | M42: =IF(EQ('Normalized Import'!L41, ""),"", 'Normalized Import'!L41+L42) -> #NAME? | N42: =IF(EQ('Normalized Import'!M41, ""), "", 'Normalized Import'!M41+M42) -> #NAME? | O42: =IF(EQ('Normalized Import'!N41, ""),"", 'Normalized Import'!N41+N42) -> #NAME? | P42: =IF(EQ('Normalized Import'!O41, ""), "", 'Normalized Import'!O41+O42) -> #NAME? | Q42: =IF(EQ('Normalized Import'!P41, ""),"", 'Normalized Import'!P41+P42) -> #NAME?
A43: ='Normalized Import'!A42 -> mongodb | B43: ='Normalized Import'!B42 -> 45352 | C43: ='Normalized Import'!C42 -> 20000 | E43: ='Most Recent Import'!E42 -> 36 | F43: ='Normalized Import'!E42 -> 1 | G43: =IF(EQ('Normalized Import'!F42, ""),"", 'Normalized Import'!F42+F43) -> #NAME? | H43: =IF(EQ('Normalized Import'!G42, ""), "", 'Normalized Import'!G42+G43) -> #NAME? | I43: =IF(EQ('Normalized Import'!H42, ""),"", 'Normalized Import'!H42+H43) -> #NAME? | J43: =IF(EQ('Normalized Import'!I42, ""), "", 'Normalized Import'!I42+I43) -> #NAME? | K43: =IF(EQ('Normalized Import'!J42, ""),"", 'Normalized Import'!J42+J43) -> #NAME? | L43: =IF(EQ('Normalized Import'!K42, ""), "", 'Normalized Import'!K42+K43) -> #NAME? | M43: =IF(EQ('Normalized Import'!L42, ""),"", 'Normalized Import'!L42+L43) -> #NAME? | N43: =IF(EQ('Normalized Import'!M42, ""), "", 'Normalized Import'!M42+M43) -> #NAME? | O43: =IF(EQ('Normalized Import'!N42, ""),"", 'Normalized Import'!N42+N43) -> #NAME? | P43: =IF(EQ('Normalized Import'!O42, ""), "", 'Normalized Import'!O42+O43) -> #NAME? | Q43: =IF(EQ('Normalized Import'!P42, ""),"", 'Normalized Import'!P42+P43) -> #NAME?
A44: ='Normalized Import'!A43 -> xometry | B44: ='Normalized Import'!B43 -> 45383 | C44: ='Normalized Import'!C43 -> 10000 | E44: ='Most Recent Import'!E43 -> 12 | F44: ='Normalized Import'!E43 -> 4 | G44: =IF(EQ('Normalized Import'!F43, ""),"", 'Normalized Import'!F43+F44) -> #NAME? | H44: =IF(EQ('Normalized Import'!G43, ""), "", 'Normalized Import'!G43+G44) -> #NAME? | I44: =IF(EQ('Normalized Import'!H43, ""),"", 'Normalized Import'!H43+H44) -> #NAME? | J44: =IF(EQ('Normalized Import'!I43, ""), "", 'Normalized Import'!I43+I44) -> #NAME? | K44: =IF(EQ('Normalized Import'!J43, ""),"", 'Normalized Import'!J43+J44) -> #NAME? | L44: =IF(EQ('Normalized Import'!K43, ""), "", 'Normalized Import'!K43+K44) -> #NAME? | M44: =IF(EQ('Normalized Import'!L43, ""),"", 'Normalized Import'!L43+L44) -> #NAME? | N44: =IF(EQ('Normalized Import'!M43, ""), "", 'Normalized Import'!M43+M44) -> #NAME? | O44: =IF(EQ('Normalized Import'!N43, ""),"", 'Normalized Import'!N43+N44) -> #NAME? | P44: =IF(EQ('Normalized Import'!O43, ""), "", 'Normalized Import'!O43+O44) -> #NAME? | Q44: =IF(EQ('Normalized Import'!P43, ""),"", 'Normalized Import'!P43+P44) -> #NAME?
A45: ='Normalized Import'!A44 -> 0 | B45: ='Normalized Import'!B44 -> #VALUE! | C45: ='Normalized Import'!C44 -> 0 | E45: ='Most Recent Import'!E44 -> 0 | F45: ='Normalized Import'!E44 -> #VALUE! | G45: =IF(EQ('Normalized Import'!F44, ""),"", 'Normalized Import'!F44+F45) -> #NAME? | H45: =IF(EQ('Normalized Import'!G44, ""), "", 'Normalized Import'!G44+G45) -> #NAME? | I45: =IF(EQ('Normalized Import'!H44, ""),"", 'Normalized Import'!H44+H45) -> #NAME? | J45: =IF(EQ('Normalized Import'!I44, ""), "", 'Normalized Import'!I44+I45) -> #NAME? | K45: =IF(EQ('Normalized Import'!J44, ""),"", 'Normalized Import'!J44+J45) -> #NAME? | L45: =IF(EQ('Normalized Import'!K44, ""), "", 'Normalized Import'!K44+K45) -> #NAME? | M45: =IF(EQ('Normalized Import'!L44, ""),"", 'Normalized Import'!L44+L45) -> #NAME? | N45: =IF(EQ('Normalized Import'!M44, ""), "", 'Normalized Import'!M44+M45) -> #NAME? | O45: =IF(EQ('Normalized Import'!N44, ""),"", 'Normalized Import'!N44+N45) -> #NAME? | P45: =IF(EQ('Normalized Import'!O44, ""), "", 'Normalized Import'!O44+O45) -> #NAME? | Q45: =IF(EQ('Normalized Import'!P44, ""),"", 'Normalized Import'!P44+P45) -> #NAME?
A46: ='Normalized Import'!A45 -> 0 | B46: ='Normalized Import'!B45 -> #VALUE! | C46: ='Normalized Import'!C45 -> 0 | E46: ='Most Recent Import'!E45 -> 0 | F46: ='Normalized Import'!E45 -> #VALUE! | G46: =IF(EQ('Normalized Import'!F45, ""),"", 'Normalized Import'!F45+F46) -> #NAME? | H46: =IF(EQ('Normalized Import'!G45, ""), "", 'Normalized Import'!G45+G46) -> #NAME? | I46: =IF(EQ('Normalized Import'!H45, ""),"", 'Normalized Import'!H45+H46) -> #NAME? | J46: =IF(EQ('Normalized Import'!I45, ""), "", 'Normalized Import'!I45+I46) -> #NAME? | K46: =IF(EQ('Normalized Import'!J45, ""),"", 'Normalized Import'!J45+J46) -> #NAME? | L46: =IF(EQ('Normalized Import'!K45, ""), "", 'Normalized Import'!K45+K46) -> #NAME? | M46: =IF(EQ('Normalized Import'!L45, ""),"", 'Normalized Import'!L45+L46) -> #NAME? | N46: =IF(EQ('Normalized Import'!M45, ""), "", 'Normalized Import'!M45+M46) -> #NAME? | O46: =IF(EQ('Normalized Import'!N45, ""),"", 'Normalized Import'!N45+N46) -> #NAME? | P46: =IF(EQ('Normalized Import'!O45, ""), "", 'Normalized Import'!O45+O46) -> #NAME? | Q46: =IF(EQ('Normalized Import'!P45, ""),"", 'Normalized Import'!P45+P46) -> #NAME?
A47: ='Normalized Import'!A46 -> 0 | B47: ='Normalized Import'!B46 -> #VALUE! | C47: ='Normalized Import'!C46 -> 0 | E47: ='Most Recent Import'!E46 -> 0 | F47: ='Normalized Import'!E46 -> #VALUE! | G47: =IF(EQ('Normalized Import'!F46, ""),"", 'Normalized Import'!F46+F47) -> #NAME? | H47: =IF(EQ('Normalized Import'!G46, ""), "", 'Normalized Import'!G46+G47) -> #NAME? | I47: =IF(EQ('Normalized Import'!H46, ""),"", 'Normalized Import'!H46+H47) -> #NAME? | J47: =IF(EQ('Normalized Import'!I46, ""), "", 'Normalized Import'!I46+I47) -> #NAME? | K47: =IF(EQ('Normalized Import'!J46, ""),"", 'Normalized Import'!J46+J47) -> #NAME? | L47: =IF(EQ('Normalized Import'!K46, ""), "", 'Normalized Import'!K46+K47) -> #NAME? | M47: =IF(EQ('Normalized Import'!L46, ""),"", 'Normalized Import'!L46+L47) -> #NAME? | N47: =IF(EQ('Normalized Import'!M46, ""), "", 'Normalized Import'!M46+M47) -> #NAME? | O47: =IF(EQ('Normalized Import'!N46, ""),"", 'Normalized Import'!N46+N47) -> #NAME? | P47: =IF(EQ('Normalized Import'!O46, ""), "", 'Normalized Import'!O46+O47) -> #NAME? | Q47: =IF(EQ('Normalized Import'!P46, ""),"", 'Normalized Import'!P46+P47) -> #NAME?
A48: ='Normalized Import'!A47 -> 0 | B48: ='Normalized Import'!B47 -> #VALUE! | C48: ='Normalized Import'!C47 -> 0 | E48: ='Most Recent Import'!E47 -> 0 | F48: ='Normalized Import'!E47 -> #VALUE! | G48: =IF(EQ('Normalized Import'!F47, ""),"", 'Normalized Import'!F47+F48) -> #NAME? | H48: =IF(EQ('Normalized Import'!G47, ""), "", 'Normalized Import'!G47+G48) -> #NAME? | I48: =IF(EQ('Normalized Import'!H47, ""),"", 'Normalized Import'!H47+H48) -> #NAME? | J48: =IF(EQ('Normalized Import'!I47, ""), "", 'Normalized Import'!I47+I48) -> #NAME? | K48: =IF(EQ('Normalized Import'!J47, ""),"", 'Normalized Import'!J47+J48) -> #NAME? | L48: =IF(EQ('Normalized Import'!K47, ""), "", 'Normalized Import'!K47+K48) -> #NAME? | M48: =IF(EQ('Normalized Import'!L47, ""),"", 'Normalized Import'!L47+L48) -> #NAME? | N48: =IF(EQ('Normalized Import'!M47, ""), "", 'Normalized Import'!M47+M48) -> #NAME? | O48: =IF(EQ('Normalized Import'!N47, ""),"", 'Normalized Import'!N47+N48) -> #NAME? | P48: =IF(EQ('Normalized Import'!O47, ""), "", 'Normalized Import'!O47+O48) -> #NAME? | Q48: =IF(EQ('Normalized Import'!P47, ""),"", 'Normalized Import'!P47+P48) -> #NAME?
A49: ='Normalized Import'!A48 -> 0 | B49: ='Normalized Import'!B48 -> #VALUE! | C49: ='Normalized Import'!C48 -> 0 | E49: ='Most Recent Import'!E48 -> 0 | F49: ='Normalized Import'!E48 -> #VALUE! | G49: =IF(EQ('Normalized Import'!F48, ""),"", 'Normalized Import'!F48+F49) -> #NAME? | H49: =IF(EQ('Normalized Import'!G48, ""), "", 'Normalized Import'!G48+G49) -> #NAME? | I49: =IF(EQ('Normalized Import'!H48, ""),"", 'Normalized Import'!H48+H49) -> #NAME? | J49: =IF(EQ('Normalized Import'!I48, ""), "", 'Normalized Import'!I48+I49) -> #NAME? | K49: =IF(EQ('Normalized Import'!J48, ""),"", 'Normalized Import'!J48+J49) -> #NAME? | L49: =IF(EQ('Normalized Import'!K48, ""), "", 'Normalized Import'!K48+K49) -> #NAME? | M49: =IF(EQ('Normalized Import'!L48, ""),"", 'Normalized Import'!L48+L49) -> #NAME? | N49: =IF(EQ('Normalized Import'!M48, ""), "", 'Normalized Import'!M48+M49) -> #NAME? | O49: =IF(EQ('Normalized Import'!N48, ""),"", 'Normalized Import'!N48+N49) -> #NAME? | P49: =IF(EQ('Normalized Import'!O48, ""), "", 'Normalized Import'!O48+O49) -> #NAME? | Q49: =IF(EQ('Normalized Import'!P48, ""),"", 'Normalized Import'!P48+P49) -> #NAME?
A50: ='Normalized Import'!A49 -> 0 | B50: ='Normalized Import'!B49 -> #VALUE! | C50: ='Normalized Import'!C49 -> 0 | E50: ='Most Recent Import'!E49 -> 0 | F50: ='Normalized Import'!E49 -> #VALUE! | G50: =IF(EQ('Normalized Import'!F49, ""),"", 'Normalized Import'!F49+F50) -> #NAME? | H50: =IF(EQ('Normalized Import'!G49, ""), "", 'Normalized Import'!G49+G50) -> #NAME? | I50: =IF(EQ('Normalized Import'!H49, ""),"", 'Normalized Import'!H49+H50) -> #NAME? | J50: =IF(EQ('Normalized Import'!I49, ""), "", 'Normalized Import'!I49+I50) -> #NAME? | K50: =IF(EQ('Normalized Import'!J49, ""),"", 'Normalized Import'!J49+J50) -> #NAME? | L50: =IF(EQ('Normalized Import'!K49, ""), "", 'Normalized Import'!K49+K50) -> #NAME? | M50: =IF(EQ('Normalized Import'!L49, ""),"", 'Normalized Import'!L49+L50) -> #NAME? | N50: =IF(EQ('Normalized Import'!M49, ""), "", 'Normalized Import'!M49+M50) -> #NAME? | O50: =IF(EQ('Normalized Import'!N49, ""),"", 'Normalized Import'!N49+N50) -> #NAME? | P50: =IF(EQ('Normalized Import'!O49, ""), "", 'Normalized Import'!O49+O50) -> #NAME? | Q50: =IF(EQ('Normalized Import'!P49, ""),"", 'Normalized Import'!P49+P50) -> #NAME?
A51: ='Normalized Import'!A50 -> 0 | B51: ='Normalized Import'!B50 -> #VALUE! | C51: ='Normalized Import'!C50 -> 0 | E51: ='Most Recent Import'!E50 -> 0 | F51: ='Normalized Import'!E50 -> #VALUE! | G51: =IF(EQ('Normalized Import'!F50, ""),"", 'Normalized Import'!F50+F51) -> #NAME? | H51: =IF(EQ('Normalized Import'!G50, ""), "", 'Normalized Import'!G50+G51) -> #NAME? | I51: =IF(EQ('Normalized Import'!H50, ""),"", 'Normalized Import'!H50+H51) -> #NAME? | J51: =IF(EQ('Normalized Import'!I50, ""), "", 'Normalized Import'!I50+I51) -> #NAME? | K51: =IF(EQ('Normalized Import'!J50, ""),"", 'Normalized Import'!J50+J51) -> #NAME? | L51: =IF(EQ('Normalized Import'!K50, ""), "", 'Normalized Import'!K50+K51) -> #NAME? | M51: =IF(EQ('Normalized Import'!L50, ""),"", 'Normalized Import'!L50+L51) -> #NAME? | N51: =IF(EQ('Normalized Import'!M50, ""), "", 'Normalized Import'!M50+M51) -> #NAME? | O51: =IF(EQ('Normalized Import'!N50, ""),"", 'Normalized Import'!N50+N51) -> #NAME? | P51: =IF(EQ('Normalized Import'!O50, ""), "", 'Normalized Import'!O50+O51) -> #NAME? | Q51: =IF(EQ('Normalized Import'!P50, ""),"", 'Normalized Import'!P50+P51) -> #NAME?
A52: ='Normalized Import'!A51 -> 0 | B52: ='Normalized Import'!B51 -> #VALUE! | C52: ='Normalized Import'!C51 -> 0 | E52: ='Most Recent Import'!E51 -> 0 | F52: ='Normalized Import'!E51 -> #VALUE! | G52: =IF(EQ('Normalized Import'!F51, ""),"", 'Normalized Import'!F51+F52) -> #NAME? | H52: =IF(EQ('Normalized Import'!G51, ""), "", 'Normalized Import'!G51+G52) -> #NAME? | I52: =IF(EQ('Normalized Import'!H51, ""),"", 'Normalized Import'!H51+H52) -> #NAME? | J52: =IF(EQ('Normalized Import'!I51, ""), "", 'Normalized Import'!I51+I52) -> #NAME? | K52: =IF(EQ('Normalized Import'!J51, ""),"", 'Normalized Import'!J51+J52) -> #NAME? | L52: =IF(EQ('Normalized Import'!K51, ""), "", 'Normalized Import'!K51+K52) -> #NAME? | M52: =IF(EQ('Normalized Import'!L51, ""),"", 'Normalized Import'!L51+L52) -> #NAME? | N52: =IF(EQ('Normalized Import'!M51, ""), "", 'Normalized Import'!M51+M52) -> #NAME? | O52: =IF(EQ('Normalized Import'!N51, ""),"", 'Normalized Import'!N51+N52) -> #NAME? | P52: =IF(EQ('Normalized Import'!O51, ""), "", 'Normalized Import'!O51+O52) -> #NAME? | Q52: =IF(EQ('Normalized Import'!P51, ""),"", 'Normalized Import'!P51+P52) -> #NAME?
... A100: ='Normalized Import'!A99 -> 0 | B100: ='Normalized Import'!B99 -> #VALUE! | C100: ='Normalized Import'!C99 -> 0 | E100: ='Most Recent Import'!E99 -> 0 | F100: ='Normalized Import'!E99 -> #VALUE! | G100: =IF(EQ('Normalized Import'!F99, ""),"", 'Normalized Import'!F99+F100) -> #NAME? | H100: =IF(EQ('Normalized Import'!G99, ""), "", 'Normalized Import'!G99+G100) -> #NAME? | I100: =IF(EQ('Normalized Import'!H99, ""),"", 'Normalized Import'!H99+H100) -> #NAME? | J100: =IF(EQ('Normalized Import'!I99, ""), "", 'Normalized Import'!I99+I100) -> #NAME? | K100: =IF(EQ('Normalized Import'!J99, ""),"", 'Normalized Import'!J99+J100) -> #NAME? | L100: =IF(EQ('Normalized Import'!K99, ""), "", 'Normalized Import'!K99+K100) -> #NAME? | M100: =IF(EQ('Normalized Import'!L99, ""),"", 'Normalized Import'!L99+L100) -> #NAME? | N100: =IF(EQ('Normalized Import'!M99, ""), "", 'Normalized Import'!M99+M100) -> #NAME? | O100: =IF(EQ('Normalized Import'!N99, ""),"", 'Normalized Import'!N99+N100) -> #NAME? | P100: =IF(EQ('Normalized Import'!O99, ""), "", 'Normalized Import'!O99+O100) -> #NAME? | Q100: =IF(EQ('Normalized Import'!P99, ""),"", 'Normalized Import'!P99+P100) -> #NAME?

Sheet Normalized Import
A1: slug | B1: Close Date | C1: ARR | D1: # of Seats | E1: Month 1 | F1: Month 2 | G1: Month 3 | H1: Month 4 | I1: Month 5 | J1: Month 6 | K1: Month 7 | L1: Month 8 | M1: Month 9 | N1: Month 10 | O1: Month 11 | P1: Month 12
A2: ='Most Recent Import'!A2 -> safe | B2: =IF(ISBLANK(A2), "", DATE(LEFT('Most Recent Import'!C2, 4), RIGHT('Most Recent Import'!C2, 2), 1)) -> 44958 | C2: ='Most Recent Import'!B2 -> 1000 | D2: ='Most Recent Import'!D2 -> 10 | E2: {=IF( DATEDIF($B2, TODAY(), "M") >= 11, INDEX('Most Recent Import'!$F2:$Q2, 1, MATCH(11 - (COLUMN(E:E) - 5), {0,1,2,3,4,5,6,7,8,9,10,11}, 0)), IF( DATEDIF($B2, TODAY(), "M") + 1 >= COLUMN(E:E) - 5, INDEX('Most Recent Import'!$F2:$Q2, 1, MATCH(DATEDIF($B2, TODAY(), "M") + 1 - (COLUMN(E:E) - 5), {0,1,2,3,4,5,6,7,8,9,10,11}, 0)), "" ) )} -> 0 | F2: {=IF( DATEDIF($B2, TODAY(), "M") >= 11, INDEX('Most Recent Import'!$F2:$Q2, 1, MATCH(11 - (COLUMN(F:F) - 5), {0,1,2,3,4,5,6,7,8,9,10,11}, 0)), IF( DATEDIF($B2, TODAY(), "M") + 1 >= COLUMN(F:F) - 5, INDEX('Most Recent Import'!$F2:$Q2, 1, MATCH(DATEDIF($B2, TODAY(), "M") + 1 - (COLUMN(F:F) - 5), {0,1,2,3,4,5,6,7,8,9,10,11}, 0)), "" ) )} -> 2 | G2: {=IF( DATEDIF($B2, TODAY(), "M") >= 11, INDEX('Most Recent Import'!$F2:$Q2, 1, MATCH(11 - (COLUMN(G:G) - 5), {0,1,2,3,4,5,6,7,8,9,10,11}, 0)), IF( DATEDIF($B2, TODAY(), "M") + 1 >= COLUMN(G:G) - 5, INDEX('Most Recent Import'!$F2:$Q2, 1, MATCH(DATEDIF($B2, TODAY(), "M") + 1 - (COLUMN(G:G) - 5), {0,1,2,3,4,5,6,7,8,9,10,11}, 0)), "" ) )} -> 0 | H2: {=IF( DATEDIF($B2, TODAY(), "M") >= 11, INDEX('Most Recent Import'!$F2:$Q2, 1, MATCH(11 - (COLUMN(H:H) - 5), {0,1,2,3,4,5,6,7,8,9,10,11}, 0)), IF( DATEDIF($B2, TODAY(), "M") + 1 >= COLUMN(H:H) - 5, INDEX('Most Recent Import'!$F2:$Q2, 1, MATCH(DATEDIF($B2, TODAY(), "M") + 1 - (COLUMN(H:H) - 5), {0,1,2,3,4,5,6,7,8,9,10,11}, 0)), "" ) )} -> 1 | I2: {=IF( DATEDIF($B2, TODAY(), "M") >= 11, INDEX('Most Recent Import'!$F2:$Q2, 1, MATCH(11 - (COLUMN(I:I) - 5), {0,1,2,3,4,5,6,7,8,9,10,11}, 0)), IF( DATEDIF($B2, TODAY(), "M") + 1 >= COLUMN(I:I) - 5, INDEX('Most Recent Import'!$F2:$Q2, 1, MATCH(DATEDIF($B2, TODAY(), "M") + 1 - (COLUMN(I:I) - 5), {0,1,2,3,4,5,6,7,8,9,10,11}, 0)), "" ) )} -> 2 | J2: {=IF( DATEDIF($B2, TODAY(), "M") >= 11, INDEX('Most Recent Import'!$F2:$Q2, 1, MATCH(11 - (COLUMN(J:J) - 5), {0,1,2,3,4,5,6,7,8,9,10,11}, 0)), IF( DATEDIF($B2, TODAY(), "M") + 1 >= COLUMN(J:J) - 5, INDEX('Most Recent Import'!$F2:$Q2, 1, MATCH(DATEDIF($B2, TODAY(), "M") + 1 - (COLUMN(J:J) - 5), {0,1,2,3,4,5,6,7,8,9,10,11}, 0)), "" ) )} -> 1 | K2: {=IF( DATEDIF($B2, TODAY(), "M") >= 11, INDEX('Most Recent Import'!$F2:$Q2, 1, MATCH(11 - (COLUMN(K:K) - 5), {0,1,2,3,4,5,6,7,8,9,10,11}, 0)), IF( DATEDIF($B2, TODAY(), "M") + 1 >= COLUMN(K:K) - 5, INDEX('Most Recent Import'!$F2:$Q2, 1, MATCH(DATEDIF($B2, TODAY(), "M") + 1 - (COLUMN(K:K) - 5), {0,1,2,3,4,5,6,7,8,9,10,11}, 0)), "" ) )} -> 0 | L2: {=IF( DATEDIF($B2, TODAY(), "M") >= 11, INDEX('Most Recent Import'!$F2:$Q2, 1, MATCH(11 - (COLUMN(L:L) - 5), {0,1,2,3,4,5,6,7,8,9,10,11}, 0)), IF( DATEDIF($B2, TODAY(), "M") + 1 >= COLUMN(L:L) - 5, INDEX('Most Recent Import'!$F2:$Q2, 1, MATCH(DATEDIF($B2, TODAY(), "M") + 1 - (COLUMN(L:L) - 5), {0,1,2,3,4,5,6,7,8,9,10,11}, 0)), "" ) )} -> 1 | M2: {=IF( DATEDIF($B2, TODAY(), "M") >= 11, INDEX('Most Recent Import'!$F2:$Q2, 1, MATCH(11 - (COLUMN(M:M) - 5), {0,1,2,3,4,5,6,7,8,9,10,11}, 0)), IF( DATEDIF($B2, TODAY(), "M") + 1 >= COLUMN(M:M) - 5, INDEX('Most Recent Import'!$F2:$Q2, 1, MATCH(DATEDIF($B2, TODAY(), "M") + 1 - (COLUMN(M:M) - 5), {0,1,2,3,4,5,6,7,8,9,10,11}, 0)), "" ) )} -> 1 | N2: {=IF( DATEDIF($B2, TODAY(), "M") >= 11, INDEX('Most Recent Import'!$F2:$Q2, 1, MATCH(11 - (COLUMN(N:N) - 5), {0,1,2,3,4,5,6,7,8,9,10,11}, 0)), IF( DATEDIF($B2, TODAY(), "M") + 1 >= COLUMN(N:N) - 5, INDEX('Most Recent Import'!$F2:$Q2, 1, MATCH(DATEDIF($B2, TODAY(), "M") + 1 - (COLUMN(N:N) - 5), {0,1,2,3,4,5,6,7,8,9,10,11}, 0)), "" ) )} -> 3 | O2: {=IF( DATEDIF($B2, TODAY(), "M") >= 11, INDEX('Most Recent Import'!$F2:$Q2, 1, MATCH(11 - (COLUMN(O:O) - 5), {0,1,2,3,4,5,6,7,8,9,10,11}, 0)), IF( DATEDIF($B2, TODAY(), "M") + 1 >= COLUMN(O:O) - 5, INDEX('Most Recent Import'!$F2:$Q2, 1, MATCH(DATEDIF($B2, TODAY(), "M") + 1 - (COLUMN(O:O) - 5), {0,1,2,3,4,5,6,7,8,9,10,11}, 0)), "" ) )} -> 0 | P2: {=IF( DATEDIF($B2, TODAY(), "M") >= 11, INDEX('Most Recent Import'!$F2:$Q2, 1, MATCH(11 - (COLUMN(P:P) - 5), {0,1,2,3,4,5,6,7,8,9,10,11}, 0)), IF( DATEDIF($B2, TODAY(), "M") + 1 >= COLUMN(P:P) - 5, INDEX('Most Recent Import'!$F2:$Q2, 1, MATCH(DATEDIF($B2, TODAY(), "M") + 1 - (COLUMN(P:P) - 5), {0,1,2,3,4,5,6,7,8,9,10,11}, 0)), "" ) )} -> 1
A3: ='Most Recent Import'!A3 -> 8x8 | B3: =IF(ISBLANK(A3), "", DATE(LEFT('Most Recent Import'!C3, 4), RIGHT('Most Recent Import'!C3, 2), 1)) -> 45047 | C3: ='Most Recent Import'!B3 -> 15000 | D3: ='Most Recent Import'!D3 -> 9 | E3: {=IF( DATEDIF($B3, TODAY(), "M") >= 11, INDEX('Most Recent Import'!$F3:$Q3, 1, MATCH(11 - (COLUMN(E:E) - 5), {0,1,2,3,4,5,6,7,8,9,10,11}, 0)), IF( DATEDIF($B3, TODAY(), "M") + 1 >= COLUMN(E:E) - 5, INDEX('Most Recent Import'!$F3:$Q3, 1, MATCH(DATEDIF($B3, TODAY(), "M") + 1 - (COLUMN(E:E) - 5), {0,1,2,3,4,5,6,7,8,9,10,11}, 0)), "" ) )} -> 0 | F3: {=IF( DATEDIF($B3, TODAY(), "M") >= 11, INDEX('Most Recent Import'!$F3:$Q3, 1, MATCH(11 - (COLUMN(F:F) - 5), {0,1,2,3,4,5,6,7,8,9,10,11}, 0)), IF( DATEDIF($B3, TODAY(), "M") + 1 >= COLUMN(F:F) - 5, INDEX('Most Recent Import'!$F3:$Q3, 1, MATCH(DATEDIF($B3, TODAY(), "M") + 1 - (COLUMN(F:F) - 5), {0,1,2,3,4,5,6,7,8,9,10,11}, 0)), "" ) )} -> 0 | G3: {=IF( DATEDIF($B3, TODAY(), "M") >= 11, INDEX('Most Recent Import'!$F3:$Q3, 1, MATCH(11 - (COLUMN(G:G) - 5), {0,1,2,3,4,5,6,7,8,9,10,11}, 0)), IF( DATEDIF($B3, TODAY(), "M") + 1 >= COLUMN(G:G) - 5, INDEX('Most Recent Import'!$F3:$Q3, 1, MATCH(DATEDIF($B3, TODAY(), "M") + 1 - (COLUMN(G:G) - 5), {0,1,2,3,4,5,6,7,8,9,10,11}, 0)), "" ) )} -> 3 | H3: {=IF( DATEDIF($B3, TODAY(), "M") >= 11, INDEX('Most Recent Import'!$F3:$Q3, 1, MATCH(11 - (COLUMN(H:H) - 5), {0,1,2,3,4,5,6,7,8,9,10,11}, 0)), IF( DATEDIF($B3, TODAY(), "M") + 1 >= COLUMN(H:H) - 5, INDEX('Most Recent Import'!$F3:$Q3, 1, MATCH(DATEDIF($B3, TODAY(), "M") + 1 - (COLUMN(H:H) - 5), {0,1,2,3,4,5,6,7,8,9,10,11}, 0)), "" ) )} -> 1 | I3: {=IF( DATEDIF($B3, TODAY(), "M") >= 11, INDEX('Most Recent Import'!$F3:$Q3, 1, MATCH(11 - (COLUMN(I:I) - 5), {0,1,2,3,4,5,6,7,8,9,10,11}, 0)), IF( DATEDIF($B3, TODAY(), "M") + 1 >= COLUMN(I:I) - 5, INDEX('Most Recent Import'!$F3:$Q3, 1, MATCH(DATEDIF($B3, TODAY(), "M") + 1 - (COLUMN(I:I) - 5), {0,1,2,3,4,5,6,7,8,9,10,11}, 0)), "" ) )} -> 4 | J3: {=IF( DATEDIF($B3, TODAY(), "M") >= 11, INDEX('Most Recent Import'!$F3:$Q3, 1, MATCH(11 - (COLUMN(J:J) - 5), {0,1,2,3,4,5,6,7,8,9,10,11}, 0)), IF( DATEDIF($B3, TODAY(), "M") + 1 >= COLUMN(J:J) - 5, INDEX('Most Recent Import'!$F3:$Q3, 1, MATCH(DATEDIF($B3, TODAY(), "M") + 1 - (COLUMN(J:J) - 5), {0,1,2,3,4,5,6,7,8,9,10,11}, 0)), "" ) )} -> 4 | K3: {=IF( DATEDIF($B3, TODAY(), "M") >= 11, INDEX('Most Recent Import'!$F3:$Q3, 1, MATCH(11 - (COLUMN(K:K) - 5), {0,1,2,3,4,5,6,7,8,9,10,11}, 0)), IF( DATEDIF($B3, TODAY(), "M") + 1 >= COLUMN(K:K) - 5, INDEX('Most Recent Import'!$F3:$Q3, 1, MATCH(DATEDIF($B3, TODAY(), "M") + 1 - (COLUMN(K:K) - 5), {0,1,2,3,4,5,6,7,8,9,10,11}, 0)), "" ) )} -> 7 | L3: {=IF( DATEDIF($B3, TODAY(), "M") >= 11, INDEX('Most Recent Import'!$F3:$Q3, 1, MATCH(11 - (COLUMN(L:L) - 5), {0,1,2,3,4,5,6,7,8,9,10,11}, 0)), IF( DATEDIF($B3, TODAY(), "M") + 1 >= COLUMN(L:L) - 5, INDEX('Most Recent Import'!$F3:$Q3, 1, MATCH(DATEDIF($B3, TODAY(), "M") + 1 - (COLUMN(L:L) - 5), {0,1,2,3,4,5,6,7,8,9,10,11}, 0)), "" ) )} -> 4 | M3: {=IF( DATEDIF($B3, TODAY(), "M") >= 11, INDEX('Most Recent Import'!$F3:$Q3, 1, MATCH(11 - (COLUMN(M:M) - 5), {0,1,2,3,4,5,6,7,8,9,10,11}, 0)), IF( DATEDIF($B3, TODAY(), "M") + 1 >= COLUMN(M:M) - 5, INDEX('Most Recent Import'!$F3:$Q3, 1, MATCH(DATEDIF($B3, TODAY(), "M") + 1 - (COLUMN(M:M) - 5), {0,1,2,3,4,5,6,7,8,9,10,11}, 0)), "" ) )} -> 0 | N3: {=IF( DATEDIF($B3, TODAY(), "M") >= 11, INDEX('Most Recent Import'!$F3:$Q3, 1, MATCH(11 - (COLUMN(N:N) - 5), {0,1,2,3,4,5,6,7,8,9,10,11}, 0)), IF( DATEDIF($B3, TODAY(), "M") + 1 >= COLUMN(N:N) - 5, INDEX('Most Recent Import'!$F3:$Q3, 1, MATCH(DATEDIF($B3, TODAY(), "M") + 1 - (COLUMN(N:N) - 5), {0,1,2,3,4,5,6,7,8,9,10,11}, 0)), "" ) )} -> 2 | O3: {=IF( DATEDIF($B3, TODAY(), "M") >= 11, INDEX('Most Recent Import'!$F3:$Q3, 1, MATCH(11 - (COLUMN(O:O) - 5), {0,1,2,3,4,5,6,7,8,9,10,11}, 0)), IF( DATEDIF($B3, TODAY(), "M") + 1 >= COLUMN(O:O) - 5, INDEX('Most Recent Import'!$F3:$Q3, 1, MATCH(DATEDIF($B3, TODAY(), "M") + 1 - (COLUMN(O:O) - 5), {0,1,2,3,4,5,6,7,8,9,10,11}, 0)), "" ) )} -> 2 | P3: {=IF( DATEDIF($B3, TODAY(), "M") >= 11, INDEX('Most Recent Import'!$F3:$Q3, 1, MATCH(11 - (COLUMN(P:P) - 5), {0,1,2,3,4,5,6,7,8,9,10,11}, 0)), IF( DATEDIF($B3, TODAY(), "M") + 1 >= COLUMN(P:P) - 5, INDEX('Most Recent Import'!$F3:$Q3, 1, MATCH(DATEDIF($B3, TODAY(), "M") + 1 - (COLUMN(P:P) - 5), {0,1,2,3,4,5,6,7,8,9,10,11}, 0)), "" ) )} -> 3
A4: ='Most Recent Import'!A4 -> convera | B4: =IF(ISBLANK(A4), "", DATE(LEFT('Most Recent Import'!C4, 4), RIGHT('Most Recent Import'!C4, 2), 1)) -> 45047 | C4: ='Most Recent Import'!B4 -> 5000 | D4: ='Most Recent Import'!D4 -> 5 | E4: {=IF( DATEDIF($B4, TODAY(), "M") >= 11, INDEX('Most Recent Import'!$F4:$Q4, 1, MATCH(11 - (COLUMN(E:E) - 5), {0,1,2,3,4,5,6,7,8,9,10,11}, 0)), IF( DATEDIF($B4, TODAY(), "M") + 1 >= COLUMN(E:E) - 5, INDEX('Most Recent Import'!$F4:$Q4, 1, MATCH(DATEDIF($B4, TODAY(), "M") + 1 - (COLUMN(E:E) - 5), {0,1,2,3,4,5,6,7,8,9,10,11}, 0)), "" ) )} -> 0 | F4: {=IF( DATEDIF($B4, TODAY(), "M") >= 11, INDEX('Most Recent Import'!$F4:$Q4, 1, MATCH(11 - (COLUMN(F:F) - 5), {0,1,2,3,4,5,6,7,8,9,10,11}, 0)), IF( DATEDIF($B4, TODAY(), "M") + 1 >= COLUMN(F:F) - 5, INDEX('Most Recent Import'!$F4:$Q4, 1, MATCH(DATEDIF($B4, TODAY(), "M") + 1 - (COLUMN(F:F) - 5), {0,1,2,3,4,5,6,7,8,9,10,11}, 0)), "" ) )} -> 0 | G4: {=IF( DATEDIF($B4, TODAY(), "M") >= 11, INDEX('Most Recent Import'!$F4:$Q4, 1, MATCH(11 - (COLUMN(G:G) - 5), {0,1,2,3,4,5,6,7,8,9,10,11}, 0)), IF( DATEDIF($B4, TODAY(), "M") + 1 >= COLUMN(G:G) - 5, INDEX('Most Recent Import'!$F4:$Q4, 1, MATCH(DATEDIF($B4, TODAY(), "M") + 1 - (COLUMN(G:G) - 5), {0,1,2,3,4,5,6,7,8,9,10,11}, 0)), "" ) )} -> 0 | H4: {=IF( DATEDIF($B4, TODAY(), "M") >= 11, INDEX('Most Recent Import'!$F4:$Q4, 1, MATCH(11 - (COLUMN(H:H) - 5), {0,1,2,3,4,5,6,7,8,9,10,11}, 0)), IF( DATEDIF($B4, TODAY(), "M") + 1 >= COLUMN(H:H) - 5, INDEX('Most Recent Import'!$F4:$Q4, 1, MATCH(DATEDIF($B4, TODAY(), "M") + 1 - (COLUMN(H:H) - 5), {0,1,2,3,4,5,6,7,8,9,10,11}, 0)), "" ) )} -> 0 | I4: {=IF( DATEDIF($B4, TODAY(), "M") >= 11, INDEX('Most Recent Import'!$F4:$Q4, 1, MATCH(11 - (COLUMN(I:I) - 5), {0,1,2,3,4,5,6,7,8,9,10,11}, 0)), IF( DATEDIF($B4, TODAY(), "M") + 1 >= COLUMN(I:I) - 5, INDEX('Most Recent Import'!$F4:$Q4, 1, MATCH(DATEDIF($B4, TODAY(), "M") + 1 - (COLUMN(I:I) - 5), {0,1,2,3,4,5,6,7,8,9,10,11}, 0)), "" ) )} -> 0 | J4: {=IF( DATEDIF($B4, TODAY(), "M") >= 11, INDEX('Most Recent Import'!$F4:$Q4, 1, MATCH(11 - (COLUMN(J:J) - 5), {0,1,2,3,4,5,6,7,8,9,10,11}, 0)), IF( DATEDIF($B4, TODAY(), "M") + 1 >= COLUMN(J:J) - 5, INDEX('Most Recent Import'!$F4:$Q4, 1, MATCH(DATEDIF($B4, TODAY(), "M") + 1 - (COLUMN(J:J) - 5), {0,1,2,3,4,5,6,7,8,9,10,11}, 0)), "" ) )} -> 1 | K4: {=IF( DATEDIF($B4, TODAY(), "M") >= 11, INDEX('Most Recent Import'!$F4:$Q4, 1, MATCH(11 - (COLUMN(K:K) - 5), {0,1,2,3,4,5,6,7,8,9,10,11}, 0)), IF( DATEDIF($B4, TODAY(), "M") + 1 >= COLUMN(K:K) - 5, INDEX('Most Recent Import'!$F4:$Q4, 1, MATCH(DATEDIF($B4, TODAY(), "M") + 1 - (COLUMN(K:K) - 5), {0,1,2,3,4,5,6,7,8,9,10,11}, 0)), "" ) )} -> 0 | L4: {=IF( DATEDIF($B4, TODAY(), "M") >= 11, INDEX('Most Recent Import'!$F4:$Q4, 1, MATCH(11 - (COLUMN(L:L) - 5), {0,1,2,3,4,5,6,7,8,9,10,11}, 0)), IF( DATEDIF($B4, TODAY(), "M") + 1 >= COLUMN(L:L) - 5, INDEX('Most Recent Import'!$F4:$Q4, 1, MATCH(DATEDIF($B4, TODAY(), "M") + 1 - (COLUMN(L:L) - 5), {0,1,2,3,4,5,6,7,8,9,10,11}, 0)), "" ) )} -> 0 | M4: {=IF( DATEDIF($B4, TODAY(), "M") >= 11, INDEX('Most Recent Import'!$F4:$Q4, 1, MATCH(11 - (COLUMN(M:M) - 5), {0,1,2,3,4,5,6,7,8,9,10,11}, 0)), IF( DATEDIF($B4, TODAY(), "M") + 1 >= COLUMN(M:M) - 5, INDEX('Most Recent Import'!$F4:$Q4, 1, MATCH(DATEDIF($B4, TODAY(), "M") + 1 - (COLUMN(M:M) - 5), {0,1,2,3,4,5,6,7,8,9,10,11}, 0)), "" ) )} -> 0 | N4: {=IF( DATEDIF($B4, TODAY(), "M") >= 11, INDEX('Most Recent Import'!$F4:$Q4, 1, MATCH(11 - (COLUMN(N:N) - 5), {0,1,2,3,4,5,6,7,8,9,10,11}, 0)), IF( DATEDIF($B4, TODAY(), "M") + 1 >= COLUMN(N:N) - 5, INDEX('Most Recent Import'!$F4:$Q4, 1, MATCH(DATEDIF($B4, TODAY(), "M") + 1 - (COLUMN(N:N) - 5), {0,1,2,3,4,5,6,7,8,9,10,11}, 0)), "" ) )} -> 0 | O4: {=IF( DATEDIF($B4, TODAY(), "M") >= 11, INDEX('Most Recent Import'!$F4:$Q4, 1, MATCH(11 - (COLUMN(O:O) - 5), {0,1,2,3,4,5,6,7,8,9,10,11}, 0)), IF( DATEDIF($B4, TODAY(), "M") + 1 >= COLUMN(O:O) - 5, INDEX('Most Recent Import'!$F4:$Q4, 1, MATCH(DATEDIF($B4, TODAY(), "M") + 1 - (COLUMN(O:O) - 5), {0,1,2,3,4,5,6,7,8,9,10,11}, 0)), "" ) )} -> 0 | P4: {=IF( DATEDIF($B4, TODAY(), "M") >= 11, INDEX('Most Recent Import'!$F4:$Q4, 1, MATCH(11 - (COLUMN(P:P) - 5), {0,1,2,3,4,5,6,7,8,9,10,11}, 0)), IF( DATEDIF($B4, TODAY(), "M") + 1 >= COLUMN(P:P) - 5, INDEX('Most Recent Import'!$F4:$Q4, 1, MATCH(DATEDIF($B4, TODAY(), "M") + 1 - (COLUMN(P:P) - 5), {0,1,2,3,4,5,6,7,8,9,10,11}, 0)), "" ) )} -> 1
A5: ='Most Recent Import'!A5 -> glovo | B5: =IF(ISBLANK(A5), "", DATE(LEFT('Most Recent Import'!C5, 4), RIGHT('Most Recent Import'!C5, 2), 1)) -> 45047 | C5: ='Most Recent Import'!B5 -> 30000 | D5: ='Most Recent Import'!D5 -> 5 | E5: {=IF( DATEDIF($B5, TODAY(), "M") >= 11, INDEX('Most Recent Import'!$F5:$Q5, 1, MATCH(11 - (COLUMN(E:E) - 5), {0,1,2,3,4,5,6,7,8,9,10,11}, 0)), IF( DATEDIF($B5, TODAY(), "M") + 1 >= COLUMN(E:E) - 5, INDEX('Most Recent Import'!$F5:$Q5, 1, MATCH(DATEDIF($B5, TODAY(), "M") + 1 - (COLUMN(E:E) - 5), {0,1,2,3,4,5,6,7,8,9,10,11}, 0)), "" ) )} -> 0 | F5: {=IF( DATEDIF($B5, TODAY(), "M") >= 11, INDEX('Most Recent Import'!$F5:$Q5, 1, MATCH(11 - (COLUMN(F:F) - 5), {0,1,2,3,4,5,6,7,8,9,10,11}, 0)), IF( DATEDIF($B5, TODAY(), "M") + 1 >= COLUMN(F:F) - 5, INDEX('Most Recent Import'!$F5:$Q5, 1, MATCH(DATEDIF($B5, TODAY(), "M") + 1 - (COLUMN(F:F) - 5), {0,1,2,3,4,5,6,7,8,9,10,11}, 0)), "" ) )} -> 1 | G5: {=IF( DATEDIF($B5, TODAY(), "M") >= 11, INDEX('Most Recent Import'!$F5:$Q5, 1, MATCH(11 - (COLUMN(G:G) - 5), {0,1,2,3,4,5,6,7,8,9,10,11}, 0)), IF( DATEDIF($B5, TODAY(), "M") + 1 >= COLUMN(G:G) - 5, INDEX('Most Recent Import'!$F5:$Q5, 1, MATCH(DATEDIF($B5, TODAY(), "M") + 1 - (COLUMN(G:G) - 5), {0,1,2,3,4,5,6,7,8,9,10,11}, 0)), "" ) )} -> 6 | H5: {=IF( DATEDIF($B5, TODAY(), "M") >= 11, INDEX('Most Recent Import'!$F5:$Q5, 1, MATCH(11 - (COLUMN(H:H) - 5), {0,1,2,3,4,5,6,7,8,9,10,11}, 0)), IF( DATEDIF($B5, TODAY(), "M") + 1 >= COLUMN(H:H) - 5, INDEX('Most Recent Import'!$F5:$Q5, 1, MATCH(DATEDIF($B5, TODAY(), "M") + 1 - (COLUMN(H:H) - 5), {0,1,2,3,4,5,6,7,8,9,10,11}, 0)), "" ) )} -> 29 | I5: {=IF( DATEDIF($B5, TODAY(), "M") >= 11, INDEX('Most Recent Import'!$F5:$Q5, 1, MATCH(11 - (COLUMN(I:I) - 5), {0,1,2,3,4,5,6,7,8,9,10,11}, 0)), IF( DATEDIF($B5, TODAY(), "M") + 1 >= COLUMN(I:I) - 5, INDEX('Most Recent Import'!$F5:$Q5, 1, MATCH(DATEDIF($B5, TODAY(), "M") + 1 - (COLUMN(I:I) - 5), {0,1,2,3,4,5,6,7,8,9,10,11}, 0)), "" ) )} -> 15 | J5: {=IF( DATEDIF($B5, TODAY(), "M") >= 11, INDEX('Most Recent Import'!$F5:$Q5, 1, MATCH(11 - (COLUMN(J:J) - 5), {0,1,2,3,4,5,6,7,8,9,10,11}, 0)), IF( DATEDIF($B5, TODAY(), "M") + 1 >= COLUMN(J:J) - 5, INDEX('Most Recent Import'!$F5:$Q5, 1, MATCH(DATEDIF($B5, TODAY(), "M") + 1 - (COLUMN(J:J) - 5), {0,1,2,3,4,5,6,7,8,9,10,11}, 0)), "" ) )} -> 11 | K5: {=IF( DATEDIF($B5, TODAY(), "M") >= 11, INDEX('Most Recent Import'!$F5:$Q5, 1, MATCH(11 - (COLUMN(K:K) - 5), {0,1,2,3,4,5,6,7,8,9,10,11}, 0)), IF( DATEDIF($B5, TODAY(), "M") + 1 >= COLUMN(K:K) - 5, INDEX('Most Recent Import'!$F5:$Q5, 1, MATCH(DATEDIF($B5, TODAY(), "M") + 1 - (COLUMN(K:K) - 5), {0,1,2,3,4,5,6,7,8,9,10,11}, 0)), "" ) )} -> 8 | L5: {=IF( DATEDIF($B5, TODAY(), "M") >= 11, INDEX('Most Recent Import'!$F5:$Q5, 1, MATCH(11 - (COLUMN(L:L) - 5), {0,1,2,3,4,5,6,7,8,9,10,11}, 0)), IF( DATEDIF($B5, TODAY(), "M") + 1 >= COLUMN(L:L) - 5, INDEX('Most Recent Import'!$F5:$Q5, 1, MATCH(DATEDIF($B5, TODAY(), "M") + 1 - (COLUMN(L:L) - 5), {0,1,2,3,4,5,6,7,8,9,10,11}, 0)), "" ) )} -> 24 | M5: {=IF( DATEDIF($B5, TODAY(), "M") >= 11, INDEX('Most Recent Import'!$F5:$Q5, 1, MATCH(11 - (COLUMN(M:M) - 5), {0,1,2,3,4,5,6,7,8,9,10,11}, 0)), IF( DATEDIF($B5, TODAY(), "M") + 1 >= COLUMN(M:M) - 5, INDEX('Most Recent Import'!$F5:$Q5, 1, MATCH(DATEDIF($B5, TODAY(), "M") + 1 - (COLUMN(M:M) - 5), {0,1,2,3,4,5,6,7,8,9,10,11}, 0)), "" ) )} -> 8 | N5: {=IF( DATEDIF($B5, TODAY(), "M") >= 11, INDEX('Most Recent Import'!$F5:$Q5, 1, MATCH(11 - (COLUMN(N:N) - 5), {0,1,2,3,4,5,6,7,8,9,10,11}, 0)), IF( DATEDIF($B5, TODAY(), "M") + 1 >= COLUMN(N:N) - 5, INDEX('Most Recent Import'!$F5:$Q5, 1, MATCH(DATEDIF($B5, TODAY(), "M") + 1 - (COLUMN(N:N) - 5), {0,1,2,3,4,5,6,7,8,9,10,11}, 0)), "" ) )} -> 15 | O5: {=IF( DATEDIF($B5, TODAY(), "M") >= 11, INDEX('Most Recent Import'!$F5:$Q5, 1, MATCH(11 - (COLUMN(O:O) - 5), {0,1,2,3,4,5,6,7,8,9,10,11}, 0)), IF( DATEDIF($B5, TODAY(), "M") + 1 >= COLUMN(O:O) - 5, INDEX('Most Recent Import'!$F5:$Q5, 1, MATCH(DATEDIF($B5, TODAY(), "M") + 1 - (COLUMN(O:O) - 5), {0,1,2,3,4,5,6,7,8,9,10,11}, 0)), "" ) )} -> 21 | P5: {=IF( DATEDIF($B5, TODAY(), "M") >= 11, INDEX('Most Recent Import'!$F5:$Q5, 1, MATCH(11 - (COLUMN(P:P) - 5), {0,1,2,3,4,5,6,7,8,9,10,11}, 0)), IF( DATEDIF($B5, TODAY(), "M") + 1 >= COLUMN(P:P) - 5, INDEX('Most Recent Import'!$F5:$Q5, 1, MATCH(DATEDIF($B5, TODAY(), "M") + 1 - (COLUMN(P:P) - 5), {0,1,2,3,4,5,6,7,8,9,10,11}, 0)), "" ) )} -> 9
A6: ='Most Recent Import'!A6 -> webflow | B6: =IF(ISBLANK(A6), "", DATE(LEFT('Most Recent Import'!C6, 4), RIGHT('Most Recent Import'!C6, 2), 1)) -> 45047 | C6: ='Most Recent Import'!B6 -> 20000 | D6: ='Most Recent Import'!D6 -> 10 | E6: {=IF( DATEDIF($B6, TODAY(), "M") >= 11, INDEX('Most Recent Import'!$F6:$Q6, 1, MATCH(11 - (COLUMN(E:E) - 5), {0,1,2,3,4,5,6,7,8,9,10,11}, 0)), IF( DATEDIF($B6, TODAY(), "M") + 1 >= COLUMN(E:E) - 5, INDEX('Most Recent Import'!$F6:$Q6, 1, MATCH(DATEDIF($B6, TODAY(), "M") + 1 - (COLUMN(E:E) - 5), {0,1,2,3,4,5,6,7,8,9,10,11}, 0)), "" ) )} -> 0 | F6: {=IF( DATEDIF($B6, TODAY(), "M") >= 11, INDEX('Most Recent Import'!$F6:$Q6, 1, MATCH(11 - (COLUMN(F:F) - 5), {0,1,2,3,4,5,6,7,8,9,10,11}, 0)), IF( DATEDIF($B6, TODAY(), "M") + 1 >= COLUMN(F:F) - 5, INDEX('Most Recent Import'!$F6:$Q6, 1, MATCH(DATEDIF($B6, TODAY(), "M") + 1 - (COLUMN(F:F) - 5), {0,1,2,3,4,5,6,7,8,9,10,11}, 0)), "" ) )} -> 1 | G6: {=IF( DATEDIF($B6, TODAY(), "M") >= 11, INDEX('Most Recent Import'!$F6:$Q6, 1, MATCH(11 - (COLUMN(G:G) - 5), {0,1,2,3,4,5,6,7,8,9,10,11}, 0)), IF( DATEDIF($B6, TODAY(), "M") + 1 >= COLUMN(G:G) - 5, INDEX('Most Recent Import'!$F6:$Q6, 1, MATCH(DATEDIF($B6, TODAY(), "M") + 1 - (COLUMN(G:G) - 5), {0,1,2,3,4,5,6,7,8,9,10,11}, 0)), "" ) )} -> 6 | H6: {=IF( DATEDIF($B6, TODAY(), "M") >= 11, INDEX('Most Recent Import'!$F6:$Q6, 1, MATCH(11 - (COLUMN(H:H) - 5), {0,1,2,3,4,5,6,7,8,9,10,11}, 0)), IF( DATEDIF($B6, TODAY(), "M") + 1 >= COLUMN(H:H) - 5, INDEX('Most Recent Import'!$F6:$Q6, 1, MATCH(DATEDIF($B6, TODAY(), "M") + 1 - (COLUMN(H:H) - 5), {0,1,2,3,4,5,6,7,8,9,10,11}, 0)), "" ) )} -> 7 | I6: {=IF( DATEDIF($B6, TODAY(), "M") >= 11, INDEX('Most Recent Import'!$F6:$Q6, 1, MATCH(11 - (COLUMN(I:I) - 5), {0,1,2,3,4,5,6,7,8,9,10,11}, 0)), IF( DATEDIF($B6, TODAY(), "M") + 1 >= COLUMN(I:I) - 5, INDEX('Most Recent Import'!$F6:$Q6, 1, MATCH(DATEDIF($B6, TODAY(), "M") + 1 - (COLUMN(I:I) - 5), {0,1,2,3,4,5,6,7,8,9,10,11}, 0)), "" ) )} -> 9 | J6: {=IF( DATEDIF($B6, TODAY(), "M") >= 11, INDEX('Most Recent Import'!$F6:$Q6, 1, MATCH(11 - (COLUMN(J:J) - 5), {0,1,2,3,4,5,6,7,8,9,10,11}, 0)), IF( DATEDIF($B6, TODAY(), "M") + 1 >= COLUMN(J:J) - 5, INDEX('Most Recent Import'!$F6:$Q6, 1, MATCH(DATEDIF($B6, TODAY(), "M") + 1 - (COLUMN(J:J) - 5), {0,1,2,3,4,5,6,7,8,9,10,11}, 0)), "" ) )} -> 6 | K6: {=IF( DATEDIF($B6, TODAY(), "M") >= 11, INDEX('Most Recent Import'!$F6:$Q6, 1, MATCH(11 - (COLUMN(K:K) - 5), {0,1,2,3,4,5,6,7,8,9,10,11}, 0)), IF( DATEDIF($B6, TODAY(), "M") + 1 >= COLUMN(K:K) - 5, INDEX('Most Recent Import'!$F6:$Q6, 1, MATCH(DATEDIF($B6, TODAY(), "M") + 1 - (COLUMN(K:K) - 5), {0,1,2,3,4,5,6,7,8,9,10,11}, 0)), "" ) )} -> 4 | L6: {=IF( DATEDIF($B6, TODAY(), "M") >= 11, INDEX('Most Recent Import'!$F6:$Q6, 1, MATCH(11 - (COLUMN(L:L) - 5), {0,1,2,3,4,5,6,7,8,9,10,11}, 0)), IF( DATEDIF($B6, TODAY(), "M") + 1 >= COLUMN(L:L) - 5, INDEX('Most Recent Import'!$F6:$Q6, 1, MATCH(DATEDIF($B6, TODAY(), "M") + 1 - (COLUMN(L:L) - 5), {0,1,2,3,4,5,6,7,8,9,10,11}, 0)), "" ) )} -> 6 | M6: {=IF( DATEDIF($B6, TODAY(), "M") >= 11, INDEX('Most Recent Import'!$F6:$Q6, 1, MATCH(11 - (COLUMN(M:M) - 5), {0,1,2,3,4,5,6,7,8,9,10,11}, 0)), IF( DATEDIF($B6, TODAY(), "M") + 1 >= COLUMN(M:M) - 5, INDEX('Most Recent Import'!$F6:$Q6, 1, MATCH(DATEDIF($B6, TODAY(), "M") + 1 - (COLUMN(M:M) - 5), {0,1,2,3,4,5,6,7,8,9,10,11}, 0)), "" ) )} -> 5 | N6: {=IF( DATEDIF($B6, TODAY(), "M") >= 11, INDEX('Most Recent Import'!$F6:$Q6, 1, MATCH(11 - (COLUMN(N:N) - 5), {0,1,2,3,4,5,6,7,8,9,10,11}, 0)), IF( DATEDIF($B6, TODAY(), "M") + 1 >= COLUMN(N:N) - 5, INDEX('Most Recent Import'!$F6:$Q6, 1, MATCH(DATEDIF($B6, TODAY(), "M") + 1 - (COLUMN(N:N) - 5), {0,1,2,3,4,5,6,7,8,9,10,11}, 0)), "" ) )} -> 3 | O6: {=IF( DATEDIF($B6, TODAY(), "M") >= 11, INDEX('Most Recent Import'!$F6:$Q6, 1, MATCH(11 - (COLUMN(O:O) - 5), {0,1,2,3,4,5,6,7,8,9,10,11}, 0)), IF( DATEDIF($B6, TODAY(), "M") + 1 >= COLUMN(O:O) - 5, INDEX('Most Recent Import'!$F6:$Q6, 1, MATCH(DATEDIF($B6, TODAY(), "M") + 1 - (COLUMN(O:O) - 5), {0,1,2,3,4,5,6,7,8,9,10,11}, 0)), "" ) )} -> 6 | P6: {=IF( DATEDIF($B6, TODAY(), "M") >= 11, INDEX('Most Recent Import'!$F6:$Q6, 1, MATCH(11 - (COLUMN(P:P) - 5), {0,1,2,3,4,5,6,7,8,9,10,11}, 0)), IF( DATEDIF($B6, TODAY(), "M") + 1 >= COLUMN(P:P) - 5, INDEX('Most Recent Import'!$F6:$Q6, 1, MATCH(DATEDIF($B6, TODAY(), "M") + 1 - (COLUMN(P:P) - 5), {0,1,2,3,4,5,6,7,8,9,10,11}, 0)), "" ) )} -> 2
A7: ='Most Recent Import'!A7 -> gitlab | B7: =IF(ISBLANK(A7), "", DATE(LEFT('Most Recent Import'!C7, 4), RIGHT('Most Recent Import'!C7, 2), 1)) -> 45078 | C7: ='Most Recent Import'!B7 -> 25000 | D7: ='Most Recent Import'!D7 -> 4 | E7: {=IF( DATEDIF($B7, TODAY(), "M") >= 11, INDEX('Most Recent Import'!$F7:$Q7, 1, MATCH(11 - (COLUMN(E:E) - 5), {0,1,2,3,4,5,6,7,8,9,10,11}, 0)), IF( DATEDIF($B7, TODAY(), "M") + 1 >= COLUMN(E:E) - 5, INDEX('Most Recent Import'!$F7:$Q7, 1, MATCH(DATEDIF($B7, TODAY(), "M") + 1 - (COLUMN(E:E) - 5), {0,1,2,3,4,5,6,7,8,9,10,11}, 0)), "" ) )} -> 0 | F7: {=IF( DATEDIF($B7, TODAY(), "M") >= 11, INDEX('Most Recent Import'!$F7:$Q7, 1, MATCH(11 - (COLUMN(F:F) - 5), {0,1,2,3,4,5,6,7,8,9,10,11}, 0)), IF( DATEDIF($B7, TODAY(), "M") + 1 >= COLUMN(F:F) - 5, INDEX('Most Recent Import'!$F7:$Q7, 1, MATCH(DATEDIF($B7, TODAY(), "M") + 1 - (COLUMN(F:F) - 5), {0,1,2,3,4,5,6,7,8,9,10,11}, 0)), "" ) )} -> 0 | G7: {=IF( DATEDIF($B7, TODAY(), "M") >= 11, INDEX('Most Recent Import'!$F7:$Q7, 1, MATCH(11 - (COLUMN(G:G) - 5), {0,1,2,3,4,5,6,7,8,9,10,11}, 0)), IF( DATEDIF($B7, TODAY(), "M") + 1 >= COLUMN(G:G) - 5, INDEX('Most Recent Import'!$F7:$Q7, 1, MATCH(DATEDIF($B7, TODAY(), "M") + 1 - (COLUMN(G:G) - 5), {0,1,2,3,4,5,6,7,8,9,10,11}, 0)), "" ) )} -> 0 | H7: {=IF( DATEDIF($B7, TODAY(), "M") >= 11, INDEX('Most Recent Import'!$F7:$Q7, 1, MATCH(11 - (COLUMN(H:H) - 5), {0,1,2,3,4,5,6,7,8,9,10,11}, 0)), IF( DATEDIF($B7, TODAY(), "M") + 1 >= COLUMN(H:H) - 5, INDEX('Most Recent Import'!$F7:$Q7, 1, MATCH(DATEDIF($B7, TODAY(), "M") + 1 - (COLUMN(H:H) - 5), {0,1,2,3,4,5,6,7,8,9,10,11}, 0)), "" ) )} -> 0 | I7: {=IF( DATEDIF($B7, TODAY(), "M") >= 11, INDEX('Most Recent Import'!$F7:$Q7, 1, MATCH(11 - (COLUMN(I:I) - 5), {0,1,2,3,4,5,6,7,8,9,10,11}, 0)), IF( DATEDIF($B7, TODAY(), "M") + 1 >= COLUMN(I:I) - 5, INDEX('Most Recent Import'!$F7:$Q7, 1, MATCH(DATEDIF($B7, TODAY(), "M") + 1 - (COLUMN(I:I) - 5), {0,1,2,3,4,5,6,7,8,9,10,11}, 0)), "" ) )} -> 5 | J7: {=IF( DATEDIF($B7, TODAY(), "M") >= 11, INDEX('Most Recent Import'!$F7:$Q7, 1, MATCH(11 - (COLUMN(J:J) - 5), {0,1,2,3,4,5,6,7,8,9,10,11}, 0)), IF( DATEDIF($B7, TODAY(), "M") + 1 >= COLUMN(J:J) - 5, INDEX('Most Recent Import'!$F7:$Q7, 1, MATCH(DATEDIF($B7, TODAY(), "M") + 1 - (COLUMN(J:J) - 5), {0,1,2,3,4,5,6,7,8,9,10,11}, 0)), "" ) )} -> 4 | K7: {=IF( DATEDIF($B7, TODAY(), "M") >= 11, INDEX('Most Recent Import'!$F7:$Q7, 1, MATCH(11 - (COLUMN(K:K) - 5), {0,1,2,3,4,5,6,7,8,9,10,11}, 0)), IF( DATEDIF($B7, TODAY(), "M") + 1 >= COLUMN(K:K) - 5, INDEX('Most Recent Import'!$F7:$Q7, 1, MATCH(DATEDIF($B7, TODAY(), "M") + 1 - (COLUMN(K:K) - 5), {0,1,2,3,4,5,6,7,8,9,10,11}, 0)), "" ) )} -> 3 | L7: {=IF( DATEDIF($B7, TODAY(), "M") >= 11, INDEX('Most Recent Import'!$F7:$Q7, 1, MATCH(11 - (COLUMN(L:L) - 5), {0,1,2,3,4,5,6,7,8,9,10,11}, 0)), IF( DATEDIF($B7, TODAY(), "M") + 1 >= COLUMN(L:L) - 5, INDEX('Most Recent Import'!$F7:$Q7, 1, MATCH(DATEDIF($B7, TODAY(), "M") + 1 - (COLUMN(L:L) - 5), {0,1,2,3,4,5,6,7,8,9,10,11}, 0)), "" ) )} -> 2 | M7: {=IF( DATEDIF($B7, TODAY(), "M") >= 11, INDEX('Most Recent Import'!$F7:$Q7, 1, MATCH(11 - (COLUMN(M:M) - 5), {0,1,2,3,4,5,6,7,8,9,10,11}, 0)), IF( DATEDIF($B7, TODAY(), "M") + 1 >= COLUMN(M:M) - 5, INDEX('Most Recent Import'!$F7:$Q7, 1, MATCH(DATEDIF($B7, TODAY(), "M") + 1 - (COLUMN(M:M) - 5), {0,1,2,3,4,5,6,7,8,9,10,11}, 0)), "" ) )} -> 3 | N7: {=IF( DATEDIF($B7, TODAY(), "M") >= 11, INDEX('Most Recent Import'!$F7:$Q7, 1, MATCH(11 - (COLUMN(N:N) - 5), {0,1,2,3,4,5,6,7,8,9,10,11}, 0)), IF( DATEDIF($B7, TODAY(), "M") + 1 >= COLUMN(N:N) - 5, INDEX('Most Recent Import'!$F7:$Q7, 1, MATCH(DATEDIF($B7, TODAY(), "M") + 1 - (COLUMN(N:N) - 5), {0,1,2,3,4,5,6,7,8,9,10,11}, 0)), "" ) )} -> 9 | O7: {=IF( DATEDIF($B7, TODAY(), "M") >= 11, INDEX('Most Recent Import'!$F7:$Q7, 1, MATCH(11 - (COLUMN(O:O) - 5), {0,1,2,3,4,5,6,7,8,9,10,11}, 0)), IF( DATEDIF($B7, TODAY(), "M") + 1 >= COLUMN(O:O) - 5, INDEX('Most Recent Import'!$F7:$Q7, 1, MATCH(DATEDIF($B7, TODAY(), "M") + 1 - (COLUMN(O:O) - 5), {0,1,2,3,4,5,6,7,8,9,10,11}, 0)), "" ) )} -> 8 | P7: {=IF( DATEDIF($B7, TODAY(), "M") >= 11, INDEX('Most Recent Import'!$F7:$Q7, 1, MATCH(11 - (COLUMN(P:P) - 5), {0,1,2,3,4,5,6,7,8,9,10,11}, 0)), IF( DATEDIF($B7, TODAY(), "M") + 1 >= COLUMN(P:P) - 5, INDEX('Most Recent Import'!$F7:$Q7, 1, MATCH(DATEDIF($B7, TODAY(), "M") + 1 - (COLUMN(P:P) - 5), {0,1,2,3,4,5,6,7,8,9,10,11}, 0)), "" ) )} -> 10
A8: ='Most Recent Import'!A8 -> chegg | B8: =IF(ISBLANK(A8), "", DATE(LEFT('Most Recent Import'!C8, 4), RIGHT('Most Recent Import'!C8, 2), 1)) -> 45139 | C8: ='Most Recent Import'!B8 -> 25000 | D8: ='Most Recent Import'!D8 -> 7 | E8: {=IF( DATEDIF($B8, TODAY(), "M") >= 11, INDEX('Most Recent Import'!$F8:$Q8, 1, MATCH(11 - (COLUMN(E:E) - 5), {0,1,2,3,4,5,6,7,8,9,10,11}, 0)), IF( DATEDIF($B8, TODAY(), "M") + 1 >= COLUMN(E:E) - 5, INDEX('Most Recent Import'!$F8:$Q8, 1, MATCH(DATEDIF($B8, TODAY(), "M") + 1 - (COLUMN(E:E) - 5), {0,1,2,3,4,5,6,7,8,9,10,11}, 0)), "" ) )} -> 0 | F8: {=IF( DATEDIF($B8, TODAY(), "M") >= 11, INDEX('Most Recent Import'!$F8:$Q8, 1, MATCH(11 - (COLUMN(F:F) - 5), {0,1,2,3,4,5,6,7,8,9,10,11}, 0)), IF( DATEDIF($B8, TODAY(), "M") + 1 >= COLUMN(F:F) - 5, INDEX('Most Recent Import'!$F8:$Q8, 1, MATCH(DATEDIF($B8, TODAY(), "M") + 1 - (COLUMN(F:F) - 5), {0,1,2,3,4,5,6,7,8,9,10,11}, 0)), "" ) )} -> 0 | G8: {=IF( DATEDIF($B8, TODAY(), "M") >= 11, INDEX('Most Recent Import'!$F8:$Q8, 1, MATCH(11 - (COLUMN(G:G) - 5), {0,1,2,3,4,5,6,7,8,9,10,11}, 0)), IF( DATEDIF($B8, TODAY(), "M") + 1 >= COLUMN(G:G) - 5, INDEX('Most Recent Import'!$F8:$Q8, 1, MATCH(DATEDIF($B8, TODAY(), "M") + 1 - (COLUMN(G:G) - 5), {0,1,2,3,4,5,6,7,8,9,10,11}, 0)), "" ) )} -> 0 | H8: {=IF( DATEDIF($B8, TODAY(), "M") >= 11, INDEX('Most Recent Import'!$F8:$Q8, 1, MATCH(11 - (COLUMN(H:H) - 5), {0,1,2,3,4,5,6,7,8,9,10,11}, 0)), IF( DATEDIF($B8, TODAY(), "M") + 1 >= COLUMN(H:H) - 5, INDEX('Most Recent Import'!$F8:$Q8, 1, MATCH(DATEDIF($B8, TODAY(), "M") + 1 - (COLUMN(H:H) - 5), {0,1,2,3,4,5,6,7,8,9,10,11}, 0)), "" ) )} -> 0 | I8: {=IF( DATEDIF($B8, TODAY(), "M") >= 11, INDEX('Most Recent Import'!$F8:$Q8, 1, MATCH(11 - (COLUMN(I:I) - 5), {0,1,2,3,4,5,6,7,8,9,10,11}, 0)), IF( DATEDIF($B8, TODAY(), "M") + 1 >= COLUMN(I:I) - 5, INDEX('Most Recent Import'!$F8:$Q8, 1, MATCH(DATEDIF($B8, TODAY(), "M") + 1 - (COLUMN(I:I) - 5), {0,1,2,3,4,5,6,7,8,9,10,11}, 0)), "" ) )} -> 1 | J8: {=IF( DATEDIF($B8, TODAY(), "M") >= 11, INDEX('Most Recent Import'!$F8:$Q8, 1, MATCH(11 - (COLUMN(J:J) - 5), {0,1,2,3,4,5,6,7,8,9,10,11}, 0)), IF( DATEDIF($B8, TODAY(), "M") + 1 >= COLUMN(J:J) - 5, INDEX('Most Recent Import'!$F8:$Q8, 1, MATCH(DATEDIF($B8, TODAY(), "M") + 1 - (COLUMN(J:J) - 5), {0,1,2,3,4,5,6,7,8,9,10,11}, 0)), "" ) )} -> 7 | K8: {=IF( DATEDIF($B8, TODAY(), "M") >= 11, INDEX('Most Recent Import'!$F8:$Q8, 1, MATCH(11 - (COLUMN(K:K) - 5), {0,1,2,3,4,5,6,7,8,9,10,11}, 0)), IF( DATEDIF($B8, TODAY(), "M") + 1 >= COLUMN(K:K) - 5, INDEX('Most Recent Import'!$F8:$Q8, 1, MATCH(DATEDIF($B8, TODAY(), "M") + 1 - (COLUMN(K:K) - 5), {0,1,2,3,4,5,6,7,8,9,10,11}, 0)), "" ) )} -> 1 | L8: {=IF( DATEDIF($B8, TODAY(), "M") >= 11, INDEX('Most Recent Import'!$F8:$Q8, 1, MATCH(11 - (COLUMN(L:L) - 5), {0,1,2,3,4,5,6,7,8,9,10,11}, 0)), IF( DATEDIF($B8, TODAY(), "M") + 1 >= COLUMN(L:L) - 5, INDEX('Most Recent Import'!$F8:$Q8, 1, MATCH(DATEDIF($B8, TODAY(), "M") + 1 - (COLUMN(L:L) - 5), {0,1,2,3,4,5,6,7,8,9,10,11}, 0)), "" ) )} -> 4 | M8: {=IF( DATEDIF($B8, TODAY(), "M") >= 11, INDEX('Most Recent Import'!$F8:$Q8, 1, MATCH(11 - (COLUMN(M:M) - 5), {0,1,2,3,4,5,6,7,8,9,10,11}, 0)), IF( DATEDIF($B8, TODAY(), "M") + 1 >= COLUMN(M:M) - 5, INDEX('Most Recent Import'!$F8:$Q8, 1, MATCH(DATEDIF($B8, TODAY(), "M") + 1 - (COLUMN(M:M) - 5), {0,1,2,3,4,5,6,7,8,9,10,11}, 0)), "" ) )} -> 5 | N8: {=IF( DATEDIF($B8, TODAY(), "M") >= 11, INDEX('Most Recent Import'!$F8:$Q8, 1, MATCH(11 - (COLUMN(N:N) - 5), {0,1,2,3,4,5,6,7,8,9,10,11}, 0)), IF( DATEDIF($B8, TODAY(), "M") + 1 >= COLUMN(N:N) - 5, INDEX('Most Recent Import'!$F8:$Q8, 1, MATCH(DATEDIF($B8, TODAY(), "M") + 1 - (COLUMN(N:N) - 5), {0,1,2,3,4,5,6,7,8,9,10,11}, 0)), "" ) )} -> 4 | O8: {=IF( DATEDIF($B8, TODAY(), "M") >= 11, INDEX('Most Recent Import'!$F8:$Q8, 1, MATCH(11 - (COLUMN(O:O) - 5), {0,1,2,3,4,5,6,7,8,9,10,11}, 0)), IF( DATEDIF($B8, TODAY(), "M") + 1 >= COLUMN(O:O) - 5, INDEX('Most Recent Import'!$F8:$Q8, 1, MATCH(DATEDIF($B8, TODAY(), "M") + 1 - (COLUMN(O:O) - 5), {0,1,2,3,4,5,6,7,8,9,10,11}, 0)), "" ) )} -> 0 | P8: {=IF( DATEDIF($B8, TODAY(), "M") >= 11, INDEX('Most Recent Import'!$F8:$Q8, 1, MATCH(11 - (COLUMN(P:P) - 5), {0,1,2,3,4,5,6,7,8,9,10,11}, 0)), IF( DATEDIF($B8, TODAY(), "M") + 1 >= COLUMN(P:P) - 5, INDEX('Most Recent Import'!$F8:$Q8, 1, MATCH(DATEDIF($B8, TODAY(), "M") + 1 - (COLUMN(P:P) - 5), {0,1,2,3,4,5,6,7,8,9,10,11}, 0)), "" ) )} -> 3
